Workbook
Name Customer_ID: #REF!
Name GaugeHeader: #REF!
Name MekkoHeader: #REF!
Name Month: #REF!
Name OrgChartHeader: #REF!
Name RadialBarChartHeader: #REF!
Name raphic5: #REF!
Name RingHeader: #REF!
Name rngGreenColor: #REF!
Name rngPlanColor: #REF!
Name rngRedColor: #REF!
Name rngWFConnectorsColor: #REF!
Name rngWFGreenColor: #REF!
Name rngWFRedColor: #REF!
Name rngWFStarEndColor: #REF!
Name rngZLColor: #REF!
Name SalesFunnel2Header: #REF!
Name SalesFunnelHeader: #REF!
Name SF2_F: #REF!
Name TrafficLightHeader: #REF!
Name VAH_F1: #REF!
Name VAH_F2: #REF!
Name VarianceActualHorizontalHeader: #REF!
Name VarianceHeader: #REF!
Name WaterFallHeader: #REF!
Name WindRoseHeader: #REF!

Sheet Templates >

Sheet Final demand(2)
B2: Final demand changes (consumption, govt, etc) | H2: CVF_lower | I2: =1/3 -> 0.33333333 | J2: hh
B3: Fields with * must be specified manually or filled in automatically by selecting values in other columns | H3: 2 | I3: =1/3 -> 0.33333333 | J3: gov
B5: Country | C5: Country ISO* | F5: Product | G5: Product code* | H5: Final demand category | I5: FD code* | J5: Type* | K5: Comments
B6: Italy | C6: =_xlfn.IFNA(INDEX('[1]Country list'!$A$2:$A$166,MATCH(B6,'[1]Country list'!$B$2:$B$166,0)),"") -> ITA | F6: ALL | G6: =_xlfn.IFNA(INDEX('[1]Sector list'!$A$2:$A$122,MATCH(F6,'[1]Sector list'!$B$2:$B$122,0)),"") -> ALL | H6: Household final consumption P.3h | I6: =_xlfn.IFNA(INDEX('[1]FD list'!$A$2:$A$122,MATCH(H6,'[1]FD list'!$B$2:$B$122,0)),"") -> FD_1 | J6: rel-b | K6: << Decrease final demand (HH consumption) 3% for all products in Italy
C7: ITA | F7: Pork | G7: =_xlfn.IFNA(INDEX('[1]Sector list'!$A$2:$A$122,MATCH(F7,'[1]Sector list'!$B$2:$B$122,0)),"") -> 43 | H7: ALL | I7: =_xlfn.IFNA(INDEX('[1]FD list'!$A$2:$A$122,MATCH(H7,'[1]FD list'!$B$2:$B$122,0)),"") -> ALL | J7: rel-b | K7: << Increase final demand (across all demand categories) for pork in Italy by 12% (if zero stays zero)
B8: Germany | C8: =_xlfn.IFNA(INDEX('[1]Country list'!$A$2:$A$166,MATCH(B8,'[1]Country list'!$B$2:$B$166,0)),"") -> DEU | G8: 1-23 | I8: FD_1 | J8: abs-b | K8: << Increase demand in Germany for all agricultural sectors (1-23), only for consumer demand; try NOT to use negative values as it might create issues
B9: Malawi | C9: =_xlfn.IFNA(INDEX('[1]Country list'!$A$2:$A$166,MATCH(B9,'[1]Country list'!$B$2:$B$166,0)),"") -> MWI | F9: Building construction | G9: =_xlfn.IFNA(INDEX('[1]Sector list'!$A$2:$A$122,MATCH(F9,'[1]Sector list'!$B$2:$B$122,0)),"") -> 98 | H9: Gross fixed capital formation P.51 | I9: =_xlfn.IFNA(INDEX('[1]FD list'!$A$2:$A$122,MATCH(H9,'[1]FD list'!$B$2:$B$122,0)),"") -> FD_4 | J9: rel-b | K9: << Directly decrease investment (GFCF) demand for construction sector in Malawi with 1%; NOTE: if you want to do INVESTMENT BY the sector IT SHOULD NOT BE DONE HERE
C13: REG_exp | E13: REG_imp | G13: TRAD_COMM | I13: PROD_COMM (only FD) | J13: Current options: rel-b and abs-b
B14: Start in the next line >>
B15: Producing country | C15: Producing country ISO* | D15: Consuming country | E15: Consuming country ISO* | F15: Product | G15: Product code* | H15: Final demand category | I15: FD code* | J15: Type* | K15: Comments | L15: 2019 | M15: 2020 | N15: 2021 | O15: 2022 | P15: 2023 | Q15: 2024 | R15: 2025 | S15: 2026 | T15: 2027 | U15: 2028 | V15: 2029 | W15: 2030 | X15: 2031 | Y15: 2032 | Z15: 2033 | AA15: 2034 | AB15: 2035 | AC15: 2036 | AD15: 2037 | AE15: 2038 | AF15: 2039 | AG15: 2040 | AH15: 2041 | AI15: 2042 | AJ15: 2043 | AK15: 2044 | AL15: 2045 | AM15: 2046 | AN15: 2047 | AO15: 2048 | AP15: 2049 | AQ15: 2050
C16: SEP | E16: SEP | F16: ALL | G16: ALL | H16: Household final consumption P.3h | I16: FD_1 | J16: abs-b | K16: =SUM(X16:AL16)/1000000 -> 0.34262129 | X16: =VLOOKUP($C16,'MSET pivots'!$B$4:$H$14,$H$3,FALSE)*1000000*$I$2*'MSET pivots'!E$65 -> 11420.881 | Y16: =VLOOKUP($C16,'MSET pivots'!$B$4:$H$14,$H$3,FALSE)*1000000*$I2*'MSET pivots'!F$65 -> 13052.386 | Z16: =VLOOKUP($C16,'MSET pivots'!$B$4:$H$14,$H$3,FALSE)*1000000*$I2*'MSET pivots'!G$65 -> 14683.892 | AA16: =VLOOKUP($C16,'MSET pivots'!$B$4:$H$14,$H$3,FALSE)*1000000*$I2*'MSET pivots'!H$65 -> 16315.397 | AB16: =VLOOKUP($C16,'MSET pivots'!$B$4:$H$14,$H$3,FALSE)*1000000*$I2*'MSET pivots'!I$65 -> 17946.903 | AC16: =VLOOKUP($C16,'MSET pivots'!$B$4:$H$14,$H$3,FALSE)*1000000*$I2*'MSET pivots'!J$65 -> 19578.408 | AD16: =VLOOKUP($C16,'MSET pivots'!$B$4:$H$14,$H$3,FALSE)*1000000*$I2*'MSET pivots'!K$65 -> 21209.914 | AE16: =VLOOKUP($C16,'MSET pivots'!$B$4:$H$14,$H$3,FALSE)*1000000*$I2*'MSET pivots'!L$65 -> 22841.419 | AF16: =VLOOKUP($C16,'MSET pivots'!$B$4:$H$14,$H$3,FALSE)*1000000*$I2*'MSET pivots'!M$65 -> 24472.925 | ... AL16: =VLOOKUP($C16,'MSET pivots'!$B$4:$H$14,$H$3,FALSE)*1000000*$I2*'MSET pivots'!S$65 -> 34261.957
C17: SEP | E17: SEP | F17: ALL | G17: ALL | H17: Government final consumption P.3g | I17: FD_3 | J17: abs-b | K17: =SUM(X17:AL17)/1000000 -> 0.34262129 | X17: =VLOOKUP($C17,'MSET pivots'!$B$4:$H$14,$H$3,FALSE)*1000000*$I$3*'MSET pivots'!E$65 -> 11420.881 | Y17: =VLOOKUP($C17,'MSET pivots'!$B$4:$H$14,$H$3,FALSE)*1000000*$I3*'MSET pivots'!F$65 -> 13052.386 | Z17: =VLOOKUP($C17,'MSET pivots'!$B$4:$H$14,$H$3,FALSE)*1000000*$I3*'MSET pivots'!G$65 -> 14683.892 | AA17: =VLOOKUP($C17,'MSET pivots'!$B$4:$H$14,$H$3,FALSE)*1000000*$I3*'MSET pivots'!H$65 -> 16315.397 | AB17: =VLOOKUP($C17,'MSET pivots'!$B$4:$H$14,$H$3,FALSE)*1000000*$I3*'MSET pivots'!I$65 -> 17946.903 | AC17: =VLOOKUP($C17,'MSET pivots'!$B$4:$H$14,$H$3,FALSE)*1000000*$I3*'MSET pivots'!J$65 -> 19578.408 | AD17: =VLOOKUP($C17,'MSET pivots'!$B$4:$H$14,$H$3,FALSE)*1000000*$I3*'MSET pivots'!K$65 -> 21209.914 | AE17: =VLOOKUP($C17,'MSET pivots'!$B$4:$H$14,$H$3,FALSE)*1000000*$I3*'MSET pivots'!L$65 -> 22841.419 | AF17: =VLOOKUP($C17,'MSET pivots'!$B$4:$H$14,$H$3,FALSE)*1000000*$I3*'MSET pivots'!M$65 -> 24472.925 | ... AL17: =VLOOKUP($C17,'MSET pivots'!$B$4:$H$14,$H$3,FALSE)*1000000*$I3*'MSET pivots'!S$65 -> 34261.957
C18: AFR | E18: AFR | F18: ALL | G18: ALL | H18: Household final consumption P.3h | I18: FD_1 | J18: abs-b | K18: =SUM(X18:AL18)/1000000 -> 0.35655058 | X18: =VLOOKUP($C18,'MSET pivots'!$B$4:$H$14,$H$3,FALSE)*1000000*$I$2*'MSET pivots'!E$65 -> 11885.198 | Y18: =VLOOKUP($C18,'MSET pivots'!$B$4:$H$14,$H$3,FALSE)*1000000*$I$2*'MSET pivots'!F$65 -> 13583.032 | Z18: =VLOOKUP($C18,'MSET pivots'!$B$4:$H$14,$H$3,FALSE)*1000000*$I$2*'MSET pivots'!G$65 -> 15280.866 | AA18: =VLOOKUP($C18,'MSET pivots'!$B$4:$H$14,$H$3,FALSE)*1000000*$I$2*'MSET pivots'!H$65 -> 16978.701 | AB18: =VLOOKUP($C18,'MSET pivots'!$B$4:$H$14,$H$3,FALSE)*1000000*$I$2*'MSET pivots'!I$65 -> 18676.535 | AC18: =VLOOKUP($C18,'MSET pivots'!$B$4:$H$14,$H$3,FALSE)*1000000*$I$2*'MSET pivots'!J$65 -> 20374.37 | AD18: =VLOOKUP($C18,'MSET pivots'!$B$4:$H$14,$H$3,FALSE)*1000000*$I$2*'MSET pivots'!K$65 -> 22072.204 | AE18: =VLOOKUP($C18,'MSET pivots'!$B$4:$H$14,$H$3,FALSE)*1000000*$I$2*'MSET pivots'!L$65 -> 23770.039 | ... AL18: =VLOOKUP($C18,'MSET pivots'!$B$4:$H$14,$H$3,FALSE)*1000000*$I$2*'MSET pivots'!S$65 -> 35654.88
C19: AFR | E19: AFR | F19: ALL | G19: ALL | H19: Government final consumption P.3g | I19: FD_3 | J19: abs-b | K19: =SUM(X19:AL19)/1000000 -> 0.35655058 | X19: =VLOOKUP($C19,'MSET pivots'!$B$4:$H$14,$H$3,FALSE)*1000000*$I$3*'MSET pivots'!E$65 -> 11885.198 | Y19: =VLOOKUP($C19,'MSET pivots'!$B$4:$H$14,$H$3,FALSE)*1000000*$I$3*'MSET pivots'!F$65 -> 13583.032 | Z19: =VLOOKUP($C19,'MSET pivots'!$B$4:$H$14,$H$3,FALSE)*1000000*$I$3*'MSET pivots'!G$65 -> 15280.866 | AA19: =VLOOKUP($C19,'MSET pivots'!$B$4:$H$14,$H$3,FALSE)*1000000*$I$3*'MSET pivots'!H$65 -> 16978.701 | AB19: =VLOOKUP($C19,'MSET pivots'!$B$4:$H$14,$H$3,FALSE)*1000000*$I$3*'MSET pivots'!I$65 -> 18676.535 | AC19: =VLOOKUP($C19,'MSET pivots'!$B$4:$H$14,$H$3,FALSE)*1000000*$I$3*'MSET pivots'!J$65 -> 20374.37 | AD19: =VLOOKUP($C19,'MSET pivots'!$B$4:$H$14,$H$3,FALSE)*1000000*$I$3*'MSET pivots'!K$65 -> 22072.204 | AE19: =VLOOKUP($C19,'MSET pivots'!$B$4:$H$14,$H$3,FALSE)*1000000*$I$3*'MSET pivots'!L$65 -> 23770.039 | ... AL19: =VLOOKUP($C19,'MSET pivots'!$B$4:$H$14,$H$3,FALSE)*1000000*$I$3*'MSET pivots'!S$65 -> 35654.88
C20: LAC | E20: LAC | F20: ALL | G20: ALL | H20: Household final consumption P.3h | I20: FD_1 | J20: abs-b | K20: =SUM(X20:AL20)/1000000 -> 0.26441491 | X20: =VLOOKUP($C20,'MSET pivots'!$B$4:$H$14,$H$3,FALSE)*1000000*$I$2*'MSET pivots'!E$65 -> 8813.9627 | Y20: =VLOOKUP($C20,'MSET pivots'!$B$4:$H$14,$H$3,FALSE)*1000000*$I$2*'MSET pivots'!F$65 -> 10073.062 | Z20: =VLOOKUP($C20,'MSET pivots'!$B$4:$H$14,$H$3,FALSE)*1000000*$I$2*'MSET pivots'!G$65 -> 11332.162 | AA20: =VLOOKUP($C20,'MSET pivots'!$B$4:$H$14,$H$3,FALSE)*1000000*$I$2*'MSET pivots'!H$65 -> 12591.262 | AB20: =VLOOKUP($C20,'MSET pivots'!$B$4:$H$14,$H$3,FALSE)*1000000*$I$2*'MSET pivots'!I$65 -> 13850.362 | AC20: =VLOOKUP($C20,'MSET pivots'!$B$4:$H$14,$H$3,FALSE)*1000000*$I$2*'MSET pivots'!J$65 -> 15109.461 | AD20: =VLOOKUP($C20,'MSET pivots'!$B$4:$H$14,$H$3,FALSE)*1000000*$I$2*'MSET pivots'!K$65 -> 16368.561 | AE20: =VLOOKUP($C20,'MSET pivots'!$B$4:$H$14,$H$3,FALSE)*1000000*$I$2*'MSET pivots'!L$65 -> 17627.661 | ... AL20: =VLOOKUP($C20,'MSET pivots'!$B$4:$H$14,$H$3,FALSE)*1000000*$I$2*'MSET pivots'!S$65 -> 26441.359
C21: LAC | E21: LAC | F21: ALL | G21: ALL | H21: Government final consumption P.3g | I21: FD_3 | J21: abs-b | K21: =SUM(X21:AL21)/1000000 -> 0.26441491 | X21: =VLOOKUP($C21,'MSET pivots'!$B$4:$H$14,$H$3,FALSE)*1000000*$I$3*'MSET pivots'!E$65 -> 8813.9627 | Y21: =VLOOKUP($C21,'MSET pivots'!$B$4:$H$14,$H$3,FALSE)*1000000*$I$3*'MSET pivots'!F$65 -> 10073.062 | Z21: =VLOOKUP($C21,'MSET pivots'!$B$4:$H$14,$H$3,FALSE)*1000000*$I$3*'MSET pivots'!G$65 -> 11332.162 | AA21: =VLOOKUP($C21,'MSET pivots'!$B$4:$H$14,$H$3,FALSE)*1000000*$I$3*'MSET pivots'!H$65 -> 12591.262 | AB21: =VLOOKUP($C21,'MSET pivots'!$B$4:$H$14,$H$3,FALSE)*1000000*$I$3*'MSET pivots'!I$65 -> 13850.362 | AC21: =VLOOKUP($C21,'MSET pivots'!$B$4:$H$14,$H$3,FALSE)*1000000*$I$3*'MSET pivots'!J$65 -> 15109.461 | AD21: =VLOOKUP($C21,'MSET pivots'!$B$4:$H$14,$H$3,FALSE)*1000000*$I$3*'MSET pivots'!K$65 -> 16368.561 | AE21: =VLOOKUP($C21,'MSET pivots'!$B$4:$H$14,$H$3,FALSE)*1000000*$I$3*'MSET pivots'!L$65 -> 17627.661 | ... AL21: =VLOOKUP($C21,'MSET pivots'!$B$4:$H$14,$H$3,FALSE)*1000000*$I$3*'MSET pivots'!S$65 -> 26441.359
B22: Pakistan | C22: SAS | E22: SAS | F22: ALL | G22: ALL | H22: Household final consumption P.3h | I22: FD_1 | J22: abs-b | K22: =SUM(X22:AL22)/1000000 -> 0.3297289 | W22: ='Preliminary results'!$C$31*1000000*I2 -> 902060.73 | X22: =VLOOKUP($C22,'MSET pivots'!$B$4:$H$14,$H$3,FALSE)*1000000*$I$2*'MSET pivots'!E$65 -> 10991.128 | Y22: =VLOOKUP($C22,'MSET pivots'!$B$4:$H$14,$H$3,FALSE)*1000000*$I$2*'MSET pivots'!F$65 -> 12561.242 | Z22: =VLOOKUP($C22,'MSET pivots'!$B$4:$H$14,$H$3,FALSE)*1000000*$I$2*'MSET pivots'!G$65 -> 14131.356 | AA22: =VLOOKUP($C22,'MSET pivots'!$B$4:$H$14,$H$3,FALSE)*1000000*$I$2*'MSET pivots'!H$65 -> 15701.47 | AB22: =VLOOKUP($C22,'MSET pivots'!$B$4:$H$14,$H$3,FALSE)*1000000*$I$2*'MSET pivots'!I$65 -> 17271.584 | AC22: =VLOOKUP($C22,'MSET pivots'!$B$4:$H$14,$H$3,FALSE)*1000000*$I$2*'MSET pivots'!J$65 -> 18841.698 | AD22: =VLOOKUP($C22,'MSET pivots'!$B$4:$H$14,$H$3,FALSE)*1000000*$I$2*'MSET pivots'!K$65 -> 20411.813 | AE22: =VLOOKUP($C22,'MSET pivots'!$B$4:$H$14,$H$3,FALSE)*1000000*$I$2*'MSET pivots'!L$65 -> 21981.927 | ... AL22: =VLOOKUP($C22,'MSET pivots'!$B$4:$H$14,$H$3,FALSE)*1000000*$I$2*'MSET pivots'!S$65 -> 32972.725
B23: Pakistan | C23: SAS | E23: SAS | F23: ALL | G23: ALL | H23: Government final consumption P.3g | I23: FD_3 | J23: abs-b | K23: =SUM(X23:AL23)/1000000 -> 0.3297289 | W23: ='Preliminary results'!$C$31*1000000*I3 -> 902060.73 | X23: =VLOOKUP($C23,'MSET pivots'!$B$4:$H$14,$H$3,FALSE)*1000000*$I$3*'MSET pivots'!E$65 -> 10991.128 | Y23: =VLOOKUP($C23,'MSET pivots'!$B$4:$H$14,$H$3,FALSE)*1000000*$I$3*'MSET pivots'!F$65 -> 12561.242 | Z23: =VLOOKUP($C23,'MSET pivots'!$B$4:$H$14,$H$3,FALSE)*1000000*$I$3*'MSET pivots'!G$65 -> 14131.356 | AA23: =VLOOKUP($C23,'MSET pivots'!$B$4:$H$14,$H$3,FALSE)*1000000*$I$3*'MSET pivots'!H$65 -> 15701.47 | AB23: =VLOOKUP($C23,'MSET pivots'!$B$4:$H$14,$H$3,FALSE)*1000000*$I$3*'MSET pivots'!I$65 -> 17271.584 | AC23: =VLOOKUP($C23,'MSET pivots'!$B$4:$H$14,$H$3,FALSE)*1000000*$I$3*'MSET pivots'!J$65 -> 18841.698 | AD23: =VLOOKUP($C23,'MSET pivots'!$B$4:$H$14,$H$3,FALSE)*1000000*$I$3*'MSET pivots'!K$65 -> 20411.813 | AE23: =VLOOKUP($C23,'MSET pivots'!$B$4:$H$14,$H$3,FALSE)*1000000*$I$3*'MSET pivots'!L$65 -> 21981.927 | ... AL23: =VLOOKUP($C23,'MSET pivots'!$B$4:$H$14,$H$3,FALSE)*1000000*$I$3*'MSET pivots'!S$65 -> 32972.725
C24: AJN | E24: AJN | F24: ALL | G24: ALL | H24: Government final consumption P.3g | I24: FD_3 | J24: rel-b | K24: =SUM(X24:AL24) -> -0.00027375815 | X24: =VLOOKUP($C24,'MSET pivots'!$J$4:$P$14,'Final demand(2)'!$H$3,FALSE)*'MSET pivots'!E$65 -> -9.1254086e-06 | Y24: =VLOOKUP($C24,'MSET pivots'!$J$4:$P$14,'Final demand(2)'!$H$3,FALSE)*'MSET pivots'!F$65 -> -1.0428999e-05 | Z24: =VLOOKUP($C24,'MSET pivots'!$J$4:$P$14,'Final demand(2)'!$H$3,FALSE)*'MSET pivots'!G$65 -> -1.173259e-05 | AA24: =VLOOKUP($C24,'MSET pivots'!$J$4:$P$14,'Final demand(2)'!$H$3,FALSE)*'MSET pivots'!H$65 -> -1.3036181e-05 | AB24: =VLOOKUP($C24,'MSET pivots'!$J$4:$P$14,'Final demand(2)'!$H$3,FALSE)*'MSET pivots'!I$65 -> -1.4339771e-05 | AC24: =VLOOKUP($C24,'MSET pivots'!$J$4:$P$14,'Final demand(2)'!$H$3,FALSE)*'MSET pivots'!J$65 -> -1.5643362e-05 | AD24: =VLOOKUP($C24,'MSET pivots'!$J$4:$P$14,'Final demand(2)'!$H$3,FALSE)*'MSET pivots'!K$65 -> -1.6946953e-05 | AE24: =VLOOKUP($C24,'MSET pivots'!$J$4:$P$14,'Final demand(2)'!$H$3,FALSE)*'MSET pivots'!L$65 -> -1.8250543e-05 | ... AL24: =VLOOKUP($C24,'MSET pivots'!$J$4:$P$14,'Final demand(2)'!$H$3,FALSE)*'MSET pivots'!S$65 -> -2.7375678e-05
C25: EAS | E25: EAS | F25: ALL | G25: ALL | H25: Government final consumption P.3g | I25: FD_3 | J25: rel-b | K25: =SUM(X25:AL25) -> -0.0001409855 | X25: =VLOOKUP($C25,'MSET pivots'!$J$4:$P$14,'Final demand(2)'!$H$3,FALSE)*'MSET pivots'!E$65 -> -4.6995871e-06 | Y25: =VLOOKUP($C25,'MSET pivots'!$J$4:$P$14,'Final demand(2)'!$H$3,FALSE)*'MSET pivots'!F$65 -> -5.3709365e-06 | Z25: =VLOOKUP($C25,'MSET pivots'!$J$4:$P$14,'Final demand(2)'!$H$3,FALSE)*'MSET pivots'!G$65 -> -6.042286e-06 | AA25: =VLOOKUP($C25,'MSET pivots'!$J$4:$P$14,'Final demand(2)'!$H$3,FALSE)*'MSET pivots'!H$65 -> -6.7136354e-06 | AB25: =VLOOKUP($C25,'MSET pivots'!$J$4:$P$14,'Final demand(2)'!$H$3,FALSE)*'MSET pivots'!I$65 -> -7.3849848e-06 | AC25: =VLOOKUP($C25,'MSET pivots'!$J$4:$P$14,'Final demand(2)'!$H$3,FALSE)*'MSET pivots'!J$65 -> -8.0563343e-06 | AD25: =VLOOKUP($C25,'MSET pivots'!$J$4:$P$14,'Final demand(2)'!$H$3,FALSE)*'MSET pivots'!K$65 -> -8.7276837e-06 | AE25: =VLOOKUP($C25,'MSET pivots'!$J$4:$P$14,'Final demand(2)'!$H$3,FALSE)*'MSET pivots'!L$65 -> -9.3990332e-06 | ... AL25: =VLOOKUP($C25,'MSET pivots'!$J$4:$P$14,'Final demand(2)'!$H$3,FALSE)*'MSET pivots'!S$65 -> -1.4098479e-05
C26: EEA | E26: EEA | F26: ALL | G26: ALL | H26: Government final consumption P.3g | I26: FD_3 | J26: rel-b | K26: =SUM(X26:AL26) -> -0.00029291557 | X26: =VLOOKUP($C26,'MSET pivots'!$J$4:$P$14,'Final demand(2)'!$H$3,FALSE)*'MSET pivots'!E$65 -> -9.7639988e-06 | Y26: =VLOOKUP($C26,'MSET pivots'!$J$4:$P$14,'Final demand(2)'!$H$3,FALSE)*'MSET pivots'!F$65 -> -1.1158814e-05 | Z26: =VLOOKUP($C26,'MSET pivots'!$J$4:$P$14,'Final demand(2)'!$H$3,FALSE)*'MSET pivots'!G$65 -> -1.2553629e-05 | AA26: =VLOOKUP($C26,'MSET pivots'!$J$4:$P$14,'Final demand(2)'!$H$3,FALSE)*'MSET pivots'!H$65 -> -1.3948444e-05 | AB26: =VLOOKUP($C26,'MSET pivots'!$J$4:$P$14,'Final demand(2)'!$H$3,FALSE)*'MSET pivots'!I$65 -> -1.5343259e-05 | AC26: =VLOOKUP($C26,'MSET pivots'!$J$4:$P$14,'Final demand(2)'!$H$3,FALSE)*'MSET pivots'!J$65 -> -1.6738074e-05 | AD26: =VLOOKUP($C26,'MSET pivots'!$J$4:$P$14,'Final demand(2)'!$H$3,FALSE)*'MSET pivots'!K$65 -> -1.813289e-05 | AE26: =VLOOKUP($C26,'MSET pivots'!$J$4:$P$14,'Final demand(2)'!$H$3,FALSE)*'MSET pivots'!L$65 -> -1.9527705e-05 | ... AL26: =VLOOKUP($C26,'MSET pivots'!$J$4:$P$14,'Final demand(2)'!$H$3,FALSE)*'MSET pivots'!S$65 -> -2.9291411e-05
B27: United Kingdom | C27: EUR | E27: EUR | F27: ALL | G27: ALL | H27: Government final consumption P.3g | I27: FD_3 | J27: rel-b | K27: =SUM(X27:AL27) -> -0.00021328804 | W27: =('Preliminary results'!$C$31)/'Baseline govt spend'!$E$51 -> 0.00066729533 | X27: =VLOOKUP($C27,'MSET pivots'!$J$4:$P$14,'Final demand(2)'!$H$3,FALSE)*'MSET pivots'!E$65 -> -7.109708e-06 | Y27: =VLOOKUP($C27,'MSET pivots'!$J$4:$P$14,'Final demand(2)'!$H$3,FALSE)*'MSET pivots'!F$65 -> -8.1253501e-06 | Z27: =VLOOKUP($C27,'MSET pivots'!$J$4:$P$14,'Final demand(2)'!$H$3,FALSE)*'MSET pivots'!G$65 -> -9.1409922e-06 | AA27: =VLOOKUP($C27,'MSET pivots'!$J$4:$P$14,'Final demand(2)'!$H$3,FALSE)*'MSET pivots'!H$65 -> -1.0156634e-05 | AB27: =VLOOKUP($C27,'MSET pivots'!$J$4:$P$14,'Final demand(2)'!$H$3,FALSE)*'MSET pivots'!I$65 -> -1.1172276e-05 | AC27: =VLOOKUP($C27,'MSET pivots'!$J$4:$P$14,'Final demand(2)'!$H$3,FALSE)*'MSET pivots'!J$65 -> -1.2187918e-05 | AD27: =VLOOKUP($C27,'MSET pivots'!$J$4:$P$14,'Final demand(2)'!$H$3,FALSE)*'MSET pivots'!K$65 -> -1.3203561e-05 | AE27: =VLOOKUP($C27,'MSET pivots'!$J$4:$P$14,'Final demand(2)'!$H$3,FALSE)*'MSET pivots'!L$65 -> -1.4219203e-05 | ... AL27: =VLOOKUP($C27,'MSET pivots'!$J$4:$P$14,'Final demand(2)'!$H$3,FALSE)*'MSET pivots'!S$65 -> -2.1328697e-05
C28: MEN | E28: MEN | F28: ALL | G28: ALL | H28: Government final consumption P.3g | I28: FD_3 | J28: rel-b | K28: =SUM(X28:AL28) -> -7.4304334e-05 | X28: =VLOOKUP($C28,'MSET pivots'!$J$4:$P$14,'Final demand(2)'!$H$3,FALSE)*'MSET pivots'!E$65 -> -2.4768483e-06 | Y28: =VLOOKUP($C28,'MSET pivots'!$J$4:$P$14,'Final demand(2)'!$H$3,FALSE)*'MSET pivots'!F$65 -> -2.8306731e-06 | Z28: =VLOOKUP($C28,'MSET pivots'!$J$4:$P$14,'Final demand(2)'!$H$3,FALSE)*'MSET pivots'!G$65 -> -3.184498e-06 | AA28: =VLOOKUP($C28,'MSET pivots'!$J$4:$P$14,'Final demand(2)'!$H$3,FALSE)*'MSET pivots'!H$65 -> -3.5383228e-06 | AB28: =VLOOKUP($C28,'MSET pivots'!$J$4:$P$14,'Final demand(2)'!$H$3,FALSE)*'MSET pivots'!I$65 -> -3.8921477e-06 | AC28: =VLOOKUP($C28,'MSET pivots'!$J$4:$P$14,'Final demand(2)'!$H$3,FALSE)*'MSET pivots'!J$65 -> -4.2459725e-06 | AD28: =VLOOKUP($C28,'MSET pivots'!$J$4:$P$14,'Final demand(2)'!$H$3,FALSE)*'MSET pivots'!K$65 -> -4.5997974e-06 | AE28: =VLOOKUP($C28,'MSET pivots'!$J$4:$P$14,'Final demand(2)'!$H$3,FALSE)*'MSET pivots'!L$65 -> -4.9536223e-06 | ... AL28: =VLOOKUP($C28,'MSET pivots'!$J$4:$P$14,'Final demand(2)'!$H$3,FALSE)*'MSET pivots'!S$65 -> -7.4303962e-06
C29: NAM | E29: NAM | F29: ALL | G29: ALL | H29: Government final consumption P.3g | I29: FD_3 | J29: rel-b | K29: =SUM(X29:AL29) -> -0.00059204867 | X29: =VLOOKUP($C29,'MSET pivots'!$J$4:$P$14,'Final demand(2)'!$H$3,FALSE)*'MSET pivots'!E$65 -> -1.9735252e-05 | Y29: =VLOOKUP($C29,'MSET pivots'!$J$4:$P$14,'Final demand(2)'!$H$3,FALSE)*'MSET pivots'!F$65 -> -2.2554489e-05 | Z29: =VLOOKUP($C29,'MSET pivots'!$J$4:$P$14,'Final demand(2)'!$H$3,FALSE)*'MSET pivots'!G$65 -> -2.5373726e-05 | AA29: =VLOOKUP($C29,'MSET pivots'!$J$4:$P$14,'Final demand(2)'!$H$3,FALSE)*'MSET pivots'!H$65 -> -2.8192963e-05 | AB29: =VLOOKUP($C29,'MSET pivots'!$J$4:$P$14,'Final demand(2)'!$H$3,FALSE)*'MSET pivots'!I$65 -> -3.10122e-05 | AC29: =VLOOKUP($C29,'MSET pivots'!$J$4:$P$14,'Final demand(2)'!$H$3,FALSE)*'MSET pivots'!J$65 -> -3.3831437e-05 | AD29: =VLOOKUP($C29,'MSET pivots'!$J$4:$P$14,'Final demand(2)'!$H$3,FALSE)*'MSET pivots'!K$65 -> -3.6650674e-05 | AE29: =VLOOKUP($C29,'MSET pivots'!$J$4:$P$14,'Final demand(2)'!$H$3,FALSE)*'MSET pivots'!L$65 -> -3.9469911e-05 | ... AL29: =VLOOKUP($C29,'MSET pivots'!$J$4:$P$14,'Final demand(2)'!$H$3,FALSE)*'MSET pivots'!S$65 -> -5.9204571e-05
G42: =_xlfn.IFNA(INDEX('[1]Sector list'!$A$2:$A$122,MATCH(F42,'[1]Sector list'!$B$2:$B$122,0)),"") | I42: =_xlfn.IFNA(INDEX('[1]FD list'!$A$2:$A$122,MATCH(H42,'[1]FD list'!$B$2:$B$122,0)),"")
G43: =_xlfn.IFNA(INDEX('[1]Sector list'!$A$2:$A$122,MATCH(F43,'[1]Sector list'!$B$2:$B$122,0)),"") | I43: =_xlfn.IFNA(INDEX('[1]FD list'!$A$2:$A$122,MATCH(H43,'[1]FD list'!$B$2:$B$122,0)),"")
G44: =_xlfn.IFNA(INDEX('[1]Sector list'!$A$2:$A$122,MATCH(F44,'[1]Sector list'!$B$2:$B$122,0)),"") | I44: =_xlfn.IFNA(INDEX('[1]FD list'!$A$2:$A$122,MATCH(H44,'[1]FD list'!$B$2:$B$122,0)),"")
G45: =_xlfn.IFNA(INDEX('[1]Sector list'!$A$2:$A$122,MATCH(F45,'[1]Sector list'!$B$2:$B$122,0)),"") | I45: =_xlfn.IFNA(INDEX('[1]FD list'!$A$2:$A$122,MATCH(H45,'[1]FD list'!$B$2:$B$122,0)),"")
G46: =_xlfn.IFNA(INDEX('[1]Sector list'!$A$2:$A$122,MATCH(F46,'[1]Sector list'!$B$2:$B$122,0)),"") | I46: =_xlfn.IFNA(INDEX('[1]FD list'!$A$2:$A$122,MATCH(H46,'[1]FD list'!$B$2:$B$122,0)),"")
G47: =_xlfn.IFNA(INDEX('[1]Sector list'!$A$2:$A$122,MATCH(F47,'[1]Sector list'!$B$2:$B$122,0)),"") | I47: =_xlfn.IFNA(INDEX('[1]FD list'!$A$2:$A$122,MATCH(H47,'[1]FD list'!$B$2:$B$122,0)),"")
G48: =_xlfn.IFNA(INDEX('[1]Sector list'!$A$2:$A$122,MATCH(F48,'[1]Sector list'!$B$2:$B$122,0)),"") | I48: =_xlfn.IFNA(INDEX('[1]FD list'!$A$2:$A$122,MATCH(H48,'[1]FD list'!$B$2:$B$122,0)),"")
G49: =_xlfn.IFNA(INDEX('[1]Sector list'!$A$2:$A$122,MATCH(F49,'[1]Sector list'!$B$2:$B$122,0)),"") | I49: =_xlfn.IFNA(INDEX('[1]FD list'!$A$2:$A$122,MATCH(H49,'[1]FD list'!$B$2:$B$122,0)),"")
G50: =_xlfn.IFNA(INDEX('[1]Sector list'!$A$2:$A$122,MATCH(F50,'[1]Sector list'!$B$2:$B$122,0)),"") | I50: =_xlfn.IFNA(INDEX('[1]FD list'!$A$2:$A$122,MATCH(H50,'[1]FD list'!$B$2:$B$122,0)),"")
G51: =_xlfn.IFNA(INDEX('[1]Sector list'!$A$2:$A$122,MATCH(F51,'[1]Sector list'!$B$2:$B$122,0)),"") | I51: =_xlfn.IFNA(INDEX('[1]FD list'!$A$2:$A$122,MATCH(H51,'[1]FD list'!$B$2:$B$122,0)),"")
G52: =_xlfn.IFNA(INDEX('[1]Sector list'!$A$2:$A$122,MATCH(F52,'[1]Sector list'!$B$2:$B$122,0)),"") | I52: =_xlfn.IFNA(INDEX('[1]FD list'!$A$2:$A$122,MATCH(H52,'[1]FD list'!$B$2:$B$122,0)),"")
G53: =_xlfn.IFNA(INDEX('[1]Sector list'!$A$2:$A$122,MATCH(F53,'[1]Sector list'!$B$2:$B$122,0)),"") | I53: =_xlfn.IFNA(INDEX('[1]FD list'!$A$2:$A$122,MATCH(H53,'[1]FD list'!$B$2:$B$122,0)),"")
... G67: =_xlfn.IFNA(INDEX('[1]Sector list'!$A$2:$A$122,MATCH(F67,'[1]Sector list'!$B$2:$B$122,0)),"") | I67: =_xlfn.IFNA(INDEX('[1]FD list'!$A$2:$A$122,MATCH(H67,'[1]FD list'!$B$2:$B$122,0)),"")
I68: =_xlfn.IFNA(INDEX('[1]FD list'!$A$2:$A$122,MATCH(H68,'[1]FD list'!$B$2:$B$122,0)),"")
I69: =_xlfn.IFNA(INDEX('[1]FD list'!$A$2:$A$122,MATCH(H69,'[1]FD list'!$B$2:$B$122,0)),"")
I70: =_xlfn.IFNA(INDEX('[1]FD list'!$A$2:$A$122,MATCH(H70,'[1]FD list'!$B$2:$B$122,0)),"")
I71: =_xlfn.IFNA(INDEX('[1]FD list'!$A$2:$A$122,MATCH(H71,'[1]FD list'!$B$2:$B$122,0)),"")
I72: =_xlfn.IFNA(INDEX('[1]FD list'!$A$2:$A$122,MATCH(H72,'[1]FD list'!$B$2:$B$122,0)),"")
I73: =_xlfn.IFNA(INDEX('[1]FD list'!$A$2:$A$122,MATCH(H73,'[1]FD list'!$B$2:$B$122,0)),"")
I74: =_xlfn.IFNA(INDEX('[1]FD list'!$A$2:$A$122,MATCH(H74,'[1]FD list'!$B$2:$B$122,0)),"")
I75: =_xlfn.IFNA(INDEX('[1]FD list'!$A$2:$A$122,MATCH(H75,'[1]FD list'!$B$2:$B$122,0)),"")
I76: =_xlfn.IFNA(INDEX('[1]FD list'!$A$2:$A$122,MATCH(H76,'[1]FD list'!$B$2:$B$122,0)),"")
I77: =_xlfn.IFNA(INDEX('[1]FD list'!$A$2:$A$122,MATCH(H77,'[1]FD list'!$B$2:$B$122,0)),"")
I78: =_xlfn.IFNA(INDEX('[1]FD list'!$A$2:$A$122,MATCH(H78,'[1]FD list'!$B$2:$B$122,0)),"")
I79: =_xlfn.IFNA(INDEX('[1]FD list'!$A$2:$A$122,MATCH(H79,'[1]FD list'!$B$2:$B$122,0)),"")
... I95: =_xlfn.IFNA(INDEX('[1]FD list'!$A$2:$A$122,MATCH(H95,'[1]FD list'!$B$2:$B$122,0)),"")
I96: =_xlfn.IFNA(INDEX('[1]Sector list'!$A$2:$A$122,MATCH(H96,'[1]Sector list'!$B$2:$B$122,0)),"")
I97: =_xlfn.IFNA(INDEX('[1]Sector list'!$A$2:$A$122,MATCH(H97,'[1]Sector list'!$B$2:$B$122,0)),"")
I98: =_xlfn.IFNA(INDEX('[1]Sector list'!$A$2:$A$122,MATCH(H98,'[1]Sector list'!$B$2:$B$122,0)),"")
I99: =_xlfn.IFNA(INDEX('[1]Sector list'!$A$2:$A$122,MATCH(H99,'[1]Sector list'!$B$2:$B$122,0)),"")
I100: =_xlfn.IFNA(INDEX('[1]Sector list'!$A$2:$A$122,MATCH(H100,'[1]Sector list'!$B$2:$B$122,0)),"")
I101: =_xlfn.IFNA(INDEX('[1]Sector list'!$A$2:$A$122,MATCH(H101,'[1]Sector list'!$B$2:$B$122,0)),"")
I102: =_xlfn.IFNA(INDEX('[1]Sector list'!$A$2:$A$122,MATCH(H102,'[1]Sector list'!$B$2:$B$122,0)),"")
I103: =_xlfn.IFNA(INDEX('[1]Sector list'!$A$2:$A$122,MATCH(H103,'[1]Sector list'!$B$2:$B$122,0)),"")
I104: =_xlfn.IFNA(INDEX('[1]Sector list'!$A$2:$A$122,MATCH(H104,'[1]Sector list'!$B$2:$B$122,0)),"")
I105: =_xlfn.IFNA(INDEX('[1]Sector list'!$A$2:$A$122,MATCH(H105,'[1]Sector list'!$B$2:$B$122,0)),"")
I106: =_xlfn.IFNA(INDEX('[1]Sector list'!$A$2:$A$122,MATCH(H106,'[1]Sector list'!$B$2:$B$122,0)),"")
I107: =_xlfn.IFNA(INDEX('[1]Sector list'!$A$2:$A$122,MATCH(H107,'[1]Sector list'!$B$2:$B$122,0)),"")
... I903: =_xlfn.IFNA(INDEX('[1]Sector list'!$A$2:$A$122,MATCH(H903,'[1]Sector list'!$B$2:$B$122,0)),"")

Sheet Investment by(2)
B2: Investment BY sector changes | G2: ='Final demand(2)'!H2 -> CVF_lower | H2: ='Final demand(2)'!H3 -> 2
B3: Fields with * must be specified manually or filled in automatically by selecting values in other columns
B5: Country | C5: Country ISO* | D5: Sector investing | E5: Sector investing code* | F5: Type* | G5: Comments
G6: =1/3 -> 0.33333333 | H6: FCF
B8: Germany | C8: =_xlfn.IFNA(INDEX('[2]Country list'!$A$2:$A$166,MATCH(B8,'[2]Country list'!$B$2:$B$166,0)),"") -> DEU | E8: 1-23 | F8: abs | G8: << Increase investment in agricultural sectors in Germany, 1000 kUSD in EVERY sector
G12: relative investment is not possible, because we don’t have an investment baseline right now
C13: REG_imp | E13: PROD_COMM | G13: Current options: abs-b
B14: Start in the next line >>
B15: Country | C15: Country ISO* | D15: Sector investing | E15: Sector investing code* | F15: Type* | G15: Comments | H15: 2019 | I15: 2020 | J15: 2021 | K15: 2022 | L15: 2023 | M15: 2024 | N15: 2025 | O15: 2026 | P15: 2027 | Q15: 2028 | R15: 2029 | S15: 2030 | T15: 2031 | U15: 2032 | V15: 2033 | W15: 2034 | X15: 2035 | Y15: 2036 | Z15: 2037 | AA15: 2038 | AB15: 2039 | AC15: 2040 | AD15: 2041 | AE15: 2042 | AF15: 2043 | AG15: 2044 | AH15: 2045 | AI15: 2046 | AJ15: 2047 | AK15: 2048 | AL15: 2049 | AM15: 2050
C16: SEP | E16: ALL | F16: abs-b | G16: =SUM(T16:AH16)/1000000 -> 0.34262129 | T16: =VLOOKUP($C16,'MSET pivots'!$B$4:$H$14,$H$2,FALSE)*1000000*$G$6*'MSET pivots'!E$65 -> 11420.881 | U16: =VLOOKUP($C16,'MSET pivots'!$B$4:$H$14,$H$2,FALSE)*1000000*$G$6*'MSET pivots'!F$65 -> 13052.386 | V16: =VLOOKUP($C16,'MSET pivots'!$B$4:$H$14,$H$2,FALSE)*1000000*$G$6*'MSET pivots'!G$65 -> 14683.892 | W16: =VLOOKUP($C16,'MSET pivots'!$B$4:$H$14,$H$2,FALSE)*1000000*$G$6*'MSET pivots'!H$65 -> 16315.397 | X16: =VLOOKUP($C16,'MSET pivots'!$B$4:$H$14,$H$2,FALSE)*1000000*$G$6*'MSET pivots'!I$65 -> 17946.903 | Y16: =VLOOKUP($C16,'MSET pivots'!$B$4:$H$14,$H$2,FALSE)*1000000*$G$6*'MSET pivots'!J$65 -> 19578.408 | Z16: =VLOOKUP($C16,'MSET pivots'!$B$4:$H$14,$H$2,FALSE)*1000000*$G$6*'MSET pivots'!K$65 -> 21209.914 | AA16: =VLOOKUP($C16,'MSET pivots'!$B$4:$H$14,$H$2,FALSE)*1000000*$G$6*'MSET pivots'!L$65 -> 22841.419 | ... AH16: =VLOOKUP($C16,'MSET pivots'!$B$4:$H$14,$H$2,FALSE)*1000000*$G$6*'MSET pivots'!S$65 -> 34261.957
C17: AFR | E17: ALL | F17: abs-b | G17: =SUM(T17:AH17)/1000000 -> 0.35655058 | T17: =VLOOKUP($C17,'MSET pivots'!$B$4:$H$14,$H$2,FALSE)*1000000*$G$6*'MSET pivots'!E$65 -> 11885.198 | U17: =VLOOKUP($C17,'MSET pivots'!$B$4:$H$14,$H$2,FALSE)*1000000*$G$6*'MSET pivots'!F$65 -> 13583.032 | V17: =VLOOKUP($C17,'MSET pivots'!$B$4:$H$14,$H$2,FALSE)*1000000*$G$6*'MSET pivots'!G$65 -> 15280.866 | W17: =VLOOKUP($C17,'MSET pivots'!$B$4:$H$14,$H$2,FALSE)*1000000*$G$6*'MSET pivots'!H$65 -> 16978.701 | X17: =VLOOKUP($C17,'MSET pivots'!$B$4:$H$14,$H$2,FALSE)*1000000*$G$6*'MSET pivots'!I$65 -> 18676.535 | Y17: =VLOOKUP($C17,'MSET pivots'!$B$4:$H$14,$H$2,FALSE)*1000000*$G$6*'MSET pivots'!J$65 -> 20374.37 | Z17: =VLOOKUP($C17,'MSET pivots'!$B$4:$H$14,$H$2,FALSE)*1000000*$G$6*'MSET pivots'!K$65 -> 22072.204 | AA17: =VLOOKUP($C17,'MSET pivots'!$B$4:$H$14,$H$2,FALSE)*1000000*$G$6*'MSET pivots'!L$65 -> 23770.039 | ... AH17: =VLOOKUP($C17,'MSET pivots'!$B$4:$H$14,$H$2,FALSE)*1000000*$G$6*'MSET pivots'!S$65 -> 35654.88
C18: LAC | E18: ALL | F18: abs-b | G18: =SUM(T18:AH18)/1000000 -> 0.26441491 | T18: =VLOOKUP($C18,'MSET pivots'!$B$4:$H$14,$H$2,FALSE)*1000000*$G$6*'MSET pivots'!E$65 -> 8813.9627 | U18: =VLOOKUP($C18,'MSET pivots'!$B$4:$H$14,$H$2,FALSE)*1000000*$G$6*'MSET pivots'!F$65 -> 10073.062 | V18: =VLOOKUP($C18,'MSET pivots'!$B$4:$H$14,$H$2,FALSE)*1000000*$G$6*'MSET pivots'!G$65 -> 11332.162 | W18: =VLOOKUP($C18,'MSET pivots'!$B$4:$H$14,$H$2,FALSE)*1000000*$G$6*'MSET pivots'!H$65 -> 12591.262 | X18: =VLOOKUP($C18,'MSET pivots'!$B$4:$H$14,$H$2,FALSE)*1000000*$G$6*'MSET pivots'!I$65 -> 13850.362 | Y18: =VLOOKUP($C18,'MSET pivots'!$B$4:$H$14,$H$2,FALSE)*1000000*$G$6*'MSET pivots'!J$65 -> 15109.461 | Z18: =VLOOKUP($C18,'MSET pivots'!$B$4:$H$14,$H$2,FALSE)*1000000*$G$6*'MSET pivots'!K$65 -> 16368.561 | AA18: =VLOOKUP($C18,'MSET pivots'!$B$4:$H$14,$H$2,FALSE)*1000000*$G$6*'MSET pivots'!L$65 -> 17627.661 | ... AH18: =VLOOKUP($C18,'MSET pivots'!$B$4:$H$14,$H$2,FALSE)*1000000*$G$6*'MSET pivots'!S$65 -> 26441.359
C19: SAS | E19: ALL | F19: abs-b | G19: =SUM(T19:AH19)/1000000 -> 0.3297289 | S19: ='Preliminary results'!$C$31*1000000*G6 -> 902060.73 | T19: =VLOOKUP($C19,'MSET pivots'!$B$4:$H$14,$H$2,FALSE)*1000000*$G$6*'MSET pivots'!E$65 -> 10991.128 | U19: =VLOOKUP($C19,'MSET pivots'!$B$4:$H$14,$H$2,FALSE)*1000000*$G$6*'MSET pivots'!F$65 -> 12561.242 | V19: =VLOOKUP($C19,'MSET pivots'!$B$4:$H$14,$H$2,FALSE)*1000000*$G$6*'MSET pivots'!G$65 -> 14131.356 | W19: =VLOOKUP($C19,'MSET pivots'!$B$4:$H$14,$H$2,FALSE)*1000000*$G$6*'MSET pivots'!H$65 -> 15701.47 | X19: =VLOOKUP($C19,'MSET pivots'!$B$4:$H$14,$H$2,FALSE)*1000000*$G$6*'MSET pivots'!I$65 -> 17271.584 | Y19: =VLOOKUP($C19,'MSET pivots'!$B$4:$H$14,$H$2,FALSE)*1000000*$G$6*'MSET pivots'!J$65 -> 18841.698 | Z19: =VLOOKUP($C19,'MSET pivots'!$B$4:$H$14,$H$2,FALSE)*1000000*$G$6*'MSET pivots'!K$65 -> 20411.813 | AA19: =VLOOKUP($C19,'MSET pivots'!$B$4:$H$14,$H$2,FALSE)*1000000*$G$6*'MSET pivots'!L$65 -> 21981.927 | ... AH19: =VLOOKUP($C19,'MSET pivots'!$B$4:$H$14,$H$2,FALSE)*1000000*$G$6*'MSET pivots'!S$65 -> 32972.725

Sheet Final demand(3)
B2: Final demand changes (consumption, govt, etc) | H2: CVF_central | I2: =1/3 -> 0.33333333 | J2: hh
B3: Fields with * must be specified manually or filled in automatically by selecting values in other columns | H3: 3 | I3: =1/3 -> 0.33333333 | J3: gov
B5: Country | C5: Country ISO* | F5: Product | G5: Product code* | H5: Final demand category | I5: FD code* | J5: Type* | K5: Comments
B6: Italy | C6: =_xlfn.IFNA(INDEX('[1]Country list'!$A$2:$A$166,MATCH(B6,'[1]Country list'!$B$2:$B$166,0)),"") -> ITA | F6: ALL | G6: =_xlfn.IFNA(INDEX('[1]Sector list'!$A$2:$A$122,MATCH(F6,'[1]Sector list'!$B$2:$B$122,0)),"") -> ALL | H6: Household final consumption P.3h | I6: =_xlfn.IFNA(INDEX('[1]FD list'!$A$2:$A$122,MATCH(H6,'[1]FD list'!$B$2:$B$122,0)),"") -> FD_1 | J6: rel-b | K6: << Decrease final demand (HH consumption) 3% for all products in Italy
C7: ITA | F7: Pork | G7: =_xlfn.IFNA(INDEX('[1]Sector list'!$A$2:$A$122,MATCH(F7,'[1]Sector list'!$B$2:$B$122,0)),"") -> 43 | H7: ALL | I7: =_xlfn.IFNA(INDEX('[1]FD list'!$A$2:$A$122,MATCH(H7,'[1]FD list'!$B$2:$B$122,0)),"") -> ALL | J7: rel-b | K7: << Increase final demand (across all demand categories) for pork in Italy by 12% (if zero stays zero)
B8: Germany | C8: =_xlfn.IFNA(INDEX('[1]Country list'!$A$2:$A$166,MATCH(B8,'[1]Country list'!$B$2:$B$166,0)),"") -> DEU | G8: 1-23 | I8: FD_1 | J8: abs-b | K8: << Increase demand in Germany for all agricultural sectors (1-23), only for consumer demand; try NOT to use negative values as it might create issues
B9: Malawi | C9: =_xlfn.IFNA(INDEX('[1]Country list'!$A$2:$A$166,MATCH(B9,'[1]Country list'!$B$2:$B$166,0)),"") -> MWI | F9: Building construction | G9: =_xlfn.IFNA(INDEX('[1]Sector list'!$A$2:$A$122,MATCH(F9,'[1]Sector list'!$B$2:$B$122,0)),"") -> 98 | H9: Gross fixed capital formation P.51 | I9: =_xlfn.IFNA(INDEX('[1]FD list'!$A$2:$A$122,MATCH(H9,'[1]FD list'!$B$2:$B$122,0)),"") -> FD_4 | J9: rel-b | K9: << Directly decrease investment (GFCF) demand for construction sector in Malawi with 1%; NOTE: if you want to do INVESTMENT BY the sector IT SHOULD NOT BE DONE HERE
C13: REG_exp | E13: REG_imp | G13: TRAD_COMM | I13: PROD_COMM (only FD) | J13: Current options: rel-b and abs-b
B14: Start in the next line >>
B15: Producing country | C15: Producing country ISO* | D15: Consuming country | E15: Consuming country ISO* | F15: Product | G15: Product code* | H15: Final demand category | I15: FD code* | J15: Type* | K15: Comments | L15: 2019 | M15: 2020 | N15: 2021 | O15: 2022 | P15: 2023 | Q15: 2024 | R15: 2025 | S15: 2026 | T15: 2027 | U15: 2028 | V15: 2029 | W15: 2030 | X15: 2031 | Y15: 2032 | Z15: 2033 | AA15: 2034 | AB15: 2035 | AC15: 2036 | AD15: 2037 | AE15: 2038 | AF15: 2039 | AG15: 2040 | AH15: 2041 | AI15: 2042 | AJ15: 2043 | AK15: 2044 | AL15: 2045 | AM15: 2046 | AN15: 2047 | AO15: 2048 | AP15: 2049 | AQ15: 2050
C16: SEP | E16: SEP | F16: ALL | G16: ALL | H16: Household final consumption P.3h | I16: FD_1 | J16: abs-b | K16: =SUM(X16:AL16)/1000000 -> 11.046509 | X16: =VLOOKUP($C16,'MSET pivots'!$B$4:$H$14,$H$3,FALSE)*1000000*$I$2*'MSET pivots'!E$65 -> 368222.5 | Y16: =VLOOKUP($C16,'MSET pivots'!$B$4:$H$14,$H$3,FALSE)*1000000*$I2*'MSET pivots'!F$65 -> 420824.13 | Z16: =VLOOKUP($C16,'MSET pivots'!$B$4:$H$14,$H$3,FALSE)*1000000*$I2*'MSET pivots'!G$65 -> 473425.77 | AA16: =VLOOKUP($C16,'MSET pivots'!$B$4:$H$14,$H$3,FALSE)*1000000*$I2*'MSET pivots'!H$65 -> 526027.41 | AB16: =VLOOKUP($C16,'MSET pivots'!$B$4:$H$14,$H$3,FALSE)*1000000*$I2*'MSET pivots'!I$65 -> 578629.04 | AC16: =VLOOKUP($C16,'MSET pivots'!$B$4:$H$14,$H$3,FALSE)*1000000*$I2*'MSET pivots'!J$65 -> 631230.68 | AD16: =VLOOKUP($C16,'MSET pivots'!$B$4:$H$14,$H$3,FALSE)*1000000*$I2*'MSET pivots'!K$65 -> 683832.31 | AE16: =VLOOKUP($C16,'MSET pivots'!$B$4:$H$14,$H$3,FALSE)*1000000*$I2*'MSET pivots'!L$65 -> 736433.95 | AF16: =VLOOKUP($C16,'MSET pivots'!$B$4:$H$14,$H$3,FALSE)*1000000*$I2*'MSET pivots'!M$65 -> 789035.59 | ... AL16: =VLOOKUP($C16,'MSET pivots'!$B$4:$H$14,$H$3,FALSE)*1000000*$I2*'MSET pivots'!S$65 -> 1104645.4
C17: SEP | E17: SEP | F17: ALL | G17: ALL | H17: Government final consumption P.3g | I17: FD_3 | J17: abs-b | K17: =SUM(X17:AL17)/1000000 -> 11.046509 | X17: =VLOOKUP($C17,'MSET pivots'!$B$4:$H$14,$H$3,FALSE)*1000000*$I$3*'MSET pivots'!E$65 -> 368222.5 | Y17: =VLOOKUP($C17,'MSET pivots'!$B$4:$H$14,$H$3,FALSE)*1000000*$I3*'MSET pivots'!F$65 -> 420824.13 | Z17: =VLOOKUP($C17,'MSET pivots'!$B$4:$H$14,$H$3,FALSE)*1000000*$I3*'MSET pivots'!G$65 -> 473425.77 | AA17: =VLOOKUP($C17,'MSET pivots'!$B$4:$H$14,$H$3,FALSE)*1000000*$I3*'MSET pivots'!H$65 -> 526027.41 | AB17: =VLOOKUP($C17,'MSET pivots'!$B$4:$H$14,$H$3,FALSE)*1000000*$I3*'MSET pivots'!I$65 -> 578629.04 | AC17: =VLOOKUP($C17,'MSET pivots'!$B$4:$H$14,$H$3,FALSE)*1000000*$I3*'MSET pivots'!J$65 -> 631230.68 | AD17: =VLOOKUP($C17,'MSET pivots'!$B$4:$H$14,$H$3,FALSE)*1000000*$I3*'MSET pivots'!K$65 -> 683832.31 | AE17: =VLOOKUP($C17,'MSET pivots'!$B$4:$H$14,$H$3,FALSE)*1000000*$I3*'MSET pivots'!L$65 -> 736433.95 | AF17: =VLOOKUP($C17,'MSET pivots'!$B$4:$H$14,$H$3,FALSE)*1000000*$I3*'MSET pivots'!M$65 -> 789035.59 | ... AL17: =VLOOKUP($C17,'MSET pivots'!$B$4:$H$14,$H$3,FALSE)*1000000*$I3*'MSET pivots'!S$65 -> 1104645.4
C18: AFR | E18: AFR | F18: ALL | G18: ALL | H18: Household final consumption P.3h | I18: FD_1 | J18: abs-b | K18: =SUM(X18:AL18)/1000000 -> 11.495606 | X18: =VLOOKUP($C18,'MSET pivots'!$B$4:$H$14,$H$3,FALSE)*1000000*$I$2*'MSET pivots'!E$65 -> 383192.61 | Y18: =VLOOKUP($C18,'MSET pivots'!$B$4:$H$14,$H$3,FALSE)*1000000*$I$2*'MSET pivots'!F$65 -> 437932.77 | Z18: =VLOOKUP($C18,'MSET pivots'!$B$4:$H$14,$H$3,FALSE)*1000000*$I$2*'MSET pivots'!G$65 -> 492672.93 | AA18: =VLOOKUP($C18,'MSET pivots'!$B$4:$H$14,$H$3,FALSE)*1000000*$I$2*'MSET pivots'!H$65 -> 547413.09 | AB18: =VLOOKUP($C18,'MSET pivots'!$B$4:$H$14,$H$3,FALSE)*1000000*$I$2*'MSET pivots'!I$65 -> 602153.25 | AC18: =VLOOKUP($C18,'MSET pivots'!$B$4:$H$14,$H$3,FALSE)*1000000*$I$2*'MSET pivots'!J$65 -> 656893.41 | AD18: =VLOOKUP($C18,'MSET pivots'!$B$4:$H$14,$H$3,FALSE)*1000000*$I$2*'MSET pivots'!K$65 -> 711633.56 | AE18: =VLOOKUP($C18,'MSET pivots'!$B$4:$H$14,$H$3,FALSE)*1000000*$I$2*'MSET pivots'!L$65 -> 766373.72 | ... AL18: =VLOOKUP($C18,'MSET pivots'!$B$4:$H$14,$H$3,FALSE)*1000000*$I$2*'MSET pivots'!S$65 -> 1149554.8
C19: AFR | E19: AFR | F19: ALL | G19: ALL | H19: Government final consumption P.3g | I19: FD_3 | J19: abs-b | K19: =SUM(X19:AL19)/1000000 -> 11.495606 | X19: =VLOOKUP($C19,'MSET pivots'!$B$4:$H$14,$H$3,FALSE)*1000000*$I$3*'MSET pivots'!E$65 -> 383192.61 | Y19: =VLOOKUP($C19,'MSET pivots'!$B$4:$H$14,$H$3,FALSE)*1000000*$I$3*'MSET pivots'!F$65 -> 437932.77 | Z19: =VLOOKUP($C19,'MSET pivots'!$B$4:$H$14,$H$3,FALSE)*1000000*$I$3*'MSET pivots'!G$65 -> 492672.93 | AA19: =VLOOKUP($C19,'MSET pivots'!$B$4:$H$14,$H$3,FALSE)*1000000*$I$3*'MSET pivots'!H$65 -> 547413.09 | AB19: =VLOOKUP($C19,'MSET pivots'!$B$4:$H$14,$H$3,FALSE)*1000000*$I$3*'MSET pivots'!I$65 -> 602153.25 | AC19: =VLOOKUP($C19,'MSET pivots'!$B$4:$H$14,$H$3,FALSE)*1000000*$I$3*'MSET pivots'!J$65 -> 656893.41 | AD19: =VLOOKUP($C19,'MSET pivots'!$B$4:$H$14,$H$3,FALSE)*1000000*$I$3*'MSET pivots'!K$65 -> 711633.56 | AE19: =VLOOKUP($C19,'MSET pivots'!$B$4:$H$14,$H$3,FALSE)*1000000*$I$3*'MSET pivots'!L$65 -> 766373.72 | ... AL19: =VLOOKUP($C19,'MSET pivots'!$B$4:$H$14,$H$3,FALSE)*1000000*$I$3*'MSET pivots'!S$65 -> 1149554.8
C20: LAC | E20: LAC | F20: ALL | G20: ALL | H20: Household final consumption P.3h | I20: FD_1 | J20: abs-b | K20: =SUM(X20:AL20)/1000000 -> 8.5250447 | X20: =VLOOKUP($C20,'MSET pivots'!$B$4:$H$14,$H$3,FALSE)*1000000*$I$2*'MSET pivots'!E$65 -> 284172.42 | Y20: =VLOOKUP($C20,'MSET pivots'!$B$4:$H$14,$H$3,FALSE)*1000000*$I$2*'MSET pivots'!F$65 -> 324767.26 | Z20: =VLOOKUP($C20,'MSET pivots'!$B$4:$H$14,$H$3,FALSE)*1000000*$I$2*'MSET pivots'!G$65 -> 365362.11 | AA20: =VLOOKUP($C20,'MSET pivots'!$B$4:$H$14,$H$3,FALSE)*1000000*$I$2*'MSET pivots'!H$65 -> 405956.95 | AB20: =VLOOKUP($C20,'MSET pivots'!$B$4:$H$14,$H$3,FALSE)*1000000*$I$2*'MSET pivots'!I$65 -> 446551.79 | AC20: =VLOOKUP($C20,'MSET pivots'!$B$4:$H$14,$H$3,FALSE)*1000000*$I$2*'MSET pivots'!J$65 -> 487146.63 | AD20: =VLOOKUP($C20,'MSET pivots'!$B$4:$H$14,$H$3,FALSE)*1000000*$I$2*'MSET pivots'!K$65 -> 527741.47 | AE20: =VLOOKUP($C20,'MSET pivots'!$B$4:$H$14,$H$3,FALSE)*1000000*$I$2*'MSET pivots'!L$65 -> 568336.32 | ... AL20: =VLOOKUP($C20,'MSET pivots'!$B$4:$H$14,$H$3,FALSE)*1000000*$I$2*'MSET pivots'!S$65 -> 852500.21
C21: LAC | E21: LAC | F21: ALL | G21: ALL | H21: Government final consumption P.3g | I21: FD_3 | J21: abs-b | K21: =SUM(X21:AL21)/1000000 -> 8.5250447 | X21: =VLOOKUP($C21,'MSET pivots'!$B$4:$H$14,$H$3,FALSE)*1000000*$I$3*'MSET pivots'!E$65 -> 284172.42 | Y21: =VLOOKUP($C21,'MSET pivots'!$B$4:$H$14,$H$3,FALSE)*1000000*$I$3*'MSET pivots'!F$65 -> 324767.26 | Z21: =VLOOKUP($C21,'MSET pivots'!$B$4:$H$14,$H$3,FALSE)*1000000*$I$3*'MSET pivots'!G$65 -> 365362.11 | AA21: =VLOOKUP($C21,'MSET pivots'!$B$4:$H$14,$H$3,FALSE)*1000000*$I$3*'MSET pivots'!H$65 -> 405956.95 | AB21: =VLOOKUP($C21,'MSET pivots'!$B$4:$H$14,$H$3,FALSE)*1000000*$I$3*'MSET pivots'!I$65 -> 446551.79 | AC21: =VLOOKUP($C21,'MSET pivots'!$B$4:$H$14,$H$3,FALSE)*1000000*$I$3*'MSET pivots'!J$65 -> 487146.63 | AD21: =VLOOKUP($C21,'MSET pivots'!$B$4:$H$14,$H$3,FALSE)*1000000*$I$3*'MSET pivots'!K$65 -> 527741.47 | AE21: =VLOOKUP($C21,'MSET pivots'!$B$4:$H$14,$H$3,FALSE)*1000000*$I$3*'MSET pivots'!L$65 -> 568336.32 | ... AL21: =VLOOKUP($C21,'MSET pivots'!$B$4:$H$14,$H$3,FALSE)*1000000*$I$3*'MSET pivots'!S$65 -> 852500.21
B22: Pakistan | C22: SAS | E22: SAS | F22: ALL | G22: ALL | H22: Household final consumption P.3h | I22: FD_1 | J22: abs-b | K22: =SUM(X22:AL22)/1000000 -> 10.630844 | W22: ='Preliminary results'!$C$31*1000000*I2 -> 902060.73 | X22: =VLOOKUP($C22,'MSET pivots'!$B$4:$H$14,$H$3,FALSE)*1000000*$I$2*'MSET pivots'!E$65 -> 354366.77 | Y22: =VLOOKUP($C22,'MSET pivots'!$B$4:$H$14,$H$3,FALSE)*1000000*$I$2*'MSET pivots'!F$65 -> 404989.08 | Z22: =VLOOKUP($C22,'MSET pivots'!$B$4:$H$14,$H$3,FALSE)*1000000*$I$2*'MSET pivots'!G$65 -> 455611.38 | AA22: =VLOOKUP($C22,'MSET pivots'!$B$4:$H$14,$H$3,FALSE)*1000000*$I$2*'MSET pivots'!H$65 -> 506233.69 | AB22: =VLOOKUP($C22,'MSET pivots'!$B$4:$H$14,$H$3,FALSE)*1000000*$I$2*'MSET pivots'!I$65 -> 556855.99 | AC22: =VLOOKUP($C22,'MSET pivots'!$B$4:$H$14,$H$3,FALSE)*1000000*$I$2*'MSET pivots'!J$65 -> 607478.3 | AD22: =VLOOKUP($C22,'MSET pivots'!$B$4:$H$14,$H$3,FALSE)*1000000*$I$2*'MSET pivots'!K$65 -> 658100.6 | AE22: =VLOOKUP($C22,'MSET pivots'!$B$4:$H$14,$H$3,FALSE)*1000000*$I$2*'MSET pivots'!L$65 -> 708722.91 | ... AL22: =VLOOKUP($C22,'MSET pivots'!$B$4:$H$14,$H$3,FALSE)*1000000*$I$2*'MSET pivots'!S$65 -> 1063079
B23: Pakistan | C23: SAS | E23: SAS | F23: ALL | G23: ALL | H23: Government final consumption P.3g | I23: FD_3 | J23: abs-b | K23: =SUM(X23:AL23)/1000000 -> 10.630844 | W23: ='Preliminary results'!$C$31*1000000*I3 -> 902060.73 | X23: =VLOOKUP($C23,'MSET pivots'!$B$4:$H$14,$H$3,FALSE)*1000000*$I$3*'MSET pivots'!E$65 -> 354366.77 | Y23: =VLOOKUP($C23,'MSET pivots'!$B$4:$H$14,$H$3,FALSE)*1000000*$I$3*'MSET pivots'!F$65 -> 404989.08 | Z23: =VLOOKUP($C23,'MSET pivots'!$B$4:$H$14,$H$3,FALSE)*1000000*$I$3*'MSET pivots'!G$65 -> 455611.38 | AA23: =VLOOKUP($C23,'MSET pivots'!$B$4:$H$14,$H$3,FALSE)*1000000*$I$3*'MSET pivots'!H$65 -> 506233.69 | AB23: =VLOOKUP($C23,'MSET pivots'!$B$4:$H$14,$H$3,FALSE)*1000000*$I$3*'MSET pivots'!I$65 -> 556855.99 | AC23: =VLOOKUP($C23,'MSET pivots'!$B$4:$H$14,$H$3,FALSE)*1000000*$I$3*'MSET pivots'!J$65 -> 607478.3 | AD23: =VLOOKUP($C23,'MSET pivots'!$B$4:$H$14,$H$3,FALSE)*1000000*$I$3*'MSET pivots'!K$65 -> 658100.6 | AE23: =VLOOKUP($C23,'MSET pivots'!$B$4:$H$14,$H$3,FALSE)*1000000*$I$3*'MSET pivots'!L$65 -> 708722.91 | ... AL23: =VLOOKUP($C23,'MSET pivots'!$B$4:$H$14,$H$3,FALSE)*1000000*$I$3*'MSET pivots'!S$65 -> 1063079
C24: AJN | E24: AJN | F24: ALL | G24: ALL | H24: Government final consumption P.3g | I24: FD_3 | J24: rel-b | K24: =SUM(X24:AL24) -> -0.0088262816 | X24: =VLOOKUP($C24,'MSET pivots'!$J$4:$P$14,'Final demand(3)'!$H$3,FALSE)*'MSET pivots'!E$65 -> -0.0002942138 | Y24: =VLOOKUP($C24,'MSET pivots'!$J$4:$P$14,'Final demand(3)'!$H$3,FALSE)*'MSET pivots'!F$65 -> -0.00033624308 | Z24: =VLOOKUP($C24,'MSET pivots'!$J$4:$P$14,'Final demand(3)'!$H$3,FALSE)*'MSET pivots'!G$65 -> -0.00037827236 | AA24: =VLOOKUP($C24,'MSET pivots'!$J$4:$P$14,'Final demand(3)'!$H$3,FALSE)*'MSET pivots'!H$65 -> -0.00042030164 | AB24: =VLOOKUP($C24,'MSET pivots'!$J$4:$P$14,'Final demand(3)'!$H$3,FALSE)*'MSET pivots'!I$65 -> -0.00046233093 | AC24: =VLOOKUP($C24,'MSET pivots'!$J$4:$P$14,'Final demand(3)'!$H$3,FALSE)*'MSET pivots'!J$65 -> -0.00050436021 | AD24: =VLOOKUP($C24,'MSET pivots'!$J$4:$P$14,'Final demand(3)'!$H$3,FALSE)*'MSET pivots'!K$65 -> -0.00054638949 | AE24: =VLOOKUP($C24,'MSET pivots'!$J$4:$P$14,'Final demand(3)'!$H$3,FALSE)*'MSET pivots'!L$65 -> -0.00058841877 | ... AL24: =VLOOKUP($C24,'MSET pivots'!$J$4:$P$14,'Final demand(3)'!$H$3,FALSE)*'MSET pivots'!S$65 -> -0.00088262374
C25: EAS | E25: EAS | F25: ALL | G25: ALL | H25: Government final consumption P.3g | I25: FD_3 | J25: rel-b | K25: =SUM(X25:AL25) -> -0.0045455366 | X25: =VLOOKUP($C25,'MSET pivots'!$J$4:$P$14,'Final demand(3)'!$H$3,FALSE)*'MSET pivots'!E$65 -> -0.00015152016 | Y25: =VLOOKUP($C25,'MSET pivots'!$J$4:$P$14,'Final demand(3)'!$H$3,FALSE)*'MSET pivots'!F$65 -> -0.00017316525 | Z25: =VLOOKUP($C25,'MSET pivots'!$J$4:$P$14,'Final demand(3)'!$H$3,FALSE)*'MSET pivots'!G$65 -> -0.00019481033 | AA25: =VLOOKUP($C25,'MSET pivots'!$J$4:$P$14,'Final demand(3)'!$H$3,FALSE)*'MSET pivots'!H$65 -> -0.00021645542 | AB25: =VLOOKUP($C25,'MSET pivots'!$J$4:$P$14,'Final demand(3)'!$H$3,FALSE)*'MSET pivots'!I$65 -> -0.00023810051 | AC25: =VLOOKUP($C25,'MSET pivots'!$J$4:$P$14,'Final demand(3)'!$H$3,FALSE)*'MSET pivots'!J$65 -> -0.0002597456 | AD25: =VLOOKUP($C25,'MSET pivots'!$J$4:$P$14,'Final demand(3)'!$H$3,FALSE)*'MSET pivots'!K$65 -> -0.00028139069 | AE25: =VLOOKUP($C25,'MSET pivots'!$J$4:$P$14,'Final demand(3)'!$H$3,FALSE)*'MSET pivots'!L$65 -> -0.00030303577 | ... AL25: =VLOOKUP($C25,'MSET pivots'!$J$4:$P$14,'Final demand(3)'!$H$3,FALSE)*'MSET pivots'!S$65 -> -0.00045455139
C26: EEA | E26: EEA | F26: ALL | G26: ALL | H26: Government final consumption P.3g | I26: FD_3 | J26: rel-b | K26: =SUM(X26:AL26) -> -0.0094439391 | X26: =VLOOKUP($C26,'MSET pivots'!$J$4:$P$14,'Final demand(3)'!$H$3,FALSE)*'MSET pivots'!E$65 -> -0.00031480269 | Y26: =VLOOKUP($C26,'MSET pivots'!$J$4:$P$14,'Final demand(3)'!$H$3,FALSE)*'MSET pivots'!F$65 -> -0.00035977316 | Z26: =VLOOKUP($C26,'MSET pivots'!$J$4:$P$14,'Final demand(3)'!$H$3,FALSE)*'MSET pivots'!G$65 -> -0.00040474362 | AA26: =VLOOKUP($C26,'MSET pivots'!$J$4:$P$14,'Final demand(3)'!$H$3,FALSE)*'MSET pivots'!H$65 -> -0.00044971408 | AB26: =VLOOKUP($C26,'MSET pivots'!$J$4:$P$14,'Final demand(3)'!$H$3,FALSE)*'MSET pivots'!I$65 -> -0.00049468455 | AC26: =VLOOKUP($C26,'MSET pivots'!$J$4:$P$14,'Final demand(3)'!$H$3,FALSE)*'MSET pivots'!J$65 -> -0.00053965501 | AD26: =VLOOKUP($C26,'MSET pivots'!$J$4:$P$14,'Final demand(3)'!$H$3,FALSE)*'MSET pivots'!K$65 -> -0.00058462548 | AE26: =VLOOKUP($C26,'MSET pivots'!$J$4:$P$14,'Final demand(3)'!$H$3,FALSE)*'MSET pivots'!L$65 -> -0.00062959594 | ... AL26: =VLOOKUP($C26,'MSET pivots'!$J$4:$P$14,'Final demand(3)'!$H$3,FALSE)*'MSET pivots'!S$65 -> -0.00094438919
B27: United Kingdom | C27: EUR | E27: EUR | F27: ALL | G27: ALL | H27: Government final consumption P.3g | I27: FD_3 | J27: rel-b | K27: =SUM(X27:AL27) -> -0.0068766548 | W27: =('Preliminary results'!$C$31)/'Baseline govt spend'!$E$51 -> 0.00066729533 | X27: =VLOOKUP($C27,'MSET pivots'!$J$4:$P$14,'Final demand(3)'!$H$3,FALSE)*'MSET pivots'!E$65 -> -0.00022922526 | Y27: =VLOOKUP($C27,'MSET pivots'!$J$4:$P$14,'Final demand(3)'!$H$3,FALSE)*'MSET pivots'!F$65 -> -0.00026197075 | Z27: =VLOOKUP($C27,'MSET pivots'!$J$4:$P$14,'Final demand(3)'!$H$3,FALSE)*'MSET pivots'!G$65 -> -0.00029471623 | AA27: =VLOOKUP($C27,'MSET pivots'!$J$4:$P$14,'Final demand(3)'!$H$3,FALSE)*'MSET pivots'!H$65 -> -0.00032746172 | AB27: =VLOOKUP($C27,'MSET pivots'!$J$4:$P$14,'Final demand(3)'!$H$3,FALSE)*'MSET pivots'!I$65 -> -0.0003602072 | AC27: =VLOOKUP($C27,'MSET pivots'!$J$4:$P$14,'Final demand(3)'!$H$3,FALSE)*'MSET pivots'!J$65 -> -0.00039295268 | AD27: =VLOOKUP($C27,'MSET pivots'!$J$4:$P$14,'Final demand(3)'!$H$3,FALSE)*'MSET pivots'!K$65 -> -0.00042569817 | AE27: =VLOOKUP($C27,'MSET pivots'!$J$4:$P$14,'Final demand(3)'!$H$3,FALSE)*'MSET pivots'!L$65 -> -0.00045844365 | ... AL27: =VLOOKUP($C27,'MSET pivots'!$J$4:$P$14,'Final demand(3)'!$H$3,FALSE)*'MSET pivots'!S$65 -> -0.00068766204
C28: MEN | E28: MEN | F28: ALL | G28: ALL | H28: Government final consumption P.3g | I28: FD_3 | J28: rel-b | K28: =SUM(X28:AL28) -> -0.0023956582 | X28: =VLOOKUP($C28,'MSET pivots'!$J$4:$P$14,'Final demand(3)'!$H$3,FALSE)*'MSET pivots'!E$65 -> -7.9856473e-05 | Y28: =VLOOKUP($C28,'MSET pivots'!$J$4:$P$14,'Final demand(3)'!$H$3,FALSE)*'MSET pivots'!F$65 -> -9.1264198e-05 | Z28: =VLOOKUP($C28,'MSET pivots'!$J$4:$P$14,'Final demand(3)'!$H$3,FALSE)*'MSET pivots'!G$65 -> -0.00010267192 | AA28: =VLOOKUP($C28,'MSET pivots'!$J$4:$P$14,'Final demand(3)'!$H$3,FALSE)*'MSET pivots'!H$65 -> -0.00011407965 | AB28: =VLOOKUP($C28,'MSET pivots'!$J$4:$P$14,'Final demand(3)'!$H$3,FALSE)*'MSET pivots'!I$65 -> -0.00012548737 | AC28: =VLOOKUP($C28,'MSET pivots'!$J$4:$P$14,'Final demand(3)'!$H$3,FALSE)*'MSET pivots'!J$65 -> -0.0001368951 | AD28: =VLOOKUP($C28,'MSET pivots'!$J$4:$P$14,'Final demand(3)'!$H$3,FALSE)*'MSET pivots'!K$65 -> -0.00014830282 | AE28: =VLOOKUP($C28,'MSET pivots'!$J$4:$P$14,'Final demand(3)'!$H$3,FALSE)*'MSET pivots'!L$65 -> -0.00015971055 | ... AL28: =VLOOKUP($C28,'MSET pivots'!$J$4:$P$14,'Final demand(3)'!$H$3,FALSE)*'MSET pivots'!S$65 -> -0.00023956463
C29: NAM | E29: NAM | F29: ALL | G29: ALL | H29: Government final consumption P.3g | I29: FD_3 | J29: rel-b | K29: =SUM(X29:AL29) -> -0.019088338 | X29: =VLOOKUP($C29,'MSET pivots'!$J$4:$P$14,'Final demand(3)'!$H$3,FALSE)*'MSET pivots'!E$65 -> -0.00063628749 | Y29: =VLOOKUP($C29,'MSET pivots'!$J$4:$P$14,'Final demand(3)'!$H$3,FALSE)*'MSET pivots'!F$65 -> -0.00072718298 | Z29: =VLOOKUP($C29,'MSET pivots'!$J$4:$P$14,'Final demand(3)'!$H$3,FALSE)*'MSET pivots'!G$65 -> -0.00081807846 | AA29: =VLOOKUP($C29,'MSET pivots'!$J$4:$P$14,'Final demand(3)'!$H$3,FALSE)*'MSET pivots'!H$65 -> -0.00090897395 | AB29: =VLOOKUP($C29,'MSET pivots'!$J$4:$P$14,'Final demand(3)'!$H$3,FALSE)*'MSET pivots'!I$65 -> -0.00099986944 | AC29: =VLOOKUP($C29,'MSET pivots'!$J$4:$P$14,'Final demand(3)'!$H$3,FALSE)*'MSET pivots'!J$65 -> -0.0010907649 | AD29: =VLOOKUP($C29,'MSET pivots'!$J$4:$P$14,'Final demand(3)'!$H$3,FALSE)*'MSET pivots'!K$65 -> -0.0011816604 | AE29: =VLOOKUP($C29,'MSET pivots'!$J$4:$P$14,'Final demand(3)'!$H$3,FALSE)*'MSET pivots'!L$65 -> -0.0012725559 | ... AL29: =VLOOKUP($C29,'MSET pivots'!$J$4:$P$14,'Final demand(3)'!$H$3,FALSE)*'MSET pivots'!S$65 -> -0.0019088243
G42: =_xlfn.IFNA(INDEX('[1]Sector list'!$A$2:$A$122,MATCH(F42,'[1]Sector list'!$B$2:$B$122,0)),"") | I42: =_xlfn.IFNA(INDEX('[1]FD list'!$A$2:$A$122,MATCH(H42,'[1]FD list'!$B$2:$B$122,0)),"")
G43: =_xlfn.IFNA(INDEX('[1]Sector list'!$A$2:$A$122,MATCH(F43,'[1]Sector list'!$B$2:$B$122,0)),"") | I43: =_xlfn.IFNA(INDEX('[1]FD list'!$A$2:$A$122,MATCH(H43,'[1]FD list'!$B$2:$B$122,0)),"")
G44: =_xlfn.IFNA(INDEX('[1]Sector list'!$A$2:$A$122,MATCH(F44,'[1]Sector list'!$B$2:$B$122,0)),"") | I44: =_xlfn.IFNA(INDEX('[1]FD list'!$A$2:$A$122,MATCH(H44,'[1]FD list'!$B$2:$B$122,0)),"")
G45: =_xlfn.IFNA(INDEX('[1]Sector list'!$A$2:$A$122,MATCH(F45,'[1]Sector list'!$B$2:$B$122,0)),"") | I45: =_xlfn.IFNA(INDEX('[1]FD list'!$A$2:$A$122,MATCH(H45,'[1]FD list'!$B$2:$B$122,0)),"")
G46: =_xlfn.IFNA(INDEX('[1]Sector list'!$A$2:$A$122,MATCH(F46,'[1]Sector list'!$B$2:$B$122,0)),"") | I46: =_xlfn.IFNA(INDEX('[1]FD list'!$A$2:$A$122,MATCH(H46,'[1]FD list'!$B$2:$B$122,0)),"")
G47: =_xlfn.IFNA(INDEX('[1]Sector list'!$A$2:$A$122,MATCH(F47,'[1]Sector list'!$B$2:$B$122,0)),"") | I47: =_xlfn.IFNA(INDEX('[1]FD list'!$A$2:$A$122,MATCH(H47,'[1]FD list'!$B$2:$B$122,0)),"")
G48: =_xlfn.IFNA(INDEX('[1]Sector list'!$A$2:$A$122,MATCH(F48,'[1]Sector list'!$B$2:$B$122,0)),"") | I48: =_xlfn.IFNA(INDEX('[1]FD list'!$A$2:$A$122,MATCH(H48,'[1]FD list'!$B$2:$B$122,0)),"")
G49: =_xlfn.IFNA(INDEX('[1]Sector list'!$A$2:$A$122,MATCH(F49,'[1]Sector list'!$B$2:$B$122,0)),"") | I49: =_xlfn.IFNA(INDEX('[1]FD list'!$A$2:$A$122,MATCH(H49,'[1]FD list'!$B$2:$B$122,0)),"")
G50: =_xlfn.IFNA(INDEX('[1]Sector list'!$A$2:$A$122,MATCH(F50,'[1]Sector list'!$B$2:$B$122,0)),"") | I50: =_xlfn.IFNA(INDEX('[1]FD list'!$A$2:$A$122,MATCH(H50,'[1]FD list'!$B$2:$B$122,0)),"")
G51: =_xlfn.IFNA(INDEX('[1]Sector list'!$A$2:$A$122,MATCH(F51,'[1]Sector list'!$B$2:$B$122,0)),"") | I51: =_xlfn.IFNA(INDEX('[1]FD list'!$A$2:$A$122,MATCH(H51,'[1]FD list'!$B$2:$B$122,0)),"")
G52: =_xlfn.IFNA(INDEX('[1]Sector list'!$A$2:$A$122,MATCH(F52,'[1]Sector list'!$B$2:$B$122,0)),"") | I52: =_xlfn.IFNA(INDEX('[1]FD list'!$A$2:$A$122,MATCH(H52,'[1]FD list'!$B$2:$B$122,0)),"")
G53: =_xlfn.IFNA(INDEX('[1]Sector list'!$A$2:$A$122,MATCH(F53,'[1]Sector list'!$B$2:$B$122,0)),"") | I53: =_xlfn.IFNA(INDEX('[1]FD list'!$A$2:$A$122,MATCH(H53,'[1]FD list'!$B$2:$B$122,0)),"")
... G67: =_xlfn.IFNA(INDEX('[1]Sector list'!$A$2:$A$122,MATCH(F67,'[1]Sector list'!$B$2:$B$122,0)),"") | I67: =_xlfn.IFNA(INDEX('[1]FD list'!$A$2:$A$122,MATCH(H67,'[1]FD list'!$B$2:$B$122,0)),"")
I68: =_xlfn.IFNA(INDEX('[1]FD list'!$A$2:$A$122,MATCH(H68,'[1]FD list'!$B$2:$B$122,0)),"")
I69: =_xlfn.IFNA(INDEX('[1]FD list'!$A$2:$A$122,MATCH(H69,'[1]FD list'!$B$2:$B$122,0)),"")
I70: =_xlfn.IFNA(INDEX('[1]FD list'!$A$2:$A$122,MATCH(H70,'[1]FD list'!$B$2:$B$122,0)),"")
I71: =_xlfn.IFNA(INDEX('[1]FD list'!$A$2:$A$122,MATCH(H71,'[1]FD list'!$B$2:$B$122,0)),"")
I72: =_xlfn.IFNA(INDEX('[1]FD list'!$A$2:$A$122,MATCH(H72,'[1]FD list'!$B$2:$B$122,0)),"")
I73: =_xlfn.IFNA(INDEX('[1]FD list'!$A$2:$A$122,MATCH(H73,'[1]FD list'!$B$2:$B$122,0)),"")
I74: =_xlfn.IFNA(INDEX('[1]FD list'!$A$2:$A$122,MATCH(H74,'[1]FD list'!$B$2:$B$122,0)),"")
I75: =_xlfn.IFNA(INDEX('[1]FD list'!$A$2:$A$122,MATCH(H75,'[1]FD list'!$B$2:$B$122,0)),"")
I76: =_xlfn.IFNA(INDEX('[1]FD list'!$A$2:$A$122,MATCH(H76,'[1]FD list'!$B$2:$B$122,0)),"")
I77: =_xlfn.IFNA(INDEX('[1]FD list'!$A$2:$A$122,MATCH(H77,'[1]FD list'!$B$2:$B$122,0)),"")
I78: =_xlfn.IFNA(INDEX('[1]FD list'!$A$2:$A$122,MATCH(H78,'[1]FD list'!$B$2:$B$122,0)),"")
I79: =_xlfn.IFNA(INDEX('[1]FD list'!$A$2:$A$122,MATCH(H79,'[1]FD list'!$B$2:$B$122,0)),"")
... I95: =_xlfn.IFNA(INDEX('[1]FD list'!$A$2:$A$122,MATCH(H95,'[1]FD list'!$B$2:$B$122,0)),"")
I96: =_xlfn.IFNA(INDEX('[1]Sector list'!$A$2:$A$122,MATCH(H96,'[1]Sector list'!$B$2:$B$122,0)),"")
I97: =_xlfn.IFNA(INDEX('[1]Sector list'!$A$2:$A$122,MATCH(H97,'[1]Sector list'!$B$2:$B$122,0)),"")
I98: =_xlfn.IFNA(INDEX('[1]Sector list'!$A$2:$A$122,MATCH(H98,'[1]Sector list'!$B$2:$B$122,0)),"")
I99: =_xlfn.IFNA(INDEX('[1]Sector list'!$A$2:$A$122,MATCH(H99,'[1]Sector list'!$B$2:$B$122,0)),"")
I100: =_xlfn.IFNA(INDEX('[1]Sector list'!$A$2:$A$122,MATCH(H100,'[1]Sector list'!$B$2:$B$122,0)),"")
I101: =_xlfn.IFNA(INDEX('[1]Sector list'!$A$2:$A$122,MATCH(H101,'[1]Sector list'!$B$2:$B$122,0)),"")
I102: =_xlfn.IFNA(INDEX('[1]Sector list'!$A$2:$A$122,MATCH(H102,'[1]Sector list'!$B$2:$B$122,0)),"")
I103: =_xlfn.IFNA(INDEX('[1]Sector list'!$A$2:$A$122,MATCH(H103,'[1]Sector list'!$B$2:$B$122,0)),"")
I104: =_xlfn.IFNA(INDEX('[1]Sector list'!$A$2:$A$122,MATCH(H104,'[1]Sector list'!$B$2:$B$122,0)),"")
I105: =_xlfn.IFNA(INDEX('[1]Sector list'!$A$2:$A$122,MATCH(H105,'[1]Sector list'!$B$2:$B$122,0)),"")
I106: =_xlfn.IFNA(INDEX('[1]Sector list'!$A$2:$A$122,MATCH(H106,'[1]Sector list'!$B$2:$B$122,0)),"")
I107: =_xlfn.IFNA(INDEX('[1]Sector list'!$A$2:$A$122,MATCH(H107,'[1]Sector list'!$B$2:$B$122,0)),"")
... I903: =_xlfn.IFNA(INDEX('[1]Sector list'!$A$2:$A$122,MATCH(H903,'[1]Sector list'!$B$2:$B$122,0)),"")

Sheet Investment by(3)
B2: Investment BY sector changes | G2: ='Final demand(3)'!H2 -> CVF_central | H2: ='Final demand(3)'!H3 -> 3
B3: Fields with * must be specified manually or filled in automatically by selecting values in other columns
B5: Country | C5: Country ISO* | D5: Sector investing | E5: Sector investing code* | F5: Type* | G5: Comments
G6: =1/3 -> 0.33333333 | H6: FCF
B8: Germany | C8: =_xlfn.IFNA(INDEX('[2]Country list'!$A$2:$A$166,MATCH(B8,'[2]Country list'!$B$2:$B$166,0)),"") -> DEU | E8: 1-23 | F8: abs | G8: << Increase investment in agricultural sectors in Germany, 1000 kUSD in EVERY sector
G12: relative investment is not possible, because we don’t have an investment baseline right now
C13: REG_imp | E13: PROD_COMM | G13: Current options: abs-b
B14: Start in the next line >>
B15: Country | C15: Country ISO* | D15: Sector investing | E15: Sector investing code* | F15: Type* | G15: Comments | H15: 2019 | I15: 2020 | J15: 2021 | K15: 2022 | L15: 2023 | M15: 2024 | N15: 2025 | O15: 2026 | P15: 2027 | Q15: 2028 | R15: 2029 | S15: 2030 | T15: 2031 | U15: 2032 | V15: 2033 | W15: 2034 | X15: 2035 | Y15: 2036 | Z15: 2037 | AA15: 2038 | AB15: 2039 | AC15: 2040 | AD15: 2041 | AE15: 2042 | AF15: 2043 | AG15: 2044 | AH15: 2045 | AI15: 2046 | AJ15: 2047 | AK15: 2048 | AL15: 2049 | AM15: 2050
C16: SEP | E16: ALL | F16: abs-b | G16: =SUM(T16:AH16)/1000000 -> 11.046509 | T16: =VLOOKUP($C16,'MSET pivots'!$B$4:$H$14,$H$2,FALSE)*1000000*$G$6*'MSET pivots'!E$65 -> 368222.5 | U16: =VLOOKUP($C16,'MSET pivots'!$B$4:$H$14,$H$2,FALSE)*1000000*$G$6*'MSET pivots'!F$65 -> 420824.13 | V16: =VLOOKUP($C16,'MSET pivots'!$B$4:$H$14,$H$2,FALSE)*1000000*$G$6*'MSET pivots'!G$65 -> 473425.77 | W16: =VLOOKUP($C16,'MSET pivots'!$B$4:$H$14,$H$2,FALSE)*1000000*$G$6*'MSET pivots'!H$65 -> 526027.41 | X16: =VLOOKUP($C16,'MSET pivots'!$B$4:$H$14,$H$2,FALSE)*1000000*$G$6*'MSET pivots'!I$65 -> 578629.04 | Y16: =VLOOKUP($C16,'MSET pivots'!$B$4:$H$14,$H$2,FALSE)*1000000*$G$6*'MSET pivots'!J$65 -> 631230.68 | Z16: =VLOOKUP($C16,'MSET pivots'!$B$4:$H$14,$H$2,FALSE)*1000000*$G$6*'MSET pivots'!K$65 -> 683832.31 | AA16: =VLOOKUP($C16,'MSET pivots'!$B$4:$H$14,$H$2,FALSE)*1000000*$G$6*'MSET pivots'!L$65 -> 736433.95 | ... AH16: =VLOOKUP($C16,'MSET pivots'!$B$4:$H$14,$H$2,FALSE)*1000000*$G$6*'MSET pivots'!S$65 -> 1104645.4
C17: AFR | E17: ALL | F17: abs-b | G17: =SUM(T17:AH17)/1000000 -> 11.495606 | T17: =VLOOKUP($C17,'MSET pivots'!$B$4:$H$14,$H$2,FALSE)*1000000*$G$6*'MSET pivots'!E$65 -> 383192.61 | U17: =VLOOKUP($C17,'MSET pivots'!$B$4:$H$14,$H$2,FALSE)*1000000*$G$6*'MSET pivots'!F$65 -> 437932.77 | V17: =VLOOKUP($C17,'MSET pivots'!$B$4:$H$14,$H$2,FALSE)*1000000*$G$6*'MSET pivots'!G$65 -> 492672.93 | W17: =VLOOKUP($C17,'MSET pivots'!$B$4:$H$14,$H$2,FALSE)*1000000*$G$6*'MSET pivots'!H$65 -> 547413.09 | X17: =VLOOKUP($C17,'MSET pivots'!$B$4:$H$14,$H$2,FALSE)*1000000*$G$6*'MSET pivots'!I$65 -> 602153.25 | Y17: =VLOOKUP($C17,'MSET pivots'!$B$4:$H$14,$H$2,FALSE)*1000000*$G$6*'MSET pivots'!J$65 -> 656893.41 | Z17: =VLOOKUP($C17,'MSET pivots'!$B$4:$H$14,$H$2,FALSE)*1000000*$G$6*'MSET pivots'!K$65 -> 711633.56 | AA17: =VLOOKUP($C17,'MSET pivots'!$B$4:$H$14,$H$2,FALSE)*1000000*$G$6*'MSET pivots'!L$65 -> 766373.72 | ... AH17: =VLOOKUP($C17,'MSET pivots'!$B$4:$H$14,$H$2,FALSE)*1000000*$G$6*'MSET pivots'!S$65 -> 1149554.8
C18: LAC | E18: ALL | F18: abs-b | G18: =SUM(T18:AH18)/1000000 -> 8.5250447 | T18: =VLOOKUP($C18,'MSET pivots'!$B$4:$H$14,$H$2,FALSE)*1000000*$G$6*'MSET pivots'!E$65 -> 284172.42 | U18: =VLOOKUP($C18,'MSET pivots'!$B$4:$H$14,$H$2,FALSE)*1000000*$G$6*'MSET pivots'!F$65 -> 324767.26 | V18: =VLOOKUP($C18,'MSET pivots'!$B$4:$H$14,$H$2,FALSE)*1000000*$G$6*'MSET pivots'!G$65 -> 365362.11 | W18: =VLOOKUP($C18,'MSET pivots'!$B$4:$H$14,$H$2,FALSE)*1000000*$G$6*'MSET pivots'!H$65 -> 405956.95 | X18: =VLOOKUP($C18,'MSET pivots'!$B$4:$H$14,$H$2,FALSE)*1000000*$G$6*'MSET pivots'!I$65 -> 446551.79 | Y18: =VLOOKUP($C18,'MSET pivots'!$B$4:$H$14,$H$2,FALSE)*1000000*$G$6*'MSET pivots'!J$65 -> 487146.63 | Z18: =VLOOKUP($C18,'MSET pivots'!$B$4:$H$14,$H$2,FALSE)*1000000*$G$6*'MSET pivots'!K$65 -> 527741.47 | AA18: =VLOOKUP($C18,'MSET pivots'!$B$4:$H$14,$H$2,FALSE)*1000000*$G$6*'MSET pivots'!L$65 -> 568336.32 | ... AH18: =VLOOKUP($C18,'MSET pivots'!$B$4:$H$14,$H$2,FALSE)*1000000*$G$6*'MSET pivots'!S$65 -> 852500.21
C19: SAS | E19: ALL | F19: abs-b | G19: =SUM(T19:AH19)/1000000 -> 10.630844 | S19: ='Preliminary results'!$C$31*1000000*G6 -> 902060.73 | T19: =VLOOKUP($C19,'MSET pivots'!$B$4:$H$14,$H$2,FALSE)*1000000*$G$6*'MSET pivots'!E$65 -> 354366.77 | U19: =VLOOKUP($C19,'MSET pivots'!$B$4:$H$14,$H$2,FALSE)*1000000*$G$6*'MSET pivots'!F$65 -> 404989.08 | V19: =VLOOKUP($C19,'MSET pivots'!$B$4:$H$14,$H$2,FALSE)*1000000*$G$6*'MSET pivots'!G$65 -> 455611.38 | W19: =VLOOKUP($C19,'MSET pivots'!$B$4:$H$14,$H$2,FALSE)*1000000*$G$6*'MSET pivots'!H$65 -> 506233.69 | X19: =VLOOKUP($C19,'MSET pivots'!$B$4:$H$14,$H$2,FALSE)*1000000*$G$6*'MSET pivots'!I$65 -> 556855.99 | Y19: =VLOOKUP($C19,'MSET pivots'!$B$4:$H$14,$H$2,FALSE)*1000000*$G$6*'MSET pivots'!J$65 -> 607478.3 | Z19: =VLOOKUP($C19,'MSET pivots'!$B$4:$H$14,$H$2,FALSE)*1000000*$G$6*'MSET pivots'!K$65 -> 658100.6 | AA19: =VLOOKUP($C19,'MSET pivots'!$B$4:$H$14,$H$2,FALSE)*1000000*$G$6*'MSET pivots'!L$65 -> 708722.91 | ... AH19: =VLOOKUP($C19,'MSET pivots'!$B$4:$H$14,$H$2,FALSE)*1000000*$G$6*'MSET pivots'!S$65 -> 1063079

Sheet Final demand(4)
B2: Final demand changes (consumption, govt, etc) | H2: CVF_upper | I2: =1/3 -> 0.33333333 | J2: hh
B3: Fields with * must be specified manually or filled in automatically by selecting values in other columns | H3: 4 | I3: =1/3 -> 0.33333333 | J3: gov
B5: Country | C5: Country ISO* | F5: Product | G5: Product code* | H5: Final demand category | I5: FD code* | J5: Type* | K5: Comments
B6: Italy | C6: =_xlfn.IFNA(INDEX('[1]Country list'!$A$2:$A$166,MATCH(B6,'[1]Country list'!$B$2:$B$166,0)),"") -> ITA | F6: ALL | G6: =_xlfn.IFNA(INDEX('[1]Sector list'!$A$2:$A$122,MATCH(F6,'[1]Sector list'!$B$2:$B$122,0)),"") -> ALL | H6: Household final consumption P.3h | I6: =_xlfn.IFNA(INDEX('[1]FD list'!$A$2:$A$122,MATCH(H6,'[1]FD list'!$B$2:$B$122,0)),"") -> FD_1 | J6: rel-b | K6: << Decrease final demand (HH consumption) 3% for all products in Italy
C7: ITA | F7: Pork | G7: =_xlfn.IFNA(INDEX('[1]Sector list'!$A$2:$A$122,MATCH(F7,'[1]Sector list'!$B$2:$B$122,0)),"") -> 43 | H7: ALL | I7: =_xlfn.IFNA(INDEX('[1]FD list'!$A$2:$A$122,MATCH(H7,'[1]FD list'!$B$2:$B$122,0)),"") -> ALL | J7: rel-b | K7: << Increase final demand (across all demand categories) for pork in Italy by 12% (if zero stays zero)
B8: Germany | C8: =_xlfn.IFNA(INDEX('[1]Country list'!$A$2:$A$166,MATCH(B8,'[1]Country list'!$B$2:$B$166,0)),"") -> DEU | G8: 1-23 | I8: FD_1 | J8: abs-b | K8: << Increase demand in Germany for all agricultural sectors (1-23), only for consumer demand; try NOT to use negative values as it might create issues
B9: Malawi | C9: =_xlfn.IFNA(INDEX('[1]Country list'!$A$2:$A$166,MATCH(B9,'[1]Country list'!$B$2:$B$166,0)),"") -> MWI | F9: Building construction | G9: =_xlfn.IFNA(INDEX('[1]Sector list'!$A$2:$A$122,MATCH(F9,'[1]Sector list'!$B$2:$B$122,0)),"") -> 98 | H9: Gross fixed capital formation P.51 | I9: =_xlfn.IFNA(INDEX('[1]FD list'!$A$2:$A$122,MATCH(H9,'[1]FD list'!$B$2:$B$122,0)),"") -> FD_4 | J9: rel-b | K9: << Directly decrease investment (GFCF) demand for construction sector in Malawi with 1%; NOTE: if you want to do INVESTMENT BY the sector IT SHOULD NOT BE DONE HERE
C13: REG_exp | E13: REG_imp | G13: TRAD_COMM | I13: PROD_COMM (only FD) | J13: Current options: rel-b and abs-b
B14: Start in the next line >>
B15: Producing country | C15: Producing country ISO* | D15: Consuming country | E15: Consuming country ISO* | F15: Product | G15: Product code* | H15: Final demand category | I15: FD code* | J15: Type* | K15: Comments | L15: 2019 | M15: 2020 | N15: 2021 | O15: 2022 | P15: 2023 | Q15: 2024 | R15: 2025 | S15: 2026 | T15: 2027 | U15: 2028 | V15: 2029 | W15: 2030 | X15: 2031 | Y15: 2032 | Z15: 2033 | AA15: 2034 | AB15: 2035 | AC15: 2036 | AD15: 2037 | AE15: 2038 | AF15: 2039 | AG15: 2040 | AH15: 2041 | AI15: 2042 | AJ15: 2043 | AK15: 2044 | AL15: 2045 | AM15: 2046 | AN15: 2047 | AO15: 2048 | AP15: 2049 | AQ15: 2050
C16: SEP | E16: SEP | F16: ALL | G16: ALL | H16: Household final consumption P.3h | I16: FD_1 | J16: abs-b | K16: =SUM(X16:AL16)/1000000 -> 46.609068 | X16: =VLOOKUP($C16,'MSET pivots'!$B$4:$H$14,$H$3,FALSE)*1000000*$I$2*'MSET pivots'!E$65 -> 1553658.9 | Y16: =VLOOKUP($C16,'MSET pivots'!$B$4:$H$14,$H$3,FALSE)*1000000*$I2*'MSET pivots'!F$65 -> 1775603.5 | Z16: =VLOOKUP($C16,'MSET pivots'!$B$4:$H$14,$H$3,FALSE)*1000000*$I2*'MSET pivots'!G$65 -> 1997548.1 | AA16: =VLOOKUP($C16,'MSET pivots'!$B$4:$H$14,$H$3,FALSE)*1000000*$I2*'MSET pivots'!H$65 -> 2219492.7 | AB16: =VLOOKUP($C16,'MSET pivots'!$B$4:$H$14,$H$3,FALSE)*1000000*$I2*'MSET pivots'!I$65 -> 2441437.4 | AC16: =VLOOKUP($C16,'MSET pivots'!$B$4:$H$14,$H$3,FALSE)*1000000*$I2*'MSET pivots'!J$65 -> 2663382 | AD16: =VLOOKUP($C16,'MSET pivots'!$B$4:$H$14,$H$3,FALSE)*1000000*$I2*'MSET pivots'!K$65 -> 2885326.6 | AE16: =VLOOKUP($C16,'MSET pivots'!$B$4:$H$14,$H$3,FALSE)*1000000*$I2*'MSET pivots'!L$65 -> 3107271.2 | AF16: =VLOOKUP($C16,'MSET pivots'!$B$4:$H$14,$H$3,FALSE)*1000000*$I2*'MSET pivots'!M$65 -> 3329215.8 | ... AL16: =VLOOKUP($C16,'MSET pivots'!$B$4:$H$14,$H$3,FALSE)*1000000*$I2*'MSET pivots'!S$65 -> 4660883.5
C17: SEP | E17: SEP | F17: ALL | G17: ALL | H17: Government final consumption P.3g | I17: FD_3 | J17: abs-b | K17: =SUM(X17:AL17)/1000000 -> 46.609068 | X17: =VLOOKUP($C17,'MSET pivots'!$B$4:$H$14,$H$3,FALSE)*1000000*$I$3*'MSET pivots'!E$65 -> 1553658.9 | Y17: =VLOOKUP($C17,'MSET pivots'!$B$4:$H$14,$H$3,FALSE)*1000000*$I3*'MSET pivots'!F$65 -> 1775603.5 | Z17: =VLOOKUP($C17,'MSET pivots'!$B$4:$H$14,$H$3,FALSE)*1000000*$I3*'MSET pivots'!G$65 -> 1997548.1 | AA17: =VLOOKUP($C17,'MSET pivots'!$B$4:$H$14,$H$3,FALSE)*1000000*$I3*'MSET pivots'!H$65 -> 2219492.7 | AB17: =VLOOKUP($C17,'MSET pivots'!$B$4:$H$14,$H$3,FALSE)*1000000*$I3*'MSET pivots'!I$65 -> 2441437.4 | AC17: =VLOOKUP($C17,'MSET pivots'!$B$4:$H$14,$H$3,FALSE)*1000000*$I3*'MSET pivots'!J$65 -> 2663382 | AD17: =VLOOKUP($C17,'MSET pivots'!$B$4:$H$14,$H$3,FALSE)*1000000*$I3*'MSET pivots'!K$65 -> 2885326.6 | AE17: =VLOOKUP($C17,'MSET pivots'!$B$4:$H$14,$H$3,FALSE)*1000000*$I3*'MSET pivots'!L$65 -> 3107271.2 | AF17: =VLOOKUP($C17,'MSET pivots'!$B$4:$H$14,$H$3,FALSE)*1000000*$I3*'MSET pivots'!M$65 -> 3329215.8 | ... AL17: =VLOOKUP($C17,'MSET pivots'!$B$4:$H$14,$H$3,FALSE)*1000000*$I3*'MSET pivots'!S$65 -> 4660883.5
C18: AFR | E18: AFR | F18: ALL | G18: ALL | H18: Household final consumption P.3h | I18: FD_1 | J18: abs-b | K18: =SUM(X18:AL18)/1000000 -> 48.503963 | X18: =VLOOKUP($C18,'MSET pivots'!$B$4:$H$14,$H$3,FALSE)*1000000*$I$2*'MSET pivots'!E$65 -> 1616823 | Y18: =VLOOKUP($C18,'MSET pivots'!$B$4:$H$14,$H$3,FALSE)*1000000*$I$2*'MSET pivots'!F$65 -> 1847790.8 | Z18: =VLOOKUP($C18,'MSET pivots'!$B$4:$H$14,$H$3,FALSE)*1000000*$I$2*'MSET pivots'!G$65 -> 2078758.6 | AA18: =VLOOKUP($C18,'MSET pivots'!$B$4:$H$14,$H$3,FALSE)*1000000*$I$2*'MSET pivots'!H$65 -> 2309726.4 | AB18: =VLOOKUP($C18,'MSET pivots'!$B$4:$H$14,$H$3,FALSE)*1000000*$I$2*'MSET pivots'!I$65 -> 2540694.2 | AC18: =VLOOKUP($C18,'MSET pivots'!$B$4:$H$14,$H$3,FALSE)*1000000*$I$2*'MSET pivots'!J$65 -> 2771662 | AD18: =VLOOKUP($C18,'MSET pivots'!$B$4:$H$14,$H$3,FALSE)*1000000*$I$2*'MSET pivots'!K$65 -> 3002629.7 | AE18: =VLOOKUP($C18,'MSET pivots'!$B$4:$H$14,$H$3,FALSE)*1000000*$I$2*'MSET pivots'!L$65 -> 3233597.5 | ... AL18: =VLOOKUP($C18,'MSET pivots'!$B$4:$H$14,$H$3,FALSE)*1000000*$I$2*'MSET pivots'!S$65 -> 4850372
C19: AFR | E19: AFR | F19: ALL | G19: ALL | H19: Government final consumption P.3g | I19: FD_3 | J19: abs-b | K19: =SUM(X19:AL19)/1000000 -> 48.503963 | X19: =VLOOKUP($C19,'MSET pivots'!$B$4:$H$14,$H$3,FALSE)*1000000*$I$3*'MSET pivots'!E$65 -> 1616823 | Y19: =VLOOKUP($C19,'MSET pivots'!$B$4:$H$14,$H$3,FALSE)*1000000*$I$3*'MSET pivots'!F$65 -> 1847790.8 | Z19: =VLOOKUP($C19,'MSET pivots'!$B$4:$H$14,$H$3,FALSE)*1000000*$I$3*'MSET pivots'!G$65 -> 2078758.6 | AA19: =VLOOKUP($C19,'MSET pivots'!$B$4:$H$14,$H$3,FALSE)*1000000*$I$3*'MSET pivots'!H$65 -> 2309726.4 | AB19: =VLOOKUP($C19,'MSET pivots'!$B$4:$H$14,$H$3,FALSE)*1000000*$I$3*'MSET pivots'!I$65 -> 2540694.2 | AC19: =VLOOKUP($C19,'MSET pivots'!$B$4:$H$14,$H$3,FALSE)*1000000*$I$3*'MSET pivots'!J$65 -> 2771662 | AD19: =VLOOKUP($C19,'MSET pivots'!$B$4:$H$14,$H$3,FALSE)*1000000*$I$3*'MSET pivots'!K$65 -> 3002629.7 | AE19: =VLOOKUP($C19,'MSET pivots'!$B$4:$H$14,$H$3,FALSE)*1000000*$I$3*'MSET pivots'!L$65 -> 3233597.5 | ... AL19: =VLOOKUP($C19,'MSET pivots'!$B$4:$H$14,$H$3,FALSE)*1000000*$I$3*'MSET pivots'!S$65 -> 4850372
C20: LAC | E20: LAC | F20: ALL | G20: ALL | H20: Household final consumption P.3h | I20: FD_1 | J20: abs-b | K20: =SUM(X20:AL20)/1000000 -> 35.970131 | X20: =VLOOKUP($C20,'MSET pivots'!$B$4:$H$14,$H$3,FALSE)*1000000*$I$2*'MSET pivots'!E$65 -> 1199022.4 | Y20: =VLOOKUP($C20,'MSET pivots'!$B$4:$H$14,$H$3,FALSE)*1000000*$I$2*'MSET pivots'!F$65 -> 1370306.1 | Z20: =VLOOKUP($C20,'MSET pivots'!$B$4:$H$14,$H$3,FALSE)*1000000*$I$2*'MSET pivots'!G$65 -> 1541589.9 | AA20: =VLOOKUP($C20,'MSET pivots'!$B$4:$H$14,$H$3,FALSE)*1000000*$I$2*'MSET pivots'!H$65 -> 1712873.7 | AB20: =VLOOKUP($C20,'MSET pivots'!$B$4:$H$14,$H$3,FALSE)*1000000*$I$2*'MSET pivots'!I$65 -> 1884157.5 | AC20: =VLOOKUP($C20,'MSET pivots'!$B$4:$H$14,$H$3,FALSE)*1000000*$I$2*'MSET pivots'!J$65 -> 2055441.2 | AD20: =VLOOKUP($C20,'MSET pivots'!$B$4:$H$14,$H$3,FALSE)*1000000*$I$2*'MSET pivots'!K$65 -> 2226725 | AE20: =VLOOKUP($C20,'MSET pivots'!$B$4:$H$14,$H$3,FALSE)*1000000*$I$2*'MSET pivots'!L$65 -> 2398008.8 | ... AL20: =VLOOKUP($C20,'MSET pivots'!$B$4:$H$14,$H$3,FALSE)*1000000*$I$2*'MSET pivots'!S$65 -> 3596995.2
C21: LAC | E21: LAC | F21: ALL | G21: ALL | H21: Government final consumption P.3g | I21: FD_3 | J21: abs-b | K21: =SUM(X21:AL21)/1000000 -> 35.970131 | X21: =VLOOKUP($C21,'MSET pivots'!$B$4:$H$14,$H$3,FALSE)*1000000*$I$3*'MSET pivots'!E$65 -> 1199022.4 | Y21: =VLOOKUP($C21,'MSET pivots'!$B$4:$H$14,$H$3,FALSE)*1000000*$I$3*'MSET pivots'!F$65 -> 1370306.1 | Z21: =VLOOKUP($C21,'MSET pivots'!$B$4:$H$14,$H$3,FALSE)*1000000*$I$3*'MSET pivots'!G$65 -> 1541589.9 | AA21: =VLOOKUP($C21,'MSET pivots'!$B$4:$H$14,$H$3,FALSE)*1000000*$I$3*'MSET pivots'!H$65 -> 1712873.7 | AB21: =VLOOKUP($C21,'MSET pivots'!$B$4:$H$14,$H$3,FALSE)*1000000*$I$3*'MSET pivots'!I$65 -> 1884157.5 | AC21: =VLOOKUP($C21,'MSET pivots'!$B$4:$H$14,$H$3,FALSE)*1000000*$I$3*'MSET pivots'!J$65 -> 2055441.2 | AD21: =VLOOKUP($C21,'MSET pivots'!$B$4:$H$14,$H$3,FALSE)*1000000*$I$3*'MSET pivots'!K$65 -> 2226725 | AE21: =VLOOKUP($C21,'MSET pivots'!$B$4:$H$14,$H$3,FALSE)*1000000*$I$3*'MSET pivots'!L$65 -> 2398008.8 | ... AL21: =VLOOKUP($C21,'MSET pivots'!$B$4:$H$14,$H$3,FALSE)*1000000*$I$3*'MSET pivots'!S$65 -> 3596995.2
B22: Pakistan | C22: SAS | E22: SAS | F22: ALL | G22: ALL | H22: Household final consumption P.3h | I22: FD_1 | J22: abs-b | K22: =SUM(X22:AL22)/1000000 -> 44.85523 | W22: ='Preliminary results'!$C$31*1000000*I2 -> 902060.73 | X22: =VLOOKUP($C22,'MSET pivots'!$B$4:$H$14,$H$3,FALSE)*1000000*$I$2*'MSET pivots'!E$65 -> 1495196.8 | Y22: =VLOOKUP($C22,'MSET pivots'!$B$4:$H$14,$H$3,FALSE)*1000000*$I$2*'MSET pivots'!F$65 -> 1708789.9 | Z22: =VLOOKUP($C22,'MSET pivots'!$B$4:$H$14,$H$3,FALSE)*1000000*$I$2*'MSET pivots'!G$65 -> 1922383 | AA22: =VLOOKUP($C22,'MSET pivots'!$B$4:$H$14,$H$3,FALSE)*1000000*$I$2*'MSET pivots'!H$65 -> 2135976.2 | AB22: =VLOOKUP($C22,'MSET pivots'!$B$4:$H$14,$H$3,FALSE)*1000000*$I$2*'MSET pivots'!I$65 -> 2349569.3 | AC22: =VLOOKUP($C22,'MSET pivots'!$B$4:$H$14,$H$3,FALSE)*1000000*$I$2*'MSET pivots'!J$65 -> 2563162.4 | AD22: =VLOOKUP($C22,'MSET pivots'!$B$4:$H$14,$H$3,FALSE)*1000000*$I$2*'MSET pivots'!K$65 -> 2776755.5 | AE22: =VLOOKUP($C22,'MSET pivots'!$B$4:$H$14,$H$3,FALSE)*1000000*$I$2*'MSET pivots'!L$65 -> 2990348.7 | ... AL22: =VLOOKUP($C22,'MSET pivots'!$B$4:$H$14,$H$3,FALSE)*1000000*$I$2*'MSET pivots'!S$65 -> 4485500.6
B23: Pakistan | C23: SAS | E23: SAS | F23: ALL | G23: ALL | H23: Government final consumption P.3g | I23: FD_3 | J23: abs-b | K23: =SUM(X23:AL23)/1000000 -> 44.85523 | W23: ='Preliminary results'!$C$31*1000000*I3 -> 902060.73 | X23: =VLOOKUP($C23,'MSET pivots'!$B$4:$H$14,$H$3,FALSE)*1000000*$I$3*'MSET pivots'!E$65 -> 1495196.8 | Y23: =VLOOKUP($C23,'MSET pivots'!$B$4:$H$14,$H$3,FALSE)*1000000*$I$3*'MSET pivots'!F$65 -> 1708789.9 | Z23: =VLOOKUP($C23,'MSET pivots'!$B$4:$H$14,$H$3,FALSE)*1000000*$I$3*'MSET pivots'!G$65 -> 1922383 | AA23: =VLOOKUP($C23,'MSET pivots'!$B$4:$H$14,$H$3,FALSE)*1000000*$I$3*'MSET pivots'!H$65 -> 2135976.2 | AB23: =VLOOKUP($C23,'MSET pivots'!$B$4:$H$14,$H$3,FALSE)*1000000*$I$3*'MSET pivots'!I$65 -> 2349569.3 | AC23: =VLOOKUP($C23,'MSET pivots'!$B$4:$H$14,$H$3,FALSE)*1000000*$I$3*'MSET pivots'!J$65 -> 2563162.4 | AD23: =VLOOKUP($C23,'MSET pivots'!$B$4:$H$14,$H$3,FALSE)*1000000*$I$3*'MSET pivots'!K$65 -> 2776755.5 | AE23: =VLOOKUP($C23,'MSET pivots'!$B$4:$H$14,$H$3,FALSE)*1000000*$I$3*'MSET pivots'!L$65 -> 2990348.7 | ... AL23: =VLOOKUP($C23,'MSET pivots'!$B$4:$H$14,$H$3,FALSE)*1000000*$I$3*'MSET pivots'!S$65 -> 4485500.6
C24: AJN | E24: AJN | F24: ALL | G24: ALL | H24: Government final consumption P.3g | I24: FD_3 | J24: rel-b | K24: =SUM(X24:AL24) -> -0.037241155 | X24: =VLOOKUP($C24,'MSET pivots'!$J$4:$P$14,'Final demand(4)'!$H$3,FALSE)*'MSET pivots'!E$65 -> -0.0012413904 | Y24: =VLOOKUP($C24,'MSET pivots'!$J$4:$P$14,'Final demand(4)'!$H$3,FALSE)*'MSET pivots'!F$65 -> -0.0014187266 | Z24: =VLOOKUP($C24,'MSET pivots'!$J$4:$P$14,'Final demand(4)'!$H$3,FALSE)*'MSET pivots'!G$65 -> -0.0015960628 | AA24: =VLOOKUP($C24,'MSET pivots'!$J$4:$P$14,'Final demand(4)'!$H$3,FALSE)*'MSET pivots'!H$65 -> -0.001773399 | AB24: =VLOOKUP($C24,'MSET pivots'!$J$4:$P$14,'Final demand(4)'!$H$3,FALSE)*'MSET pivots'!I$65 -> -0.0019507351 | AC24: =VLOOKUP($C24,'MSET pivots'!$J$4:$P$14,'Final demand(4)'!$H$3,FALSE)*'MSET pivots'!J$65 -> -0.0021280713 | AD24: =VLOOKUP($C24,'MSET pivots'!$J$4:$P$14,'Final demand(4)'!$H$3,FALSE)*'MSET pivots'!K$65 -> -0.0023054075 | AE24: =VLOOKUP($C24,'MSET pivots'!$J$4:$P$14,'Final demand(4)'!$H$3,FALSE)*'MSET pivots'!L$65 -> -0.0024827436 | ... AL24: =VLOOKUP($C24,'MSET pivots'!$J$4:$P$14,'Final demand(4)'!$H$3,FALSE)*'MSET pivots'!S$65 -> -0.0037240968
C25: EAS | E25: EAS | F25: ALL | G25: ALL | H25: Government final consumption P.3g | I25: FD_3 | J25: rel-b | K25: =SUM(X25:AL25) -> -0.019179201 | X25: =VLOOKUP($C25,'MSET pivots'!$J$4:$P$14,'Final demand(4)'!$H$3,FALSE)*'MSET pivots'!E$65 -> -0.0006393163 | Y25: =VLOOKUP($C25,'MSET pivots'!$J$4:$P$14,'Final demand(4)'!$H$3,FALSE)*'MSET pivots'!F$65 -> -0.00073064446 | Z25: =VLOOKUP($C25,'MSET pivots'!$J$4:$P$14,'Final demand(4)'!$H$3,FALSE)*'MSET pivots'!G$65 -> -0.00082197262 | AA25: =VLOOKUP($C25,'MSET pivots'!$J$4:$P$14,'Final demand(4)'!$H$3,FALSE)*'MSET pivots'!H$65 -> -0.00091330078 | AB25: =VLOOKUP($C25,'MSET pivots'!$J$4:$P$14,'Final demand(4)'!$H$3,FALSE)*'MSET pivots'!I$65 -> -0.0010046289 | AC25: =VLOOKUP($C25,'MSET pivots'!$J$4:$P$14,'Final demand(4)'!$H$3,FALSE)*'MSET pivots'!J$65 -> -0.0010959571 | AD25: =VLOOKUP($C25,'MSET pivots'!$J$4:$P$14,'Final demand(4)'!$H$3,FALSE)*'MSET pivots'!K$65 -> -0.0011872853 | AE25: =VLOOKUP($C25,'MSET pivots'!$J$4:$P$14,'Final demand(4)'!$H$3,FALSE)*'MSET pivots'!L$65 -> -0.0012786134 | ... AL25: =VLOOKUP($C25,'MSET pivots'!$J$4:$P$14,'Final demand(4)'!$H$3,FALSE)*'MSET pivots'!S$65 -> -0.0019179105
C26: EEA | E26: EEA | F26: ALL | G26: ALL | H26: Government final consumption P.3g | I26: FD_3 | J26: rel-b | K26: =SUM(X26:AL26) -> -0.039847267 | X26: =VLOOKUP($C26,'MSET pivots'!$J$4:$P$14,'Final demand(4)'!$H$3,FALSE)*'MSET pivots'!E$65 -> -0.0013282621 | Y26: =VLOOKUP($C26,'MSET pivots'!$J$4:$P$14,'Final demand(4)'!$H$3,FALSE)*'MSET pivots'!F$65 -> -0.0015180082 | Z26: =VLOOKUP($C26,'MSET pivots'!$J$4:$P$14,'Final demand(4)'!$H$3,FALSE)*'MSET pivots'!G$65 -> -0.0017077542 | AA26: =VLOOKUP($C26,'MSET pivots'!$J$4:$P$14,'Final demand(4)'!$H$3,FALSE)*'MSET pivots'!H$65 -> -0.0018975003 | AB26: =VLOOKUP($C26,'MSET pivots'!$J$4:$P$14,'Final demand(4)'!$H$3,FALSE)*'MSET pivots'!I$65 -> -0.0020872463 | AC26: =VLOOKUP($C26,'MSET pivots'!$J$4:$P$14,'Final demand(4)'!$H$3,FALSE)*'MSET pivots'!J$65 -> -0.0022769924 | AD26: =VLOOKUP($C26,'MSET pivots'!$J$4:$P$14,'Final demand(4)'!$H$3,FALSE)*'MSET pivots'!K$65 -> -0.0024667384 | AE26: =VLOOKUP($C26,'MSET pivots'!$J$4:$P$14,'Final demand(4)'!$H$3,FALSE)*'MSET pivots'!L$65 -> -0.0026564844 | ... AL26: =VLOOKUP($C26,'MSET pivots'!$J$4:$P$14,'Final demand(4)'!$H$3,FALSE)*'MSET pivots'!S$65 -> -0.0039847067
B27: United Kingdom | C27: EUR | E27: EUR | F27: ALL | G27: ALL | H27: Government final consumption P.3g | I27: FD_3 | J27: rel-b | K27: =SUM(X27:AL27) -> -0.029015 | W27: =('Preliminary results'!$C$31)/'Baseline govt spend'!$E$51 -> 0.00066729533 | X27: =VLOOKUP($C27,'MSET pivots'!$J$4:$P$14,'Final demand(4)'!$H$3,FALSE)*'MSET pivots'!E$65 -> -0.00096718118 | Y27: =VLOOKUP($C27,'MSET pivots'!$J$4:$P$14,'Final demand(4)'!$H$3,FALSE)*'MSET pivots'!F$65 -> -0.0011053458 | Z27: =VLOOKUP($C27,'MSET pivots'!$J$4:$P$14,'Final demand(4)'!$H$3,FALSE)*'MSET pivots'!G$65 -> -0.0012435104 | AA27: =VLOOKUP($C27,'MSET pivots'!$J$4:$P$14,'Final demand(4)'!$H$3,FALSE)*'MSET pivots'!H$65 -> -0.001381675 | AB27: =VLOOKUP($C27,'MSET pivots'!$J$4:$P$14,'Final demand(4)'!$H$3,FALSE)*'MSET pivots'!I$65 -> -0.0015198396 | AC27: =VLOOKUP($C27,'MSET pivots'!$J$4:$P$14,'Final demand(4)'!$H$3,FALSE)*'MSET pivots'!J$65 -> -0.0016580042 | AD27: =VLOOKUP($C27,'MSET pivots'!$J$4:$P$14,'Final demand(4)'!$H$3,FALSE)*'MSET pivots'!K$65 -> -0.0017961688 | AE27: =VLOOKUP($C27,'MSET pivots'!$J$4:$P$14,'Final demand(4)'!$H$3,FALSE)*'MSET pivots'!L$65 -> -0.0019343334 | ... AL27: =VLOOKUP($C27,'MSET pivots'!$J$4:$P$14,'Final demand(4)'!$H$3,FALSE)*'MSET pivots'!S$65 -> -0.0029014855
C28: MEN | E28: MEN | F28: ALL | G28: ALL | H28: Government final consumption P.3g | I28: FD_3 | J28: rel-b | K28: =SUM(X28:AL28) -> -0.010108116 | X28: =VLOOKUP($C28,'MSET pivots'!$J$4:$P$14,'Final demand(4)'!$H$3,FALSE)*'MSET pivots'!E$65 -> -0.00033694226 | Y28: =VLOOKUP($C28,'MSET pivots'!$J$4:$P$14,'Final demand(4)'!$H$3,FALSE)*'MSET pivots'!F$65 -> -0.00038507542 | Z28: =VLOOKUP($C28,'MSET pivots'!$J$4:$P$14,'Final demand(4)'!$H$3,FALSE)*'MSET pivots'!G$65 -> -0.00043320859 | AA28: =VLOOKUP($C28,'MSET pivots'!$J$4:$P$14,'Final demand(4)'!$H$3,FALSE)*'MSET pivots'!H$65 -> -0.00048134175 | AB28: =VLOOKUP($C28,'MSET pivots'!$J$4:$P$14,'Final demand(4)'!$H$3,FALSE)*'MSET pivots'!I$65 -> -0.00052947491 | AC28: =VLOOKUP($C28,'MSET pivots'!$J$4:$P$14,'Final demand(4)'!$H$3,FALSE)*'MSET pivots'!J$65 -> -0.00057760808 | AD28: =VLOOKUP($C28,'MSET pivots'!$J$4:$P$14,'Final demand(4)'!$H$3,FALSE)*'MSET pivots'!K$65 -> -0.00062574124 | AE28: =VLOOKUP($C28,'MSET pivots'!$J$4:$P$14,'Final demand(4)'!$H$3,FALSE)*'MSET pivots'!L$65 -> -0.00067387441 | ... AL28: =VLOOKUP($C28,'MSET pivots'!$J$4:$P$14,'Final demand(4)'!$H$3,FALSE)*'MSET pivots'!S$65 -> -0.0010108066
C29: NAM | E29: NAM | F29: ALL | G29: ALL | H29: Government final consumption P.3g | I29: FD_3 | J29: rel-b | K29: =SUM(X29:AL29) -> -0.080540345 | X29: =VLOOKUP($C29,'MSET pivots'!$J$4:$P$14,'Final demand(4)'!$H$3,FALSE)*'MSET pivots'!E$65 -> -0.0026847184 | Y29: =VLOOKUP($C29,'MSET pivots'!$J$4:$P$14,'Final demand(4)'!$H$3,FALSE)*'MSET pivots'!F$65 -> -0.0030682381 | Z29: =VLOOKUP($C29,'MSET pivots'!$J$4:$P$14,'Final demand(4)'!$H$3,FALSE)*'MSET pivots'!G$65 -> -0.0034517578 | AA29: =VLOOKUP($C29,'MSET pivots'!$J$4:$P$14,'Final demand(4)'!$H$3,FALSE)*'MSET pivots'!H$65 -> -0.0038352775 | AB29: =VLOOKUP($C29,'MSET pivots'!$J$4:$P$14,'Final demand(4)'!$H$3,FALSE)*'MSET pivots'!I$65 -> -0.0042187972 | AC29: =VLOOKUP($C29,'MSET pivots'!$J$4:$P$14,'Final demand(4)'!$H$3,FALSE)*'MSET pivots'!J$65 -> -0.0046023169 | AD29: =VLOOKUP($C29,'MSET pivots'!$J$4:$P$14,'Final demand(4)'!$H$3,FALSE)*'MSET pivots'!K$65 -> -0.0049858366 | AE29: =VLOOKUP($C29,'MSET pivots'!$J$4:$P$14,'Final demand(4)'!$H$3,FALSE)*'MSET pivots'!L$65 -> -0.0053693563 | ... AL29: =VLOOKUP($C29,'MSET pivots'!$J$4:$P$14,'Final demand(4)'!$H$3,FALSE)*'MSET pivots'!S$65 -> -0.0080539942
G42: =_xlfn.IFNA(INDEX('[1]Sector list'!$A$2:$A$122,MATCH(F42,'[1]Sector list'!$B$2:$B$122,0)),"") | I42: =_xlfn.IFNA(INDEX('[1]FD list'!$A$2:$A$122,MATCH(H42,'[1]FD list'!$B$2:$B$122,0)),"")
G43: =_xlfn.IFNA(INDEX('[1]Sector list'!$A$2:$A$122,MATCH(F43,'[1]Sector list'!$B$2:$B$122,0)),"") | I43: =_xlfn.IFNA(INDEX('[1]FD list'!$A$2:$A$122,MATCH(H43,'[1]FD list'!$B$2:$B$122,0)),"")
G44: =_xlfn.IFNA(INDEX('[1]Sector list'!$A$2:$A$122,MATCH(F44,'[1]Sector list'!$B$2:$B$122,0)),"") | I44: =_xlfn.IFNA(INDEX('[1]FD list'!$A$2:$A$122,MATCH(H44,'[1]FD list'!$B$2:$B$122,0)),"")
G45: =_xlfn.IFNA(INDEX('[1]Sector list'!$A$2:$A$122,MATCH(F45,'[1]Sector list'!$B$2:$B$122,0)),"") | I45: =_xlfn.IFNA(INDEX('[1]FD list'!$A$2:$A$122,MATCH(H45,'[1]FD list'!$B$2:$B$122,0)),"")
G46: =_xlfn.IFNA(INDEX('[1]Sector list'!$A$2:$A$122,MATCH(F46,'[1]Sector list'!$B$2:$B$122,0)),"") | I46: =_xlfn.IFNA(INDEX('[1]FD list'!$A$2:$A$122,MATCH(H46,'[1]FD list'!$B$2:$B$122,0)),"")
G47: =_xlfn.IFNA(INDEX('[1]Sector list'!$A$2:$A$122,MATCH(F47,'[1]Sector list'!$B$2:$B$122,0)),"") | I47: =_xlfn.IFNA(INDEX('[1]FD list'!$A$2:$A$122,MATCH(H47,'[1]FD list'!$B$2:$B$122,0)),"")
G48: =_xlfn.IFNA(INDEX('[1]Sector list'!$A$2:$A$122,MATCH(F48,'[1]Sector list'!$B$2:$B$122,0)),"") | I48: =_xlfn.IFNA(INDEX('[1]FD list'!$A$2:$A$122,MATCH(H48,'[1]FD list'!$B$2:$B$122,0)),"")
G49: =_xlfn.IFNA(INDEX('[1]Sector list'!$A$2:$A$122,MATCH(F49,'[1]Sector list'!$B$2:$B$122,0)),"") | I49: =_xlfn.IFNA(INDEX('[1]FD list'!$A$2:$A$122,MATCH(H49,'[1]FD list'!$B$2:$B$122,0)),"")
G50: =_xlfn.IFNA(INDEX('[1]Sector list'!$A$2:$A$122,MATCH(F50,'[1]Sector list'!$B$2:$B$122,0)),"") | I50: =_xlfn.IFNA(INDEX('[1]FD list'!$A$2:$A$122,MATCH(H50,'[1]FD list'!$B$2:$B$122,0)),"")
G51: =_xlfn.IFNA(INDEX('[1]Sector list'!$A$2:$A$122,MATCH(F51,'[1]Sector list'!$B$2:$B$122,0)),"") | I51: =_xlfn.IFNA(INDEX('[1]FD list'!$A$2:$A$122,MATCH(H51,'[1]FD list'!$B$2:$B$122,0)),"")
G52: =_xlfn.IFNA(INDEX('[1]Sector list'!$A$2:$A$122,MATCH(F52,'[1]Sector list'!$B$2:$B$122,0)),"") | I52: =_xlfn.IFNA(INDEX('[1]FD list'!$A$2:$A$122,MATCH(H52,'[1]FD list'!$B$2:$B$122,0)),"")
G53: =_xlfn.IFNA(INDEX('[1]Sector list'!$A$2:$A$122,MATCH(F53,'[1]Sector list'!$B$2:$B$122,0)),"") | I53: =_xlfn.IFNA(INDEX('[1]FD list'!$A$2:$A$122,MATCH(H53,'[1]FD list'!$B$2:$B$122,0)),"")
... G67: =_xlfn.IFNA(INDEX('[1]Sector list'!$A$2:$A$122,MATCH(F67,'[1]Sector list'!$B$2:$B$122,0)),"") | I67: =_xlfn.IFNA(INDEX('[1]FD list'!$A$2:$A$122,MATCH(H67,'[1]FD list'!$B$2:$B$122,0)),"")
I68: =_xlfn.IFNA(INDEX('[1]FD list'!$A$2:$A$122,MATCH(H68,'[1]FD list'!$B$2:$B$122,0)),"")
I69: =_xlfn.IFNA(INDEX('[1]FD list'!$A$2:$A$122,MATCH(H69,'[1]FD list'!$B$2:$B$122,0)),"")
I70: =_xlfn.IFNA(INDEX('[1]FD list'!$A$2:$A$122,MATCH(H70,'[1]FD list'!$B$2:$B$122,0)),"")
I71: =_xlfn.IFNA(INDEX('[1]FD list'!$A$2:$A$122,MATCH(H71,'[1]FD list'!$B$2:$B$122,0)),"")
I72: =_xlfn.IFNA(INDEX('[1]FD list'!$A$2:$A$122,MATCH(H72,'[1]FD list'!$B$2:$B$122,0)),"")
I73: =_xlfn.IFNA(INDEX('[1]FD list'!$A$2:$A$122,MATCH(H73,'[1]FD list'!$B$2:$B$122,0)),"")
I74: =_xlfn.IFNA(INDEX('[1]FD list'!$A$2:$A$122,MATCH(H74,'[1]FD list'!$B$2:$B$122,0)),"")
I75: =_xlfn.IFNA(INDEX('[1]FD list'!$A$2:$A$122,MATCH(H75,'[1]FD list'!$B$2:$B$122,0)),"")
I76: =_xlfn.IFNA(INDEX('[1]FD list'!$A$2:$A$122,MATCH(H76,'[1]FD list'!$B$2:$B$122,0)),"")
I77: =_xlfn.IFNA(INDEX('[1]FD list'!$A$2:$A$122,MATCH(H77,'[1]FD list'!$B$2:$B$122,0)),"")
I78: =_xlfn.IFNA(INDEX('[1]FD list'!$A$2:$A$122,MATCH(H78,'[1]FD list'!$B$2:$B$122,0)),"")
I79: =_xlfn.IFNA(INDEX('[1]FD list'!$A$2:$A$122,MATCH(H79,'[1]FD list'!$B$2:$B$122,0)),"")
... I95: =_xlfn.IFNA(INDEX('[1]FD list'!$A$2:$A$122,MATCH(H95,'[1]FD list'!$B$2:$B$122,0)),"")
I96: =_xlfn.IFNA(INDEX('[1]Sector list'!$A$2:$A$122,MATCH(H96,'[1]Sector list'!$B$2:$B$122,0)),"")
I97: =_xlfn.IFNA(INDEX('[1]Sector list'!$A$2:$A$122,MATCH(H97,'[1]Sector list'!$B$2:$B$122,0)),"")
I98: =_xlfn.IFNA(INDEX('[1]Sector list'!$A$2:$A$122,MATCH(H98,'[1]Sector list'!$B$2:$B$122,0)),"")
I99: =_xlfn.IFNA(INDEX('[1]Sector list'!$A$2:$A$122,MATCH(H99,'[1]Sector list'!$B$2:$B$122,0)),"")
I100: =_xlfn.IFNA(INDEX('[1]Sector list'!$A$2:$A$122,MATCH(H100,'[1]Sector list'!$B$2:$B$122,0)),"")
I101: =_xlfn.IFNA(INDEX('[1]Sector list'!$A$2:$A$122,MATCH(H101,'[1]Sector list'!$B$2:$B$122,0)),"")
I102: =_xlfn.IFNA(INDEX('[1]Sector list'!$A$2:$A$122,MATCH(H102,'[1]Sector list'!$B$2:$B$122,0)),"")
I103: =_xlfn.IFNA(INDEX('[1]Sector list'!$A$2:$A$122,MATCH(H103,'[1]Sector list'!$B$2:$B$122,0)),"")
I104: =_xlfn.IFNA(INDEX('[1]Sector list'!$A$2:$A$122,MATCH(H104,'[1]Sector list'!$B$2:$B$122,0)),"")
I105: =_xlfn.IFNA(INDEX('[1]Sector list'!$A$2:$A$122,MATCH(H105,'[1]Sector list'!$B$2:$B$122,0)),"")
I106: =_xlfn.IFNA(INDEX('[1]Sector list'!$A$2:$A$122,MATCH(H106,'[1]Sector list'!$B$2:$B$122,0)),"")
I107: =_xlfn.IFNA(INDEX('[1]Sector list'!$A$2:$A$122,MATCH(H107,'[1]Sector list'!$B$2:$B$122,0)),"")
... I903: =_xlfn.IFNA(INDEX('[1]Sector list'!$A$2:$A$122,MATCH(H903,'[1]Sector list'!$B$2:$B$122,0)),"")

Sheet Investment by(4)
B2: Investment BY sector changes | G2: ='Final demand(4)'!H2 -> CVF_upper | H2: ='Final demand(4)'!H3 -> 4
B3: Fields with * must be specified manually or filled in automatically by selecting values in other columns
B5: Country | C5: Country ISO* | D5: Sector investing | E5: Sector investing code* | F5: Type* | G5: Comments
G6: =1/3 -> 0.33333333 | H6: FCF
B8: Germany | C8: =_xlfn.IFNA(INDEX('[2]Country list'!$A$2:$A$166,MATCH(B8,'[2]Country list'!$B$2:$B$166,0)),"") -> DEU | E8: 1-23 | F8: abs | G8: << Increase investment in agricultural sectors in Germany, 1000 kUSD in EVERY sector
G12: relative investment is not possible, because we don’t have an investment baseline right now
C13: REG_imp | E13: PROD_COMM | G13: Current options: abs-b
B14: Start in the next line >>
B15: Country | C15: Country ISO* | D15: Sector investing | E15: Sector investing code* | F15: Type* | G15: Comments | H15: 2019 | I15: 2020 | J15: 2021 | K15: 2022 | L15: 2023 | M15: 2024 | N15: 2025 | O15: 2026 | P15: 2027 | Q15: 2028 | R15: 2029 | S15: 2030 | T15: 2031 | U15: 2032 | V15: 2033 | W15: 2034 | X15: 2035 | Y15: 2036 | Z15: 2037 | AA15: 2038 | AB15: 2039 | AC15: 2040 | AD15: 2041 | AE15: 2042 | AF15: 2043 | AG15: 2044 | AH15: 2045 | AI15: 2046 | AJ15: 2047 | AK15: 2048 | AL15: 2049 | AM15: 2050
C16: SEP | E16: ALL | F16: abs-b | G16: =SUM(T16:AH16)/1000000 -> 46.609068 | T16: =VLOOKUP($C16,'MSET pivots'!$B$4:$H$14,$H$2,FALSE)*1000000*$G$6*'MSET pivots'!E$65 -> 1553658.9 | U16: =VLOOKUP($C16,'MSET pivots'!$B$4:$H$14,$H$2,FALSE)*1000000*$G$6*'MSET pivots'!F$65 -> 1775603.5 | V16: =VLOOKUP($C16,'MSET pivots'!$B$4:$H$14,$H$2,FALSE)*1000000*$G$6*'MSET pivots'!G$65 -> 1997548.1 | W16: =VLOOKUP($C16,'MSET pivots'!$B$4:$H$14,$H$2,FALSE)*1000000*$G$6*'MSET pivots'!H$65 -> 2219492.7 | X16: =VLOOKUP($C16,'MSET pivots'!$B$4:$H$14,$H$2,FALSE)*1000000*$G$6*'MSET pivots'!I$65 -> 2441437.4 | Y16: =VLOOKUP($C16,'MSET pivots'!$B$4:$H$14,$H$2,FALSE)*1000000*$G$6*'MSET pivots'!J$65 -> 2663382 | Z16: =VLOOKUP($C16,'MSET pivots'!$B$4:$H$14,$H$2,FALSE)*1000000*$G$6*'MSET pivots'!K$65 -> 2885326.6 | AA16: =VLOOKUP($C16,'MSET pivots'!$B$4:$H$14,$H$2,FALSE)*1000000*$G$6*'MSET pivots'!L$65 -> 3107271.2 | ... AH16: =VLOOKUP($C16,'MSET pivots'!$B$4:$H$14,$H$2,FALSE)*1000000*$G$6*'MSET pivots'!S$65 -> 4660883.5
C17: AFR | E17: ALL | F17: abs-b | G17: =SUM(T17:AH17)/1000000 -> 48.503963 | T17: =VLOOKUP($C17,'MSET pivots'!$B$4:$H$14,$H$2,FALSE)*1000000*$G$6*'MSET pivots'!E$65 -> 1616823 | U17: =VLOOKUP($C17,'MSET pivots'!$B$4:$H$14,$H$2,FALSE)*1000000*$G$6*'MSET pivots'!F$65 -> 1847790.8 | V17: =VLOOKUP($C17,'MSET pivots'!$B$4:$H$14,$H$2,FALSE)*1000000*$G$6*'MSET pivots'!G$65 -> 2078758.6 | W17: =VLOOKUP($C17,'MSET pivots'!$B$4:$H$14,$H$2,FALSE)*1000000*$G$6*'MSET pivots'!H$65 -> 2309726.4 | X17: =VLOOKUP($C17,'MSET pivots'!$B$4:$H$14,$H$2,FALSE)*1000000*$G$6*'MSET pivots'!I$65 -> 2540694.2 | Y17: =VLOOKUP($C17,'MSET pivots'!$B$4:$H$14,$H$2,FALSE)*1000000*$G$6*'MSET pivots'!J$65 -> 2771662 | Z17: =VLOOKUP($C17,'MSET pivots'!$B$4:$H$14,$H$2,FALSE)*1000000*$G$6*'MSET pivots'!K$65 -> 3002629.7 | AA17: =VLOOKUP($C17,'MSET pivots'!$B$4:$H$14,$H$2,FALSE)*1000000*$G$6*'MSET pivots'!L$65 -> 3233597.5 | ... AH17: =VLOOKUP($C17,'MSET pivots'!$B$4:$H$14,$H$2,FALSE)*1000000*$G$6*'MSET pivots'!S$65 -> 4850372
C18: LAC | E18: ALL | F18: abs-b | G18: =SUM(T18:AH18)/1000000 -> 35.970131 | T18: =VLOOKUP($C18,'MSET pivots'!$B$4:$H$14,$H$2,FALSE)*1000000*$G$6*'MSET pivots'!E$65 -> 1199022.4 | U18: =VLOOKUP($C18,'MSET pivots'!$B$4:$H$14,$H$2,FALSE)*1000000*$G$6*'MSET pivots'!F$65 -> 1370306.1 | V18: =VLOOKUP($C18,'MSET pivots'!$B$4:$H$14,$H$2,FALSE)*1000000*$G$6*'MSET pivots'!G$65 -> 1541589.9 | W18: =VLOOKUP($C18,'MSET pivots'!$B$4:$H$14,$H$2,FALSE)*1000000*$G$6*'MSET pivots'!H$65 -> 1712873.7 | X18: =VLOOKUP($C18,'MSET pivots'!$B$4:$H$14,$H$2,FALSE)*1000000*$G$6*'MSET pivots'!I$65 -> 1884157.5 | Y18: =VLOOKUP($C18,'MSET pivots'!$B$4:$H$14,$H$2,FALSE)*1000000*$G$6*'MSET pivots'!J$65 -> 2055441.2 | Z18: =VLOOKUP($C18,'MSET pivots'!$B$4:$H$14,$H$2,FALSE)*1000000*$G$6*'MSET pivots'!K$65 -> 2226725 | AA18: =VLOOKUP($C18,'MSET pivots'!$B$4:$H$14,$H$2,FALSE)*1000000*$G$6*'MSET pivots'!L$65 -> 2398008.8 | ... AH18: =VLOOKUP($C18,'MSET pivots'!$B$4:$H$14,$H$2,FALSE)*1000000*$G$6*'MSET pivots'!S$65 -> 3596995.2
C19: SAS | E19: ALL | F19: abs-b | G19: =SUM(T19:AH19)/1000000 -> 44.85523 | S19: ='Preliminary results'!$C$31*1000000*G6 -> 902060.73 | T19: =VLOOKUP($C19,'MSET pivots'!$B$4:$H$14,$H$2,FALSE)*1000000*$G$6*'MSET pivots'!E$65 -> 1495196.8 | U19: =VLOOKUP($C19,'MSET pivots'!$B$4:$H$14,$H$2,FALSE)*1000000*$G$6*'MSET pivots'!F$65 -> 1708789.9 | V19: =VLOOKUP($C19,'MSET pivots'!$B$4:$H$14,$H$2,FALSE)*1000000*$G$6*'MSET pivots'!G$65 -> 1922383 | W19: =VLOOKUP($C19,'MSET pivots'!$B$4:$H$14,$H$2,FALSE)*1000000*$G$6*'MSET pivots'!H$65 -> 2135976.2 | X19: =VLOOKUP($C19,'MSET pivots'!$B$4:$H$14,$H$2,FALSE)*1000000*$G$6*'MSET pivots'!I$65 -> 2349569.3 | Y19: =VLOOKUP($C19,'MSET pivots'!$B$4:$H$14,$H$2,FALSE)*1000000*$G$6*'MSET pivots'!J$65 -> 2563162.4 | Z19: =VLOOKUP($C19,'MSET pivots'!$B$4:$H$14,$H$2,FALSE)*1000000*$G$6*'MSET pivots'!K$65 -> 2776755.5 | AA19: =VLOOKUP($C19,'MSET pivots'!$B$4:$H$14,$H$2,FALSE)*1000000*$G$6*'MSET pivots'!L$65 -> 2990348.7 | ... AH19: =VLOOKUP($C19,'MSET pivots'!$B$4:$H$14,$H$2,FALSE)*1000000*$G$6*'MSET pivots'!S$65 -> 4485500.6

Sheet Final demand(5)
B2: Final demand changes (consumption, govt, etc) | H2: G77+C_lower | I2: =1/3 -> 0.33333333 | J2: hh
B3: Fields with * must be specified manually or filled in automatically by selecting values in other columns | H3: 5 | I3: =1/3 -> 0.33333333 | J3: gov
B5: Country | C5: Country ISO* | F5: Product | G5: Product code* | H5: Final demand category | I5: FD code* | J5: Type* | K5: Comments
B6: Italy | C6: =_xlfn.IFNA(INDEX('[1]Country list'!$A$2:$A$166,MATCH(B6,'[1]Country list'!$B$2:$B$166,0)),"") -> ITA | F6: ALL | G6: =_xlfn.IFNA(INDEX('[1]Sector list'!$A$2:$A$122,MATCH(F6,'[1]Sector list'!$B$2:$B$122,0)),"") -> ALL | H6: Household final consumption P.3h | I6: =_xlfn.IFNA(INDEX('[1]FD list'!$A$2:$A$122,MATCH(H6,'[1]FD list'!$B$2:$B$122,0)),"") -> FD_1 | J6: rel-b | K6: << Decrease final demand (HH consumption) 3% for all products in Italy
C7: ITA | F7: Pork | G7: =_xlfn.IFNA(INDEX('[1]Sector list'!$A$2:$A$122,MATCH(F7,'[1]Sector list'!$B$2:$B$122,0)),"") -> 43 | H7: ALL | I7: =_xlfn.IFNA(INDEX('[1]FD list'!$A$2:$A$122,MATCH(H7,'[1]FD list'!$B$2:$B$122,0)),"") -> ALL | J7: rel-b | K7: << Increase final demand (across all demand categories) for pork in Italy by 12% (if zero stays zero)
B8: Germany | C8: =_xlfn.IFNA(INDEX('[1]Country list'!$A$2:$A$166,MATCH(B8,'[1]Country list'!$B$2:$B$166,0)),"") -> DEU | G8: 1-23 | I8: FD_1 | J8: abs-b | K8: << Increase demand in Germany for all agricultural sectors (1-23), only for consumer demand; try NOT to use negative values as it might create issues
B9: Malawi | C9: =_xlfn.IFNA(INDEX('[1]Country list'!$A$2:$A$166,MATCH(B9,'[1]Country list'!$B$2:$B$166,0)),"") -> MWI | F9: Building construction | G9: =_xlfn.IFNA(INDEX('[1]Sector list'!$A$2:$A$122,MATCH(F9,'[1]Sector list'!$B$2:$B$122,0)),"") -> 98 | H9: Gross fixed capital formation P.51 | I9: =_xlfn.IFNA(INDEX('[1]FD list'!$A$2:$A$122,MATCH(H9,'[1]FD list'!$B$2:$B$122,0)),"") -> FD_4 | J9: rel-b | K9: << Directly decrease investment (GFCF) demand for construction sector in Malawi with 1%; NOTE: if you want to do INVESTMENT BY the sector IT SHOULD NOT BE DONE HERE
C13: REG_exp | E13: REG_imp | G13: TRAD_COMM | I13: PROD_COMM (only FD) | J13: Current options: rel-b and abs-b
B14: Start in the next line >>
B15: Producing country | C15: Producing country ISO* | D15: Consuming country | E15: Consuming country ISO* | F15: Product | G15: Product code* | H15: Final demand category | I15: FD code* | J15: Type* | K15: Comments | L15: 2019 | M15: 2020 | N15: 2021 | O15: 2022 | P15: 2023 | Q15: 2024 | R15: 2025 | S15: 2026 | T15: 2027 | U15: 2028 | V15: 2029 | W15: 2030 | X15: 2031 | Y15: 2032 | Z15: 2033 | AA15: 2034 | AB15: 2035 | AC15: 2036 | AD15: 2037 | AE15: 2038 | AF15: 2039 | AG15: 2040 | AH15: 2041 | AI15: 2042 | AJ15: 2043 | AK15: 2044 | AL15: 2045 | AM15: 2046 | AN15: 2047 | AO15: 2048 | AP15: 2049 | AQ15: 2050
C16: SEP | E16: SEP | F16: ALL | G16: ALL | H16: Household final consumption P.3h | I16: FD_1 | J16: abs-b | K16: =SUM(X16:AL16)/1000000 -> 1.2914527 | X16: =VLOOKUP($C16,'MSET pivots'!$B$4:$H$14,$H$3,FALSE)*1000000*$I$2*'MSET pivots'!E$65 -> 43049.071 | Y16: =VLOOKUP($C16,'MSET pivots'!$B$4:$H$14,$H$3,FALSE)*1000000*$I$2*'MSET pivots'!F$65 -> 49198.753 | Z16: =VLOOKUP($C16,'MSET pivots'!$B$4:$H$14,$H$3,FALSE)*1000000*$I$2*'MSET pivots'!G$65 -> 55348.436 | AA16: =VLOOKUP($C16,'MSET pivots'!$B$4:$H$14,$H$3,FALSE)*1000000*$I$2*'MSET pivots'!H$65 -> 61498.119 | AB16: =VLOOKUP($C16,'MSET pivots'!$B$4:$H$14,$H$3,FALSE)*1000000*$I$2*'MSET pivots'!I$65 -> 67647.802 | AC16: =VLOOKUP($C16,'MSET pivots'!$B$4:$H$14,$H$3,FALSE)*1000000*$I$2*'MSET pivots'!J$65 -> 73797.484 | AD16: =VLOOKUP($C16,'MSET pivots'!$B$4:$H$14,$H$3,FALSE)*1000000*$I$2*'MSET pivots'!K$65 -> 79947.167 | AE16: =VLOOKUP($C16,'MSET pivots'!$B$4:$H$14,$H$3,FALSE)*1000000*$I$2*'MSET pivots'!L$65 -> 86096.85 | ... AL16: =VLOOKUP($C16,'MSET pivots'!$B$4:$H$14,$H$3,FALSE)*1000000*$I$2*'MSET pivots'!S$65 -> 129144.63
C17: SEP | E17: SEP | F17: ALL | G17: ALL | H17: Government final consumption P.3g | I17: FD_3 | J17: abs-b | K17: =SUM(X17:AL17)/1000000 -> 1.2914527 | X17: =VLOOKUP($C17,'MSET pivots'!$B$4:$H$14,$H$3,FALSE)*1000000*$I$3*'MSET pivots'!E$65 -> 43049.071 | Y17: =VLOOKUP($C17,'MSET pivots'!$B$4:$H$14,$H$3,FALSE)*1000000*$I$3*'MSET pivots'!F$65 -> 49198.753 | Z17: =VLOOKUP($C17,'MSET pivots'!$B$4:$H$14,$H$3,FALSE)*1000000*$I$3*'MSET pivots'!G$65 -> 55348.436 | AA17: =VLOOKUP($C17,'MSET pivots'!$B$4:$H$14,$H$3,FALSE)*1000000*$I$3*'MSET pivots'!H$65 -> 61498.119 | AB17: =VLOOKUP($C17,'MSET pivots'!$B$4:$H$14,$H$3,FALSE)*1000000*$I$3*'MSET pivots'!I$65 -> 67647.802 | AC17: =VLOOKUP($C17,'MSET pivots'!$B$4:$H$14,$H$3,FALSE)*1000000*$I$3*'MSET pivots'!J$65 -> 73797.484 | AD17: =VLOOKUP($C17,'MSET pivots'!$B$4:$H$14,$H$3,FALSE)*1000000*$I$3*'MSET pivots'!K$65 -> 79947.167 | AE17: =VLOOKUP($C17,'MSET pivots'!$B$4:$H$14,$H$3,FALSE)*1000000*$I$3*'MSET pivots'!L$65 -> 86096.85 | ... AL17: =VLOOKUP($C17,'MSET pivots'!$B$4:$H$14,$H$3,FALSE)*1000000*$I$3*'MSET pivots'!S$65 -> 129144.63
C18: AFR | E18: AFR | F18: ALL | G18: ALL | H18: Household final consumption P.3h | I18: FD_1 | J18: abs-b | K18: =SUM(X18:AL18)/1000000 -> 0.94167139 | X18: =VLOOKUP($C18,'MSET pivots'!$B$4:$H$14,$H$3,FALSE)*1000000*$I$2*'MSET pivots'!E$65 -> 31389.517 | Y18: =VLOOKUP($C18,'MSET pivots'!$B$4:$H$14,$H$3,FALSE)*1000000*$I$2*'MSET pivots'!F$65 -> 35873.6 | Z18: =VLOOKUP($C18,'MSET pivots'!$B$4:$H$14,$H$3,FALSE)*1000000*$I$2*'MSET pivots'!G$65 -> 40357.682 | AA18: =VLOOKUP($C18,'MSET pivots'!$B$4:$H$14,$H$3,FALSE)*1000000*$I$2*'MSET pivots'!H$65 -> 44841.764 | AB18: =VLOOKUP($C18,'MSET pivots'!$B$4:$H$14,$H$3,FALSE)*1000000*$I$2*'MSET pivots'!I$65 -> 49325.846 | AC18: =VLOOKUP($C18,'MSET pivots'!$B$4:$H$14,$H$3,FALSE)*1000000*$I$2*'MSET pivots'!J$65 -> 53809.928 | AD18: =VLOOKUP($C18,'MSET pivots'!$B$4:$H$14,$H$3,FALSE)*1000000*$I$2*'MSET pivots'!K$65 -> 58294.011 | AE18: =VLOOKUP($C18,'MSET pivots'!$B$4:$H$14,$H$3,FALSE)*1000000*$I$2*'MSET pivots'!L$65 -> 62778.093 | ... AL18: =VLOOKUP($C18,'MSET pivots'!$B$4:$H$14,$H$3,FALSE)*1000000*$I$2*'MSET pivots'!S$65 -> 94166.669
C19: AFR | E19: AFR | F19: ALL | G19: ALL | H19: Government final consumption P.3g | I19: FD_3 | J19: abs-b | K19: =SUM(X19:AL19)/1000000 -> 0.94167139 | X19: =VLOOKUP($C19,'MSET pivots'!$B$4:$H$14,$H$3,FALSE)*1000000*$I$3*'MSET pivots'!E$65 -> 31389.517 | Y19: =VLOOKUP($C19,'MSET pivots'!$B$4:$H$14,$H$3,FALSE)*1000000*$I$3*'MSET pivots'!F$65 -> 35873.6 | Z19: =VLOOKUP($C19,'MSET pivots'!$B$4:$H$14,$H$3,FALSE)*1000000*$I$3*'MSET pivots'!G$65 -> 40357.682 | AA19: =VLOOKUP($C19,'MSET pivots'!$B$4:$H$14,$H$3,FALSE)*1000000*$I$3*'MSET pivots'!H$65 -> 44841.764 | AB19: =VLOOKUP($C19,'MSET pivots'!$B$4:$H$14,$H$3,FALSE)*1000000*$I$3*'MSET pivots'!I$65 -> 49325.846 | AC19: =VLOOKUP($C19,'MSET pivots'!$B$4:$H$14,$H$3,FALSE)*1000000*$I$3*'MSET pivots'!J$65 -> 53809.928 | AD19: =VLOOKUP($C19,'MSET pivots'!$B$4:$H$14,$H$3,FALSE)*1000000*$I$3*'MSET pivots'!K$65 -> 58294.011 | AE19: =VLOOKUP($C19,'MSET pivots'!$B$4:$H$14,$H$3,FALSE)*1000000*$I$3*'MSET pivots'!L$65 -> 62778.093 | ... AL19: =VLOOKUP($C19,'MSET pivots'!$B$4:$H$14,$H$3,FALSE)*1000000*$I$3*'MSET pivots'!S$65 -> 94166.669
C20: EAS | E20: EAS | F20: ALL | G20: ALL | H20: Household final consumption P.3h | I20: FD_1 | J20: abs-b | K20: =SUM(X20:AL20)/1000000 -> 4.8842779 | X20: =VLOOKUP($C20,'MSET pivots'!$B$4:$H$14,$H$3,FALSE)*1000000*$I$2*'MSET pivots'!E$65 -> 162811.71 | Y20: =VLOOKUP($C20,'MSET pivots'!$B$4:$H$14,$H$3,FALSE)*1000000*$I$2*'MSET pivots'!F$65 -> 186069.82 | Z20: =VLOOKUP($C20,'MSET pivots'!$B$4:$H$14,$H$3,FALSE)*1000000*$I$2*'MSET pivots'!G$65 -> 209327.94 | AA20: =VLOOKUP($C20,'MSET pivots'!$B$4:$H$14,$H$3,FALSE)*1000000*$I$2*'MSET pivots'!H$65 -> 232586.06 | AB20: =VLOOKUP($C20,'MSET pivots'!$B$4:$H$14,$H$3,FALSE)*1000000*$I$2*'MSET pivots'!I$65 -> 255844.17 | AC20: =VLOOKUP($C20,'MSET pivots'!$B$4:$H$14,$H$3,FALSE)*1000000*$I$2*'MSET pivots'!J$65 -> 279102.29 | AD20: =VLOOKUP($C20,'MSET pivots'!$B$4:$H$14,$H$3,FALSE)*1000000*$I$2*'MSET pivots'!K$65 -> 302360.41 | AE20: =VLOOKUP($C20,'MSET pivots'!$B$4:$H$14,$H$3,FALSE)*1000000*$I$2*'MSET pivots'!L$65 -> 325618.53 | ... AL20: =VLOOKUP($C20,'MSET pivots'!$B$4:$H$14,$H$3,FALSE)*1000000*$I$2*'MSET pivots'!S$65 -> 488425.35
C21: EAS | E21: EAS | F21: ALL | G21: ALL | H21: Government final consumption P.3g | I21: FD_3 | J21: abs-b | K21: =SUM(X21:AL21)/1000000 -> 4.8842779 | X21: =VLOOKUP($C21,'MSET pivots'!$B$4:$H$14,$H$3,FALSE)*1000000*$I$3*'MSET pivots'!E$65 -> 162811.71 | Y21: =VLOOKUP($C21,'MSET pivots'!$B$4:$H$14,$H$3,FALSE)*1000000*$I$3*'MSET pivots'!F$65 -> 186069.82 | Z21: =VLOOKUP($C21,'MSET pivots'!$B$4:$H$14,$H$3,FALSE)*1000000*$I$3*'MSET pivots'!G$65 -> 209327.94 | AA21: =VLOOKUP($C21,'MSET pivots'!$B$4:$H$14,$H$3,FALSE)*1000000*$I$3*'MSET pivots'!H$65 -> 232586.06 | AB21: =VLOOKUP($C21,'MSET pivots'!$B$4:$H$14,$H$3,FALSE)*1000000*$I$3*'MSET pivots'!I$65 -> 255844.17 | AC21: =VLOOKUP($C21,'MSET pivots'!$B$4:$H$14,$H$3,FALSE)*1000000*$I$3*'MSET pivots'!J$65 -> 279102.29 | AD21: =VLOOKUP($C21,'MSET pivots'!$B$4:$H$14,$H$3,FALSE)*1000000*$I$3*'MSET pivots'!K$65 -> 302360.41 | AE21: =VLOOKUP($C21,'MSET pivots'!$B$4:$H$14,$H$3,FALSE)*1000000*$I$3*'MSET pivots'!L$65 -> 325618.53 | ... AL21: =VLOOKUP($C21,'MSET pivots'!$B$4:$H$14,$H$3,FALSE)*1000000*$I$3*'MSET pivots'!S$65 -> 488425.35
C22: LAC | E22: LAC | F22: ALL | G22: ALL | H22: Household final consumption P.3h | I22: FD_1 | J22: abs-b | K22: =SUM(X22:AL22)/1000000 -> 1.1857457 | X22: =VLOOKUP($C22,'MSET pivots'!$B$4:$H$14,$H$3,FALSE)*1000000*$I$2*'MSET pivots'!E$65 -> 39525.449 | Y22: =VLOOKUP($C22,'MSET pivots'!$B$4:$H$14,$H$3,FALSE)*1000000*$I$2*'MSET pivots'!F$65 -> 45171.772 | Z22: =VLOOKUP($C22,'MSET pivots'!$B$4:$H$14,$H$3,FALSE)*1000000*$I$2*'MSET pivots'!G$65 -> 50818.095 | AA22: =VLOOKUP($C22,'MSET pivots'!$B$4:$H$14,$H$3,FALSE)*1000000*$I$2*'MSET pivots'!H$65 -> 56464.418 | AB22: =VLOOKUP($C22,'MSET pivots'!$B$4:$H$14,$H$3,FALSE)*1000000*$I$2*'MSET pivots'!I$65 -> 62110.742 | AC22: =VLOOKUP($C22,'MSET pivots'!$B$4:$H$14,$H$3,FALSE)*1000000*$I$2*'MSET pivots'!J$65 -> 67757.065 | AD22: =VLOOKUP($C22,'MSET pivots'!$B$4:$H$14,$H$3,FALSE)*1000000*$I$2*'MSET pivots'!K$65 -> 73403.388 | AE22: =VLOOKUP($C22,'MSET pivots'!$B$4:$H$14,$H$3,FALSE)*1000000*$I$2*'MSET pivots'!L$65 -> 79049.711 | ... AL22: =VLOOKUP($C22,'MSET pivots'!$B$4:$H$14,$H$3,FALSE)*1000000*$I$2*'MSET pivots'!S$65 -> 118573.97
C23: LAC | E23: LAC | F23: ALL | G23: ALL | H23: Government final consumption P.3g | I23: FD_3 | J23: abs-b | K23: =SUM(X23:AL23)/1000000 -> 1.1857457 | X23: =VLOOKUP($C23,'MSET pivots'!$B$4:$H$14,$H$3,FALSE)*1000000*$I$3*'MSET pivots'!E$65 -> 39525.449 | Y23: =VLOOKUP($C23,'MSET pivots'!$B$4:$H$14,$H$3,FALSE)*1000000*$I$3*'MSET pivots'!F$65 -> 45171.772 | Z23: =VLOOKUP($C23,'MSET pivots'!$B$4:$H$14,$H$3,FALSE)*1000000*$I$3*'MSET pivots'!G$65 -> 50818.095 | AA23: =VLOOKUP($C23,'MSET pivots'!$B$4:$H$14,$H$3,FALSE)*1000000*$I$3*'MSET pivots'!H$65 -> 56464.418 | AB23: =VLOOKUP($C23,'MSET pivots'!$B$4:$H$14,$H$3,FALSE)*1000000*$I$3*'MSET pivots'!I$65 -> 62110.742 | AC23: =VLOOKUP($C23,'MSET pivots'!$B$4:$H$14,$H$3,FALSE)*1000000*$I$3*'MSET pivots'!J$65 -> 67757.065 | AD23: =VLOOKUP($C23,'MSET pivots'!$B$4:$H$14,$H$3,FALSE)*1000000*$I$3*'MSET pivots'!K$65 -> 73403.388 | AE23: =VLOOKUP($C23,'MSET pivots'!$B$4:$H$14,$H$3,FALSE)*1000000*$I$3*'MSET pivots'!L$65 -> 79049.711 | ... AL23: =VLOOKUP($C23,'MSET pivots'!$B$4:$H$14,$H$3,FALSE)*1000000*$I$3*'MSET pivots'!S$65 -> 118573.97
C24: MEN | E24: MEN | F24: ALL | G24: ALL | H24: Household final consumption P.3h | I24: FD_1 | J24: abs-b | K24: =SUM(X24:AL24)/1000000 -> 0.58838813 | X24: =VLOOKUP($C24,'MSET pivots'!$B$4:$H$14,$H$3,FALSE)*1000000*$I$2*'MSET pivots'!E$65 -> 19613.232 | Y24: =VLOOKUP($C24,'MSET pivots'!$B$4:$H$14,$H$3,FALSE)*1000000*$I$2*'MSET pivots'!F$65 -> 22415.038 | Z24: =VLOOKUP($C24,'MSET pivots'!$B$4:$H$14,$H$3,FALSE)*1000000*$I$2*'MSET pivots'!G$65 -> 25216.844 | AA24: =VLOOKUP($C24,'MSET pivots'!$B$4:$H$14,$H$3,FALSE)*1000000*$I$2*'MSET pivots'!H$65 -> 28018.65 | AB24: =VLOOKUP($C24,'MSET pivots'!$B$4:$H$14,$H$3,FALSE)*1000000*$I$2*'MSET pivots'!I$65 -> 30820.457 | AC24: =VLOOKUP($C24,'MSET pivots'!$B$4:$H$14,$H$3,FALSE)*1000000*$I$2*'MSET pivots'!J$65 -> 33622.263 | AD24: =VLOOKUP($C24,'MSET pivots'!$B$4:$H$14,$H$3,FALSE)*1000000*$I$2*'MSET pivots'!K$65 -> 36424.069 | AE24: =VLOOKUP($C24,'MSET pivots'!$B$4:$H$14,$H$3,FALSE)*1000000*$I$2*'MSET pivots'!L$65 -> 39225.875 | ... AL24: =VLOOKUP($C24,'MSET pivots'!$B$4:$H$14,$H$3,FALSE)*1000000*$I$2*'MSET pivots'!S$65 -> 58838.519
C25: MEN | E25: MEN | F25: ALL | G25: ALL | H25: Government final consumption P.3g | I25: FD_3 | J25: abs-b | K25: =SUM(X25:AL25)/1000000 -> 0.58838813 | X25: =VLOOKUP($C25,'MSET pivots'!$B$4:$H$14,$H$3,FALSE)*1000000*$I$3*'MSET pivots'!E$65 -> 19613.232 | Y25: =VLOOKUP($C25,'MSET pivots'!$B$4:$H$14,$H$3,FALSE)*1000000*$I$3*'MSET pivots'!F$65 -> 22415.038 | Z25: =VLOOKUP($C25,'MSET pivots'!$B$4:$H$14,$H$3,FALSE)*1000000*$I$3*'MSET pivots'!G$65 -> 25216.844 | AA25: =VLOOKUP($C25,'MSET pivots'!$B$4:$H$14,$H$3,FALSE)*1000000*$I$3*'MSET pivots'!H$65 -> 28018.65 | AB25: =VLOOKUP($C25,'MSET pivots'!$B$4:$H$14,$H$3,FALSE)*1000000*$I$3*'MSET pivots'!I$65 -> 30820.457 | AC25: =VLOOKUP($C25,'MSET pivots'!$B$4:$H$14,$H$3,FALSE)*1000000*$I$3*'MSET pivots'!J$65 -> 33622.263 | AD25: =VLOOKUP($C25,'MSET pivots'!$B$4:$H$14,$H$3,FALSE)*1000000*$I$3*'MSET pivots'!K$65 -> 36424.069 | AE25: =VLOOKUP($C25,'MSET pivots'!$B$4:$H$14,$H$3,FALSE)*1000000*$I$3*'MSET pivots'!L$65 -> 39225.875 | ... AL25: =VLOOKUP($C25,'MSET pivots'!$B$4:$H$14,$H$3,FALSE)*1000000*$I$3*'MSET pivots'!S$65 -> 58838.519
B26: Pakistan | C26: SAS | E26: SAS | F26: ALL | G26: ALL | H26: Household final consumption P.3h | I26: FD_1 | J26: abs-b | K26: =SUM(X26:AL26)/1000000 -> 1.5848338 | W26: ='Preliminary results'!$C$31*1000000*I2 -> 902060.73 | X26: =VLOOKUP($C26,'MSET pivots'!$B$4:$H$14,$H$3,FALSE)*1000000*$I$2*'MSET pivots'!E$65 -> 52828.585 | Y26: =VLOOKUP($C26,'MSET pivots'!$B$4:$H$14,$H$3,FALSE)*1000000*$I$2*'MSET pivots'!F$65 -> 60375.3 | Z26: =VLOOKUP($C26,'MSET pivots'!$B$4:$H$14,$H$3,FALSE)*1000000*$I$2*'MSET pivots'!G$65 -> 67922.014 | AA26: =VLOOKUP($C26,'MSET pivots'!$B$4:$H$14,$H$3,FALSE)*1000000*$I$2*'MSET pivots'!H$65 -> 75468.729 | AB26: =VLOOKUP($C26,'MSET pivots'!$B$4:$H$14,$H$3,FALSE)*1000000*$I$2*'MSET pivots'!I$65 -> 83015.443 | AC26: =VLOOKUP($C26,'MSET pivots'!$B$4:$H$14,$H$3,FALSE)*1000000*$I$2*'MSET pivots'!J$65 -> 90562.157 | AD26: =VLOOKUP($C26,'MSET pivots'!$B$4:$H$14,$H$3,FALSE)*1000000*$I$2*'MSET pivots'!K$65 -> 98108.872 | AE26: =VLOOKUP($C26,'MSET pivots'!$B$4:$H$14,$H$3,FALSE)*1000000*$I$2*'MSET pivots'!L$65 -> 105655.59 | ... AL26: =VLOOKUP($C26,'MSET pivots'!$B$4:$H$14,$H$3,FALSE)*1000000*$I$2*'MSET pivots'!S$65 -> 158482.59
B27: Pakistan | C27: SAS | E27: SAS | F27: ALL | G27: ALL | H27: Government final consumption P.3g | I27: FD_3 | J27: abs-b | K27: =SUM(X27:AL27)/1000000 -> 1.5848338 | W27: ='Preliminary results'!$C$31*1000000*I3 -> 902060.73 | X27: =VLOOKUP($C27,'MSET pivots'!$B$4:$H$14,$H$3,FALSE)*1000000*$I$3*'MSET pivots'!E$65 -> 52828.585 | Y27: =VLOOKUP($C27,'MSET pivots'!$B$4:$H$14,$H$3,FALSE)*1000000*$I$3*'MSET pivots'!F$65 -> 60375.3 | Z27: =VLOOKUP($C27,'MSET pivots'!$B$4:$H$14,$H$3,FALSE)*1000000*$I$3*'MSET pivots'!G$65 -> 67922.014 | AA27: =VLOOKUP($C27,'MSET pivots'!$B$4:$H$14,$H$3,FALSE)*1000000*$I$3*'MSET pivots'!H$65 -> 75468.729 | AB27: =VLOOKUP($C27,'MSET pivots'!$B$4:$H$14,$H$3,FALSE)*1000000*$I$3*'MSET pivots'!I$65 -> 83015.443 | AC27: =VLOOKUP($C27,'MSET pivots'!$B$4:$H$14,$H$3,FALSE)*1000000*$I$3*'MSET pivots'!J$65 -> 90562.157 | AD27: =VLOOKUP($C27,'MSET pivots'!$B$4:$H$14,$H$3,FALSE)*1000000*$I$3*'MSET pivots'!K$65 -> 98108.872 | AE27: =VLOOKUP($C27,'MSET pivots'!$B$4:$H$14,$H$3,FALSE)*1000000*$I$3*'MSET pivots'!L$65 -> 105655.59 | ... AL27: =VLOOKUP($C27,'MSET pivots'!$B$4:$H$14,$H$3,FALSE)*1000000*$I$3*'MSET pivots'!S$65 -> 158482.59
C28: AJN | E28: AJN | F28: ALL | G28: ALL | H28: Government final consumption P.3g | I28: FD_3 | J28: rel-b | K28: =SUM(X28:AL28) -> -0.0024830706 | X28: =VLOOKUP($C28,'MSET pivots'!$J$4:$P$14,'Final demand(5)'!$H$3,FALSE)*'MSET pivots'!E$65 -> -8.2770262e-05 | Y28: =VLOOKUP($C28,'MSET pivots'!$J$4:$P$14,'Final demand(5)'!$H$3,FALSE)*'MSET pivots'!F$65 -> -9.459423e-05 | Z28: =VLOOKUP($C28,'MSET pivots'!$J$4:$P$14,'Final demand(5)'!$H$3,FALSE)*'MSET pivots'!G$65 -> -0.0001064182 | AA28: =VLOOKUP($C28,'MSET pivots'!$J$4:$P$14,'Final demand(5)'!$H$3,FALSE)*'MSET pivots'!H$65 -> -0.00011824217 | AB28: =VLOOKUP($C28,'MSET pivots'!$J$4:$P$14,'Final demand(5)'!$H$3,FALSE)*'MSET pivots'!I$65 -> -0.00013006614 | AC28: =VLOOKUP($C28,'MSET pivots'!$J$4:$P$14,'Final demand(5)'!$H$3,FALSE)*'MSET pivots'!J$65 -> -0.0001418901 | AD28: =VLOOKUP($C28,'MSET pivots'!$J$4:$P$14,'Final demand(5)'!$H$3,FALSE)*'MSET pivots'!K$65 -> -0.00015371407 | AE28: =VLOOKUP($C28,'MSET pivots'!$J$4:$P$14,'Final demand(5)'!$H$3,FALSE)*'MSET pivots'!L$65 -> -0.00016553804 | ... AL28: =VLOOKUP($C28,'MSET pivots'!$J$4:$P$14,'Final demand(5)'!$H$3,FALSE)*'MSET pivots'!S$65 -> -0.00024830582
C29: EEA | E29: EEA | F29: ALL | G29: ALL | H29: Government final consumption P.3g | I29: FD_3 | J29: rel-b | K29: =SUM(X29:AL29) -> -0.0028084209 | X29: =VLOOKUP($C29,'MSET pivots'!$J$4:$P$14,'Final demand(5)'!$H$3,FALSE)*'MSET pivots'!E$65 -> -9.3615434e-05 | Y29: =VLOOKUP($C29,'MSET pivots'!$J$4:$P$14,'Final demand(5)'!$H$3,FALSE)*'MSET pivots'!F$65 -> -0.00010698867 | Z29: =VLOOKUP($C29,'MSET pivots'!$J$4:$P$14,'Final demand(5)'!$H$3,FALSE)*'MSET pivots'!G$65 -> -0.0001203619 | AA29: =VLOOKUP($C29,'MSET pivots'!$J$4:$P$14,'Final demand(5)'!$H$3,FALSE)*'MSET pivots'!H$65 -> -0.00013373513 | AB29: =VLOOKUP($C29,'MSET pivots'!$J$4:$P$14,'Final demand(5)'!$H$3,FALSE)*'MSET pivots'!I$65 -> -0.00014710836 | AC29: =VLOOKUP($C29,'MSET pivots'!$J$4:$P$14,'Final demand(5)'!$H$3,FALSE)*'MSET pivots'!J$65 -> -0.0001604816 | AD29: =VLOOKUP($C29,'MSET pivots'!$J$4:$P$14,'Final demand(5)'!$H$3,FALSE)*'MSET pivots'!K$65 -> -0.00017385483 | AE29: =VLOOKUP($C29,'MSET pivots'!$J$4:$P$14,'Final demand(5)'!$H$3,FALSE)*'MSET pivots'!L$65 -> -0.00018722806 | ... AL29: =VLOOKUP($C29,'MSET pivots'!$J$4:$P$14,'Final demand(5)'!$H$3,FALSE)*'MSET pivots'!S$65 -> -0.00028084069
B30: United Kingdom | C30: EUR | E30: EUR | F30: ALL | G30: ALL | H30: Government final consumption P.3g | I30: FD_3 | J30: rel-b | K30: =SUM(X30:AL30) -> -0.0019859118 | W30: =('Preliminary results'!$C$31)/'Baseline govt spend'!$E$51 -> 0.00066729533 | X30: =VLOOKUP($C30,'MSET pivots'!$J$4:$P$14,'Final demand(5)'!$H$3,FALSE)*'MSET pivots'!E$65 -> -6.6198052e-05 | Y30: =VLOOKUP($C30,'MSET pivots'!$J$4:$P$14,'Final demand(5)'!$H$3,FALSE)*'MSET pivots'!F$65 -> -7.5654633e-05 | Z30: =VLOOKUP($C30,'MSET pivots'!$J$4:$P$14,'Final demand(5)'!$H$3,FALSE)*'MSET pivots'!G$65 -> -8.5111213e-05 | AA30: =VLOOKUP($C30,'MSET pivots'!$J$4:$P$14,'Final demand(5)'!$H$3,FALSE)*'MSET pivots'!H$65 -> -9.4567794e-05 | AB30: =VLOOKUP($C30,'MSET pivots'!$J$4:$P$14,'Final demand(5)'!$H$3,FALSE)*'MSET pivots'!I$65 -> -0.00010402438 | AC30: =VLOOKUP($C30,'MSET pivots'!$J$4:$P$14,'Final demand(5)'!$H$3,FALSE)*'MSET pivots'!J$65 -> -0.00011348096 | AD30: =VLOOKUP($C30,'MSET pivots'!$J$4:$P$14,'Final demand(5)'!$H$3,FALSE)*'MSET pivots'!K$65 -> -0.00012293754 | AE30: =VLOOKUP($C30,'MSET pivots'!$J$4:$P$14,'Final demand(5)'!$H$3,FALSE)*'MSET pivots'!L$65 -> -0.00013239412 | ... AL30: =VLOOKUP($C30,'MSET pivots'!$J$4:$P$14,'Final demand(5)'!$H$3,FALSE)*'MSET pivots'!S$65 -> -0.00019859018
C31: NAM | E31: NAM | F31: ALL | G31: ALL | H31: Government final consumption P.3g | I31: FD_3 | J31: rel-b | K31: =SUM(X31:AL31) -> -0.0053700635 | X31: =VLOOKUP($C31,'MSET pivots'!$J$4:$P$14,'Final demand(5)'!$H$3,FALSE)*'MSET pivots'!E$65 -> -0.0001790048 | Y31: =VLOOKUP($C31,'MSET pivots'!$J$4:$P$14,'Final demand(5)'!$H$3,FALSE)*'MSET pivots'!F$65 -> -0.00020457615 | Z31: =VLOOKUP($C31,'MSET pivots'!$J$4:$P$14,'Final demand(5)'!$H$3,FALSE)*'MSET pivots'!G$65 -> -0.00023014749 | AA31: =VLOOKUP($C31,'MSET pivots'!$J$4:$P$14,'Final demand(5)'!$H$3,FALSE)*'MSET pivots'!H$65 -> -0.00025571884 | AB31: =VLOOKUP($C31,'MSET pivots'!$J$4:$P$14,'Final demand(5)'!$H$3,FALSE)*'MSET pivots'!I$65 -> -0.00028129019 | AC31: =VLOOKUP($C31,'MSET pivots'!$J$4:$P$14,'Final demand(5)'!$H$3,FALSE)*'MSET pivots'!J$65 -> -0.00030686154 | AD31: =VLOOKUP($C31,'MSET pivots'!$J$4:$P$14,'Final demand(5)'!$H$3,FALSE)*'MSET pivots'!K$65 -> -0.00033243288 | AE31: =VLOOKUP($C31,'MSET pivots'!$J$4:$P$14,'Final demand(5)'!$H$3,FALSE)*'MSET pivots'!L$65 -> -0.00035800423 | ... AL31: =VLOOKUP($C31,'MSET pivots'!$J$4:$P$14,'Final demand(5)'!$H$3,FALSE)*'MSET pivots'!S$65 -> -0.00053700366
G44: =_xlfn.IFNA(INDEX('[1]Sector list'!$A$2:$A$122,MATCH(F44,'[1]Sector list'!$B$2:$B$122,0)),"") | I44: =_xlfn.IFNA(INDEX('[1]FD list'!$A$2:$A$122,MATCH(H44,'[1]FD list'!$B$2:$B$122,0)),"")
G45: =_xlfn.IFNA(INDEX('[1]Sector list'!$A$2:$A$122,MATCH(F45,'[1]Sector list'!$B$2:$B$122,0)),"") | I45: =_xlfn.IFNA(INDEX('[1]FD list'!$A$2:$A$122,MATCH(H45,'[1]FD list'!$B$2:$B$122,0)),"")
G46: =_xlfn.IFNA(INDEX('[1]Sector list'!$A$2:$A$122,MATCH(F46,'[1]Sector list'!$B$2:$B$122,0)),"") | I46: =_xlfn.IFNA(INDEX('[1]FD list'!$A$2:$A$122,MATCH(H46,'[1]FD list'!$B$2:$B$122,0)),"")
G47: =_xlfn.IFNA(INDEX('[1]Sector list'!$A$2:$A$122,MATCH(F47,'[1]Sector list'!$B$2:$B$122,0)),"") | I47: =_xlfn.IFNA(INDEX('[1]FD list'!$A$2:$A$122,MATCH(H47,'[1]FD list'!$B$2:$B$122,0)),"")
G48: =_xlfn.IFNA(INDEX('[1]Sector list'!$A$2:$A$122,MATCH(F48,'[1]Sector list'!$B$2:$B$122,0)),"") | I48: =_xlfn.IFNA(INDEX('[1]FD list'!$A$2:$A$122,MATCH(H48,'[1]FD list'!$B$2:$B$122,0)),"")
G49: =_xlfn.IFNA(INDEX('[1]Sector list'!$A$2:$A$122,MATCH(F49,'[1]Sector list'!$B$2:$B$122,0)),"") | I49: =_xlfn.IFNA(INDEX('[1]FD list'!$A$2:$A$122,MATCH(H49,'[1]FD list'!$B$2:$B$122,0)),"")
G50: =_xlfn.IFNA(INDEX('[1]Sector list'!$A$2:$A$122,MATCH(F50,'[1]Sector list'!$B$2:$B$122,0)),"") | I50: =_xlfn.IFNA(INDEX('[1]FD list'!$A$2:$A$122,MATCH(H50,'[1]FD list'!$B$2:$B$122,0)),"")
G51: =_xlfn.IFNA(INDEX('[1]Sector list'!$A$2:$A$122,MATCH(F51,'[1]Sector list'!$B$2:$B$122,0)),"") | I51: =_xlfn.IFNA(INDEX('[1]FD list'!$A$2:$A$122,MATCH(H51,'[1]FD list'!$B$2:$B$122,0)),"")
G52: =_xlfn.IFNA(INDEX('[1]Sector list'!$A$2:$A$122,MATCH(F52,'[1]Sector list'!$B$2:$B$122,0)),"") | I52: =_xlfn.IFNA(INDEX('[1]FD list'!$A$2:$A$122,MATCH(H52,'[1]FD list'!$B$2:$B$122,0)),"")
G53: =_xlfn.IFNA(INDEX('[1]Sector list'!$A$2:$A$122,MATCH(F53,'[1]Sector list'!$B$2:$B$122,0)),"") | I53: =_xlfn.IFNA(INDEX('[1]FD list'!$A$2:$A$122,MATCH(H53,'[1]FD list'!$B$2:$B$122,0)),"")
G54: =_xlfn.IFNA(INDEX('[1]Sector list'!$A$2:$A$122,MATCH(F54,'[1]Sector list'!$B$2:$B$122,0)),"") | I54: =_xlfn.IFNA(INDEX('[1]FD list'!$A$2:$A$122,MATCH(H54,'[1]FD list'!$B$2:$B$122,0)),"")
G55: =_xlfn.IFNA(INDEX('[1]Sector list'!$A$2:$A$122,MATCH(F55,'[1]Sector list'!$B$2:$B$122,0)),"") | I55: =_xlfn.IFNA(INDEX('[1]FD list'!$A$2:$A$122,MATCH(H55,'[1]FD list'!$B$2:$B$122,0)),"")
... G69: =_xlfn.IFNA(INDEX('[1]Sector list'!$A$2:$A$122,MATCH(F69,'[1]Sector list'!$B$2:$B$122,0)),"") | I69: =_xlfn.IFNA(INDEX('[1]FD list'!$A$2:$A$122,MATCH(H69,'[1]FD list'!$B$2:$B$122,0)),"")
I70: =_xlfn.IFNA(INDEX('[1]FD list'!$A$2:$A$122,MATCH(H70,'[1]FD list'!$B$2:$B$122,0)),"")
I71: =_xlfn.IFNA(INDEX('[1]FD list'!$A$2:$A$122,MATCH(H71,'[1]FD list'!$B$2:$B$122,0)),"")
I72: =_xlfn.IFNA(INDEX('[1]FD list'!$A$2:$A$122,MATCH(H72,'[1]FD list'!$B$2:$B$122,0)),"")
I73: =_xlfn.IFNA(INDEX('[1]FD list'!$A$2:$A$122,MATCH(H73,'[1]FD list'!$B$2:$B$122,0)),"")
I74: =_xlfn.IFNA(INDEX('[1]FD list'!$A$2:$A$122,MATCH(H74,'[1]FD list'!$B$2:$B$122,0)),"")
I75: =_xlfn.IFNA(INDEX('[1]FD list'!$A$2:$A$122,MATCH(H75,'[1]FD list'!$B$2:$B$122,0)),"")
I76: =_xlfn.IFNA(INDEX('[1]FD list'!$A$2:$A$122,MATCH(H76,'[1]FD list'!$B$2:$B$122,0)),"")
I77: =_xlfn.IFNA(INDEX('[1]FD list'!$A$2:$A$122,MATCH(H77,'[1]FD list'!$B$2:$B$122,0)),"")
I78: =_xlfn.IFNA(INDEX('[1]FD list'!$A$2:$A$122,MATCH(H78,'[1]FD list'!$B$2:$B$122,0)),"")
I79: =_xlfn.IFNA(INDEX('[1]FD list'!$A$2:$A$122,MATCH(H79,'[1]FD list'!$B$2:$B$122,0)),"")
I80: =_xlfn.IFNA(INDEX('[1]FD list'!$A$2:$A$122,MATCH(H80,'[1]FD list'!$B$2:$B$122,0)),"")
I81: =_xlfn.IFNA(INDEX('[1]FD list'!$A$2:$A$122,MATCH(H81,'[1]FD list'!$B$2:$B$122,0)),"")
... I97: =_xlfn.IFNA(INDEX('[1]FD list'!$A$2:$A$122,MATCH(H97,'[1]FD list'!$B$2:$B$122,0)),"")
I98: =_xlfn.IFNA(INDEX('[1]Sector list'!$A$2:$A$122,MATCH(H98,'[1]Sector list'!$B$2:$B$122,0)),"")
I99: =_xlfn.IFNA(INDEX('[1]Sector list'!$A$2:$A$122,MATCH(H99,'[1]Sector list'!$B$2:$B$122,0)),"")
I100: =_xlfn.IFNA(INDEX('[1]Sector list'!$A$2:$A$122,MATCH(H100,'[1]Sector list'!$B$2:$B$122,0)),"")
I101: =_xlfn.IFNA(INDEX('[1]Sector list'!$A$2:$A$122,MATCH(H101,'[1]Sector list'!$B$2:$B$122,0)),"")
I102: =_xlfn.IFNA(INDEX('[1]Sector list'!$A$2:$A$122,MATCH(H102,'[1]Sector list'!$B$2:$B$122,0)),"")
I103: =_xlfn.IFNA(INDEX('[1]Sector list'!$A$2:$A$122,MATCH(H103,'[1]Sector list'!$B$2:$B$122,0)),"")
I104: =_xlfn.IFNA(INDEX('[1]Sector list'!$A$2:$A$122,MATCH(H104,'[1]Sector list'!$B$2:$B$122,0)),"")
I105: =_xlfn.IFNA(INDEX('[1]Sector list'!$A$2:$A$122,MATCH(H105,'[1]Sector list'!$B$2:$B$122,0)),"")
I106: =_xlfn.IFNA(INDEX('[1]Sector list'!$A$2:$A$122,MATCH(H106,'[1]Sector list'!$B$2:$B$122,0)),"")
I107: =_xlfn.IFNA(INDEX('[1]Sector list'!$A$2:$A$122,MATCH(H107,'[1]Sector list'!$B$2:$B$122,0)),"")
I108: =_xlfn.IFNA(INDEX('[1]Sector list'!$A$2:$A$122,MATCH(H108,'[1]Sector list'!$B$2:$B$122,0)),"")
I109: =_xlfn.IFNA(INDEX('[1]Sector list'!$A$2:$A$122,MATCH(H109,'[1]Sector list'!$B$2:$B$122,0)),"")
... I905: =_xlfn.IFNA(INDEX('[1]Sector list'!$A$2:$A$122,MATCH(H905,'[1]Sector list'!$B$2:$B$122,0)),"")

Sheet Investment by(5)
B2: Investment BY sector changes | G2: ='Final demand(5)'!H2 -> G77+C_lower | H2: ='Final demand(5)'!H3 -> 5
B3: Fields with * must be specified manually or filled in automatically by selecting values in other columns
B5: Country | C5: Country ISO* | D5: Sector investing | E5: Sector investing code* | F5: Type* | G5: Comments
G6: =1/3 -> 0.33333333 | H6: FCF
B8: Germany | C8: =_xlfn.IFNA(INDEX('[2]Country list'!$A$2:$A$166,MATCH(B8,'[2]Country list'!$B$2:$B$166,0)),"") -> DEU | E8: 1-23 | F8: abs | G8: << Increase investment in agricultural sectors in Germany, 1000 kUSD in EVERY sector
G12: relative investment is not possible, because we don’t have an investment baseline right now
C13: REG_imp | E13: PROD_COMM | G13: Current options: abs-b
B14: Start in the next line >>
B15: Country | C15: Country ISO* | D15: Sector investing | E15: Sector investing code* | F15: Type* | G15: Comments | H15: 2019 | I15: 2020 | J15: 2021 | K15: 2022 | L15: 2023 | M15: 2024 | N15: 2025 | O15: 2026 | P15: 2027 | Q15: 2028 | R15: 2029 | S15: 2030 | T15: 2031 | U15: 2032 | V15: 2033 | W15: 2034 | X15: 2035 | Y15: 2036 | Z15: 2037 | AA15: 2038 | AB15: 2039 | AC15: 2040 | AD15: 2041 | AE15: 2042 | AF15: 2043 | AG15: 2044 | AH15: 2045 | AI15: 2046 | AJ15: 2047 | AK15: 2048 | AL15: 2049 | AM15: 2050
C16: SEP | E16: ALL | F16: abs-b | G16: =SUM(T16:AH16)/1000000 -> 1.2914527 | T16: =VLOOKUP($C16,'MSET pivots'!$B$4:$H$14,$H$2,FALSE)*1000000*$G$6*'MSET pivots'!E$65 -> 43049.071 | U16: =VLOOKUP($C16,'MSET pivots'!$B$4:$H$14,$H$2,FALSE)*1000000*$G$6*'MSET pivots'!F$65 -> 49198.753 | V16: =VLOOKUP($C16,'MSET pivots'!$B$4:$H$14,$H$2,FALSE)*1000000*$G$6*'MSET pivots'!G$65 -> 55348.436 | W16: =VLOOKUP($C16,'MSET pivots'!$B$4:$H$14,$H$2,FALSE)*1000000*$G$6*'MSET pivots'!H$65 -> 61498.119 | X16: =VLOOKUP($C16,'MSET pivots'!$B$4:$H$14,$H$2,FALSE)*1000000*$G$6*'MSET pivots'!I$65 -> 67647.802 | Y16: =VLOOKUP($C16,'MSET pivots'!$B$4:$H$14,$H$2,FALSE)*1000000*$G$6*'MSET pivots'!J$65 -> 73797.484 | Z16: =VLOOKUP($C16,'MSET pivots'!$B$4:$H$14,$H$2,FALSE)*1000000*$G$6*'MSET pivots'!K$65 -> 79947.167 | AA16: =VLOOKUP($C16,'MSET pivots'!$B$4:$H$14,$H$2,FALSE)*1000000*$G$6*'MSET pivots'!L$65 -> 86096.85 | ... AH16: =VLOOKUP($C16,'MSET pivots'!$B$4:$H$14,$H$2,FALSE)*1000000*$G$6*'MSET pivots'!S$65 -> 129144.63
C17: AFR | E17: ALL | F17: abs-b | G17: =SUM(T17:AH17)/1000000 -> 0.94167139 | T17: =VLOOKUP($C17,'MSET pivots'!$B$4:$H$14,$H$2,FALSE)*1000000*$G$6*'MSET pivots'!E$65 -> 31389.517 | U17: =VLOOKUP($C17,'MSET pivots'!$B$4:$H$14,$H$2,FALSE)*1000000*$G$6*'MSET pivots'!F$65 -> 35873.6 | V17: =VLOOKUP($C17,'MSET pivots'!$B$4:$H$14,$H$2,FALSE)*1000000*$G$6*'MSET pivots'!G$65 -> 40357.682 | W17: =VLOOKUP($C17,'MSET pivots'!$B$4:$H$14,$H$2,FALSE)*1000000*$G$6*'MSET pivots'!H$65 -> 44841.764 | X17: =VLOOKUP($C17,'MSET pivots'!$B$4:$H$14,$H$2,FALSE)*1000000*$G$6*'MSET pivots'!I$65 -> 49325.846 | Y17: =VLOOKUP($C17,'MSET pivots'!$B$4:$H$14,$H$2,FALSE)*1000000*$G$6*'MSET pivots'!J$65 -> 53809.928 | Z17: =VLOOKUP($C17,'MSET pivots'!$B$4:$H$14,$H$2,FALSE)*1000000*$G$6*'MSET pivots'!K$65 -> 58294.011 | AA17: =VLOOKUP($C17,'MSET pivots'!$B$4:$H$14,$H$2,FALSE)*1000000*$G$6*'MSET pivots'!L$65 -> 62778.093 | ... AH17: =VLOOKUP($C17,'MSET pivots'!$B$4:$H$14,$H$2,FALSE)*1000000*$G$6*'MSET pivots'!S$65 -> 94166.669
C18: EAS | E18: ALL | F18: abs-b | G18: =SUM(T18:AH18)/1000000 -> 4.8842779 | T18: =VLOOKUP($C18,'MSET pivots'!$B$4:$H$14,$H$2,FALSE)*1000000*$G$6*'MSET pivots'!E$65 -> 162811.71 | U18: =VLOOKUP($C18,'MSET pivots'!$B$4:$H$14,$H$2,FALSE)*1000000*$G$6*'MSET pivots'!F$65 -> 186069.82 | V18: =VLOOKUP($C18,'MSET pivots'!$B$4:$H$14,$H$2,FALSE)*1000000*$G$6*'MSET pivots'!G$65 -> 209327.94 | W18: =VLOOKUP($C18,'MSET pivots'!$B$4:$H$14,$H$2,FALSE)*1000000*$G$6*'MSET pivots'!H$65 -> 232586.06 | X18: =VLOOKUP($C18,'MSET pivots'!$B$4:$H$14,$H$2,FALSE)*1000000*$G$6*'MSET pivots'!I$65 -> 255844.17 | Y18: =VLOOKUP($C18,'MSET pivots'!$B$4:$H$14,$H$2,FALSE)*1000000*$G$6*'MSET pivots'!J$65 -> 279102.29 | Z18: =VLOOKUP($C18,'MSET pivots'!$B$4:$H$14,$H$2,FALSE)*1000000*$G$6*'MSET pivots'!K$65 -> 302360.41 | AA18: =VLOOKUP($C18,'MSET pivots'!$B$4:$H$14,$H$2,FALSE)*1000000*$G$6*'MSET pivots'!L$65 -> 325618.53 | ... AH18: =VLOOKUP($C18,'MSET pivots'!$B$4:$H$14,$H$2,FALSE)*1000000*$G$6*'MSET pivots'!S$65 -> 488425.35
C19: LAC | E19: ALL | F19: abs-b | G19: =SUM(T19:AH19)/1000000 -> 1.1857457 | T19: =VLOOKUP($C19,'MSET pivots'!$B$4:$H$14,$H$2,FALSE)*1000000*$G$6*'MSET pivots'!E$65 -> 39525.449 | U19: =VLOOKUP($C19,'MSET pivots'!$B$4:$H$14,$H$2,FALSE)*1000000*$G$6*'MSET pivots'!F$65 -> 45171.772 | V19: =VLOOKUP($C19,'MSET pivots'!$B$4:$H$14,$H$2,FALSE)*1000000*$G$6*'MSET pivots'!G$65 -> 50818.095 | W19: =VLOOKUP($C19,'MSET pivots'!$B$4:$H$14,$H$2,FALSE)*1000000*$G$6*'MSET pivots'!H$65 -> 56464.418 | X19: =VLOOKUP($C19,'MSET pivots'!$B$4:$H$14,$H$2,FALSE)*1000000*$G$6*'MSET pivots'!I$65 -> 62110.742 | Y19: =VLOOKUP($C19,'MSET pivots'!$B$4:$H$14,$H$2,FALSE)*1000000*$G$6*'MSET pivots'!J$65 -> 67757.065 | Z19: =VLOOKUP($C19,'MSET pivots'!$B$4:$H$14,$H$2,FALSE)*1000000*$G$6*'MSET pivots'!K$65 -> 73403.388 | AA19: =VLOOKUP($C19,'MSET pivots'!$B$4:$H$14,$H$2,FALSE)*1000000*$G$6*'MSET pivots'!L$65 -> 79049.711 | ... AH19: =VLOOKUP($C19,'MSET pivots'!$B$4:$H$14,$H$2,FALSE)*1000000*$G$6*'MSET pivots'!S$65 -> 118573.97
C20: SAS | E20: ALL | F20: abs-b | G20: =SUM(T20:AH20)/1000000 -> 1.5848338 | S20: ='Preliminary results'!$C$31*1000000*G6 -> 902060.73 | T20: =VLOOKUP($C20,'MSET pivots'!$B$4:$H$14,$H$2,FALSE)*1000000*$G$6*'MSET pivots'!E$65 -> 52828.585 | U20: =VLOOKUP($C20,'MSET pivots'!$B$4:$H$14,$H$2,FALSE)*1000000*$G$6*'MSET pivots'!F$65 -> 60375.3 | V20: =VLOOKUP($C20,'MSET pivots'!$B$4:$H$14,$H$2,FALSE)*1000000*$G$6*'MSET pivots'!G$65 -> 67922.014 | W20: =VLOOKUP($C20,'MSET pivots'!$B$4:$H$14,$H$2,FALSE)*1000000*$G$6*'MSET pivots'!H$65 -> 75468.729 | X20: =VLOOKUP($C20,'MSET pivots'!$B$4:$H$14,$H$2,FALSE)*1000000*$G$6*'MSET pivots'!I$65 -> 83015.443 | Y20: =VLOOKUP($C20,'MSET pivots'!$B$4:$H$14,$H$2,FALSE)*1000000*$G$6*'MSET pivots'!J$65 -> 90562.157 | Z20: =VLOOKUP($C20,'MSET pivots'!$B$4:$H$14,$H$2,FALSE)*1000000*$G$6*'MSET pivots'!K$65 -> 98108.872 | AA20: =VLOOKUP($C20,'MSET pivots'!$B$4:$H$14,$H$2,FALSE)*1000000*$G$6*'MSET pivots'!L$65 -> 105655.59 | ... AH20: =VLOOKUP($C20,'MSET pivots'!$B$4:$H$14,$H$2,FALSE)*1000000*$G$6*'MSET pivots'!S$65 -> 158482.59
C21: MEN | E21: ALL | F21: abs-b | G21: =SUM(T21:AH21)/1000000 -> 0.58838813 | T21: =VLOOKUP($C21,'MSET pivots'!$B$4:$H$14,$H$2,FALSE)*1000000*$G$6*'MSET pivots'!E$65 -> 19613.232 | U21: =VLOOKUP($C21,'MSET pivots'!$B$4:$H$14,$H$2,FALSE)*1000000*$G$6*'MSET pivots'!F$65 -> 22415.038 | V21: =VLOOKUP($C21,'MSET pivots'!$B$4:$H$14,$H$2,FALSE)*1000000*$G$6*'MSET pivots'!G$65 -> 25216.844 | W21: =VLOOKUP($C21,'MSET pivots'!$B$4:$H$14,$H$2,FALSE)*1000000*$G$6*'MSET pivots'!H$65 -> 28018.65 | X21: =VLOOKUP($C21,'MSET pivots'!$B$4:$H$14,$H$2,FALSE)*1000000*$G$6*'MSET pivots'!I$65 -> 30820.457 | Y21: =VLOOKUP($C21,'MSET pivots'!$B$4:$H$14,$H$2,FALSE)*1000000*$G$6*'MSET pivots'!J$65 -> 33622.263 | Z21: =VLOOKUP($C21,'MSET pivots'!$B$4:$H$14,$H$2,FALSE)*1000000*$G$6*'MSET pivots'!K$65 -> 36424.069 | AA21: =VLOOKUP($C21,'MSET pivots'!$B$4:$H$14,$H$2,FALSE)*1000000*$G$6*'MSET pivots'!L$65 -> 39225.875 | ... AH21: =VLOOKUP($C21,'MSET pivots'!$B$4:$H$14,$H$2,FALSE)*1000000*$G$6*'MSET pivots'!S$65 -> 58838.519

Sheet Final demand(6)
B2: Final demand changes (consumption, govt, etc) | H2: G77+C_central | I2: =1/3 -> 0.33333333 | J2: hh
B3: Fields with * must be specified manually or filled in automatically by selecting values in other columns | H3: 6 | I3: =1/3 -> 0.33333333 | J3: gov
B5: Country | C5: Country ISO* | F5: Product | G5: Product code* | H5: Final demand category | I5: FD code* | J5: Type* | K5: Comments
B6: Italy | C6: =_xlfn.IFNA(INDEX('[1]Country list'!$A$2:$A$166,MATCH(B6,'[1]Country list'!$B$2:$B$166,0)),"") -> ITA | F6: ALL | G6: =_xlfn.IFNA(INDEX('[1]Sector list'!$A$2:$A$122,MATCH(F6,'[1]Sector list'!$B$2:$B$122,0)),"") -> ALL | H6: Household final consumption P.3h | I6: =_xlfn.IFNA(INDEX('[1]FD list'!$A$2:$A$122,MATCH(H6,'[1]FD list'!$B$2:$B$122,0)),"") -> FD_1 | J6: rel-b | K6: << Decrease final demand (HH consumption) 3% for all products in Italy
C7: ITA | F7: Pork | G7: =_xlfn.IFNA(INDEX('[1]Sector list'!$A$2:$A$122,MATCH(F7,'[1]Sector list'!$B$2:$B$122,0)),"") -> 43 | H7: ALL | I7: =_xlfn.IFNA(INDEX('[1]FD list'!$A$2:$A$122,MATCH(H7,'[1]FD list'!$B$2:$B$122,0)),"") -> ALL | J7: rel-b | K7: << Increase final demand (across all demand categories) for pork in Italy by 12% (if zero stays zero)
B8: Germany | C8: =_xlfn.IFNA(INDEX('[1]Country list'!$A$2:$A$166,MATCH(B8,'[1]Country list'!$B$2:$B$166,0)),"") -> DEU | G8: 1-23 | I8: FD_1 | J8: abs-b | K8: << Increase demand in Germany for all agricultural sectors (1-23), only for consumer demand; try NOT to use negative values as it might create issues
B9: Malawi | C9: =_xlfn.IFNA(INDEX('[1]Country list'!$A$2:$A$166,MATCH(B9,'[1]Country list'!$B$2:$B$166,0)),"") -> MWI | F9: Building construction | G9: =_xlfn.IFNA(INDEX('[1]Sector list'!$A$2:$A$122,MATCH(F9,'[1]Sector list'!$B$2:$B$122,0)),"") -> 98 | H9: Gross fixed capital formation P.51 | I9: =_xlfn.IFNA(INDEX('[1]FD list'!$A$2:$A$122,MATCH(H9,'[1]FD list'!$B$2:$B$122,0)),"") -> FD_4 | J9: rel-b | K9: << Directly decrease investment (GFCF) demand for construction sector in Malawi with 1%; NOTE: if you want to do INVESTMENT BY the sector IT SHOULD NOT BE DONE HERE
C13: REG_exp | E13: REG_imp | G13: TRAD_COMM | I13: PROD_COMM (only FD) | J13: Current options: rel-b and abs-b
B14: Start in the next line >>
B15: Producing country | C15: Producing country ISO* | D15: Consuming country | E15: Consuming country ISO* | F15: Product | G15: Product code* | H15: Final demand category | I15: FD code* | J15: Type* | K15: Comments | L15: 2019 | M15: 2020 | N15: 2021 | O15: 2022 | P15: 2023 | Q15: 2024 | R15: 2025 | S15: 2026 | T15: 2027 | U15: 2028 | V15: 2029 | W15: 2030 | X15: 2031 | Y15: 2032 | Z15: 2033 | AA15: 2034 | AB15: 2035 | AC15: 2036 | AD15: 2037 | AE15: 2038 | AF15: 2039 | AG15: 2040 | AH15: 2041 | AI15: 2042 | AJ15: 2043 | AK15: 2044 | AL15: 2045 | AM15: 2046 | AN15: 2047 | AO15: 2048 | AP15: 2049 | AQ15: 2050
C16: SEP | E16: SEP | F16: ALL | G16: ALL | H16: Household final consumption P.3h | I16: FD_1 | J16: abs-b | K16: =SUM(X16:AL16)/1000000 -> 41.63794 | X16: =VLOOKUP($C16,'MSET pivots'!$B$4:$H$14,$H$3,FALSE)*1000000*$I$2*'MSET pivots'!E$65 -> 1387952.2 | Y16: =VLOOKUP($C16,'MSET pivots'!$B$4:$H$14,$H$3,FALSE)*1000000*$I$2*'MSET pivots'!F$65 -> 1586225.1 | Z16: =VLOOKUP($C16,'MSET pivots'!$B$4:$H$14,$H$3,FALSE)*1000000*$I$2*'MSET pivots'!G$65 -> 1784498 | AA16: =VLOOKUP($C16,'MSET pivots'!$B$4:$H$14,$H$3,FALSE)*1000000*$I$2*'MSET pivots'!H$65 -> 1982771 | AB16: =VLOOKUP($C16,'MSET pivots'!$B$4:$H$14,$H$3,FALSE)*1000000*$I$2*'MSET pivots'!I$65 -> 2181043.9 | AC16: =VLOOKUP($C16,'MSET pivots'!$B$4:$H$14,$H$3,FALSE)*1000000*$I$2*'MSET pivots'!J$65 -> 2379316.8 | AD16: =VLOOKUP($C16,'MSET pivots'!$B$4:$H$14,$H$3,FALSE)*1000000*$I$2*'MSET pivots'!K$65 -> 2577589.8 | AE16: =VLOOKUP($C16,'MSET pivots'!$B$4:$H$14,$H$3,FALSE)*1000000*$I$2*'MSET pivots'!L$65 -> 2775862.7 | ... AL16: =VLOOKUP($C16,'MSET pivots'!$B$4:$H$14,$H$3,FALSE)*1000000*$I$2*'MSET pivots'!S$65 -> 4163773.2
C17: SEP | E17: SEP | F17: ALL | G17: ALL | H17: Government final consumption P.3g | I17: FD_3 | J17: abs-b | K17: =SUM(X17:AL17)/1000000 -> 41.63794 | X17: =VLOOKUP($C17,'MSET pivots'!$B$4:$H$14,$H$3,FALSE)*1000000*$I$3*'MSET pivots'!E$65 -> 1387952.2 | Y17: =VLOOKUP($C17,'MSET pivots'!$B$4:$H$14,$H$3,FALSE)*1000000*$I$3*'MSET pivots'!F$65 -> 1586225.1 | Z17: =VLOOKUP($C17,'MSET pivots'!$B$4:$H$14,$H$3,FALSE)*1000000*$I$3*'MSET pivots'!G$65 -> 1784498 | AA17: =VLOOKUP($C17,'MSET pivots'!$B$4:$H$14,$H$3,FALSE)*1000000*$I$3*'MSET pivots'!H$65 -> 1982771 | AB17: =VLOOKUP($C17,'MSET pivots'!$B$4:$H$14,$H$3,FALSE)*1000000*$I$3*'MSET pivots'!I$65 -> 2181043.9 | AC17: =VLOOKUP($C17,'MSET pivots'!$B$4:$H$14,$H$3,FALSE)*1000000*$I$3*'MSET pivots'!J$65 -> 2379316.8 | AD17: =VLOOKUP($C17,'MSET pivots'!$B$4:$H$14,$H$3,FALSE)*1000000*$I$3*'MSET pivots'!K$65 -> 2577589.8 | AE17: =VLOOKUP($C17,'MSET pivots'!$B$4:$H$14,$H$3,FALSE)*1000000*$I$3*'MSET pivots'!L$65 -> 2775862.7 | ... AL17: =VLOOKUP($C17,'MSET pivots'!$B$4:$H$14,$H$3,FALSE)*1000000*$I$3*'MSET pivots'!S$65 -> 4163773.2
C18: AFR | E18: AFR | F18: ALL | G18: ALL | H18: Household final consumption P.3h | I18: FD_1 | J18: abs-b | K18: =SUM(X18:AL18)/1000000 -> 30.360582 | X18: =VLOOKUP($C18,'MSET pivots'!$B$4:$H$14,$H$3,FALSE)*1000000*$I$2*'MSET pivots'!E$65 -> 1012034.6 | Y18: =VLOOKUP($C18,'MSET pivots'!$B$4:$H$14,$H$3,FALSE)*1000000*$I$2*'MSET pivots'!F$65 -> 1156606.6 | Z18: =VLOOKUP($C18,'MSET pivots'!$B$4:$H$14,$H$3,FALSE)*1000000*$I$2*'MSET pivots'!G$65 -> 1301178.7 | AA18: =VLOOKUP($C18,'MSET pivots'!$B$4:$H$14,$H$3,FALSE)*1000000*$I$2*'MSET pivots'!H$65 -> 1445750.7 | AB18: =VLOOKUP($C18,'MSET pivots'!$B$4:$H$14,$H$3,FALSE)*1000000*$I$2*'MSET pivots'!I$65 -> 1590322.7 | AC18: =VLOOKUP($C18,'MSET pivots'!$B$4:$H$14,$H$3,FALSE)*1000000*$I$2*'MSET pivots'!J$65 -> 1734894.8 | AD18: =VLOOKUP($C18,'MSET pivots'!$B$4:$H$14,$H$3,FALSE)*1000000*$I$2*'MSET pivots'!K$65 -> 1879466.8 | AE18: =VLOOKUP($C18,'MSET pivots'!$B$4:$H$14,$H$3,FALSE)*1000000*$I$2*'MSET pivots'!L$65 -> 2024038.8 | ... AL18: =VLOOKUP($C18,'MSET pivots'!$B$4:$H$14,$H$3,FALSE)*1000000*$I$2*'MSET pivots'!S$65 -> 3036043
C19: AFR | E19: AFR | F19: ALL | G19: ALL | H19: Government final consumption P.3g | I19: FD_3 | J19: abs-b | K19: =SUM(X19:AL19)/1000000 -> 30.360582 | X19: =VLOOKUP($C19,'MSET pivots'!$B$4:$H$14,$H$3,FALSE)*1000000*$I$3*'MSET pivots'!E$65 -> 1012034.6 | Y19: =VLOOKUP($C19,'MSET pivots'!$B$4:$H$14,$H$3,FALSE)*1000000*$I$3*'MSET pivots'!F$65 -> 1156606.6 | Z19: =VLOOKUP($C19,'MSET pivots'!$B$4:$H$14,$H$3,FALSE)*1000000*$I$3*'MSET pivots'!G$65 -> 1301178.7 | AA19: =VLOOKUP($C19,'MSET pivots'!$B$4:$H$14,$H$3,FALSE)*1000000*$I$3*'MSET pivots'!H$65 -> 1445750.7 | AB19: =VLOOKUP($C19,'MSET pivots'!$B$4:$H$14,$H$3,FALSE)*1000000*$I$3*'MSET pivots'!I$65 -> 1590322.7 | AC19: =VLOOKUP($C19,'MSET pivots'!$B$4:$H$14,$H$3,FALSE)*1000000*$I$3*'MSET pivots'!J$65 -> 1734894.8 | AD19: =VLOOKUP($C19,'MSET pivots'!$B$4:$H$14,$H$3,FALSE)*1000000*$I$3*'MSET pivots'!K$65 -> 1879466.8 | AE19: =VLOOKUP($C19,'MSET pivots'!$B$4:$H$14,$H$3,FALSE)*1000000*$I$3*'MSET pivots'!L$65 -> 2024038.8 | ... AL19: =VLOOKUP($C19,'MSET pivots'!$B$4:$H$14,$H$3,FALSE)*1000000*$I$3*'MSET pivots'!S$65 -> 3036043
C20: EAS | E20: EAS | F20: ALL | G20: ALL | H20: Household final consumption P.3h | I20: FD_1 | J20: abs-b | K20: =SUM(X20:AL20)/1000000 -> 157.47481 | X20: =VLOOKUP($C20,'MSET pivots'!$B$4:$H$14,$H$3,FALSE)*1000000*$I$2*'MSET pivots'!E$65 -> 5249239 | Y20: =VLOOKUP($C20,'MSET pivots'!$B$4:$H$14,$H$3,FALSE)*1000000*$I$2*'MSET pivots'!F$65 -> 5999107.7 | Z20: =VLOOKUP($C20,'MSET pivots'!$B$4:$H$14,$H$3,FALSE)*1000000*$I$2*'MSET pivots'!G$65 -> 6748976.5 | AA20: =VLOOKUP($C20,'MSET pivots'!$B$4:$H$14,$H$3,FALSE)*1000000*$I$2*'MSET pivots'!H$65 -> 7498845.3 | AB20: =VLOOKUP($C20,'MSET pivots'!$B$4:$H$14,$H$3,FALSE)*1000000*$I$2*'MSET pivots'!I$65 -> 8248714.1 | AC20: =VLOOKUP($C20,'MSET pivots'!$B$4:$H$14,$H$3,FALSE)*1000000*$I$2*'MSET pivots'!J$65 -> 8998582.9 | AD20: =VLOOKUP($C20,'MSET pivots'!$B$4:$H$14,$H$3,FALSE)*1000000*$I$2*'MSET pivots'!K$65 -> 9748451.7 | AE20: =VLOOKUP($C20,'MSET pivots'!$B$4:$H$14,$H$3,FALSE)*1000000*$I$2*'MSET pivots'!L$65 -> 10498320 | ... AL20: =VLOOKUP($C20,'MSET pivots'!$B$4:$H$14,$H$3,FALSE)*1000000*$I$2*'MSET pivots'!S$65 -> 15747402
C21: EAS | E21: EAS | F21: ALL | G21: ALL | H21: Government final consumption P.3g | I21: FD_3 | J21: abs-b | K21: =SUM(X21:AL21)/1000000 -> 157.47481 | X21: =VLOOKUP($C21,'MSET pivots'!$B$4:$H$14,$H$3,FALSE)*1000000*$I$3*'MSET pivots'!E$65 -> 5249239 | Y21: =VLOOKUP($C21,'MSET pivots'!$B$4:$H$14,$H$3,FALSE)*1000000*$I$3*'MSET pivots'!F$65 -> 5999107.7 | Z21: =VLOOKUP($C21,'MSET pivots'!$B$4:$H$14,$H$3,FALSE)*1000000*$I$3*'MSET pivots'!G$65 -> 6748976.5 | AA21: =VLOOKUP($C21,'MSET pivots'!$B$4:$H$14,$H$3,FALSE)*1000000*$I$3*'MSET pivots'!H$65 -> 7498845.3 | AB21: =VLOOKUP($C21,'MSET pivots'!$B$4:$H$14,$H$3,FALSE)*1000000*$I$3*'MSET pivots'!I$65 -> 8248714.1 | AC21: =VLOOKUP($C21,'MSET pivots'!$B$4:$H$14,$H$3,FALSE)*1000000*$I$3*'MSET pivots'!J$65 -> 8998582.9 | AD21: =VLOOKUP($C21,'MSET pivots'!$B$4:$H$14,$H$3,FALSE)*1000000*$I$3*'MSET pivots'!K$65 -> 9748451.7 | AE21: =VLOOKUP($C21,'MSET pivots'!$B$4:$H$14,$H$3,FALSE)*1000000*$I$3*'MSET pivots'!L$65 -> 10498320 | ... AL21: =VLOOKUP($C21,'MSET pivots'!$B$4:$H$14,$H$3,FALSE)*1000000*$I$3*'MSET pivots'!S$65 -> 15747402
C22: LAC | E22: LAC | F22: ALL | G22: ALL | H22: Household final consumption P.3h | I22: FD_1 | J22: abs-b | K22: =SUM(X22:AL22)/1000000 -> 38.229821 | X22: =VLOOKUP($C22,'MSET pivots'!$B$4:$H$14,$H$3,FALSE)*1000000*$I$2*'MSET pivots'!E$65 -> 1274346.5 | Y22: =VLOOKUP($C22,'MSET pivots'!$B$4:$H$14,$H$3,FALSE)*1000000*$I$2*'MSET pivots'!F$65 -> 1456390.5 | Z22: =VLOOKUP($C22,'MSET pivots'!$B$4:$H$14,$H$3,FALSE)*1000000*$I$2*'MSET pivots'!G$65 -> 1638434.6 | AA22: =VLOOKUP($C22,'MSET pivots'!$B$4:$H$14,$H$3,FALSE)*1000000*$I$2*'MSET pivots'!H$65 -> 1820478.6 | AB22: =VLOOKUP($C22,'MSET pivots'!$B$4:$H$14,$H$3,FALSE)*1000000*$I$2*'MSET pivots'!I$65 -> 2002522.6 | AC22: =VLOOKUP($C22,'MSET pivots'!$B$4:$H$14,$H$3,FALSE)*1000000*$I$2*'MSET pivots'!J$65 -> 2184566.7 | AD22: =VLOOKUP($C22,'MSET pivots'!$B$4:$H$14,$H$3,FALSE)*1000000*$I$2*'MSET pivots'!K$65 -> 2366610.7 | AE22: =VLOOKUP($C22,'MSET pivots'!$B$4:$H$14,$H$3,FALSE)*1000000*$I$2*'MSET pivots'!L$65 -> 2548654.7 | ... AL22: =VLOOKUP($C22,'MSET pivots'!$B$4:$H$14,$H$3,FALSE)*1000000*$I$2*'MSET pivots'!S$65 -> 3822963
C23: LAC | E23: LAC | F23: ALL | G23: ALL | H23: Government final consumption P.3g | I23: FD_3 | J23: abs-b | K23: =SUM(X23:AL23)/1000000 -> 38.229821 | X23: =VLOOKUP($C23,'MSET pivots'!$B$4:$H$14,$H$3,FALSE)*1000000*$I$3*'MSET pivots'!E$65 -> 1274346.5 | Y23: =VLOOKUP($C23,'MSET pivots'!$B$4:$H$14,$H$3,FALSE)*1000000*$I$3*'MSET pivots'!F$65 -> 1456390.5 | Z23: =VLOOKUP($C23,'MSET pivots'!$B$4:$H$14,$H$3,FALSE)*1000000*$I$3*'MSET pivots'!G$65 -> 1638434.6 | AA23: =VLOOKUP($C23,'MSET pivots'!$B$4:$H$14,$H$3,FALSE)*1000000*$I$3*'MSET pivots'!H$65 -> 1820478.6 | AB23: =VLOOKUP($C23,'MSET pivots'!$B$4:$H$14,$H$3,FALSE)*1000000*$I$3*'MSET pivots'!I$65 -> 2002522.6 | AC23: =VLOOKUP($C23,'MSET pivots'!$B$4:$H$14,$H$3,FALSE)*1000000*$I$3*'MSET pivots'!J$65 -> 2184566.7 | AD23: =VLOOKUP($C23,'MSET pivots'!$B$4:$H$14,$H$3,FALSE)*1000000*$I$3*'MSET pivots'!K$65 -> 2366610.7 | AE23: =VLOOKUP($C23,'MSET pivots'!$B$4:$H$14,$H$3,FALSE)*1000000*$I$3*'MSET pivots'!L$65 -> 2548654.7 | ... AL23: =VLOOKUP($C23,'MSET pivots'!$B$4:$H$14,$H$3,FALSE)*1000000*$I$3*'MSET pivots'!S$65 -> 3822963
C24: MEN | E24: MEN | F24: ALL | G24: ALL | H24: Household final consumption P.3h | I24: FD_1 | J24: abs-b | K24: =SUM(X24:AL24)/1000000 -> 18.970318 | X24: =VLOOKUP($C24,'MSET pivots'!$B$4:$H$14,$H$3,FALSE)*1000000*$I$2*'MSET pivots'!E$65 -> 632353.43 | Y24: =VLOOKUP($C24,'MSET pivots'!$B$4:$H$14,$H$3,FALSE)*1000000*$I$2*'MSET pivots'!F$65 -> 722686.93 | Z24: =VLOOKUP($C24,'MSET pivots'!$B$4:$H$14,$H$3,FALSE)*1000000*$I$2*'MSET pivots'!G$65 -> 813020.42 | AA24: =VLOOKUP($C24,'MSET pivots'!$B$4:$H$14,$H$3,FALSE)*1000000*$I$2*'MSET pivots'!H$65 -> 903353.92 | AB24: =VLOOKUP($C24,'MSET pivots'!$B$4:$H$14,$H$3,FALSE)*1000000*$I$2*'MSET pivots'!I$65 -> 993687.41 | AC24: =VLOOKUP($C24,'MSET pivots'!$B$4:$H$14,$H$3,FALSE)*1000000*$I$2*'MSET pivots'!J$65 -> 1084020.9 | AD24: =VLOOKUP($C24,'MSET pivots'!$B$4:$H$14,$H$3,FALSE)*1000000*$I$2*'MSET pivots'!K$65 -> 1174354.4 | AE24: =VLOOKUP($C24,'MSET pivots'!$B$4:$H$14,$H$3,FALSE)*1000000*$I$2*'MSET pivots'!L$65 -> 1264687.9 | ... AL24: =VLOOKUP($C24,'MSET pivots'!$B$4:$H$14,$H$3,FALSE)*1000000*$I$2*'MSET pivots'!S$65 -> 1897022.4
C25: MEN | E25: MEN | F25: ALL | G25: ALL | H25: Government final consumption P.3g | I25: FD_3 | J25: abs-b | K25: =SUM(X25:AL25)/1000000 -> 18.970318 | X25: =VLOOKUP($C25,'MSET pivots'!$B$4:$H$14,$H$3,FALSE)*1000000*$I$3*'MSET pivots'!E$65 -> 632353.43 | Y25: =VLOOKUP($C25,'MSET pivots'!$B$4:$H$14,$H$3,FALSE)*1000000*$I$3*'MSET pivots'!F$65 -> 722686.93 | Z25: =VLOOKUP($C25,'MSET pivots'!$B$4:$H$14,$H$3,FALSE)*1000000*$I$3*'MSET pivots'!G$65 -> 813020.42 | AA25: =VLOOKUP($C25,'MSET pivots'!$B$4:$H$14,$H$3,FALSE)*1000000*$I$3*'MSET pivots'!H$65 -> 903353.92 | AB25: =VLOOKUP($C25,'MSET pivots'!$B$4:$H$14,$H$3,FALSE)*1000000*$I$3*'MSET pivots'!I$65 -> 993687.41 | AC25: =VLOOKUP($C25,'MSET pivots'!$B$4:$H$14,$H$3,FALSE)*1000000*$I$3*'MSET pivots'!J$65 -> 1084020.9 | AD25: =VLOOKUP($C25,'MSET pivots'!$B$4:$H$14,$H$3,FALSE)*1000000*$I$3*'MSET pivots'!K$65 -> 1174354.4 | AE25: =VLOOKUP($C25,'MSET pivots'!$B$4:$H$14,$H$3,FALSE)*1000000*$I$3*'MSET pivots'!L$65 -> 1264687.9 | ... AL25: =VLOOKUP($C25,'MSET pivots'!$B$4:$H$14,$H$3,FALSE)*1000000*$I$3*'MSET pivots'!S$65 -> 1897022.4
B26: Pakistan | C26: SAS | E26: SAS | F26: ALL | G26: ALL | H26: Household final consumption P.3h | I26: FD_1 | J26: abs-b | K26: =SUM(X26:AL26)/1000000 -> 51.096887 | W26: ='Preliminary results'!$C$31*1000000*I2 -> 902060.73 | X26: =VLOOKUP($C26,'MSET pivots'!$B$4:$H$14,$H$3,FALSE)*1000000*$I$2*'MSET pivots'!E$65 -> 1703255.1 | Y26: =VLOOKUP($C26,'MSET pivots'!$B$4:$H$14,$H$3,FALSE)*1000000*$I$2*'MSET pivots'!F$65 -> 1946570 | Z26: =VLOOKUP($C26,'MSET pivots'!$B$4:$H$14,$H$3,FALSE)*1000000*$I$2*'MSET pivots'!G$65 -> 2189884.8 | AA26: =VLOOKUP($C26,'MSET pivots'!$B$4:$H$14,$H$3,FALSE)*1000000*$I$2*'MSET pivots'!H$65 -> 2433199.7 | AB26: =VLOOKUP($C26,'MSET pivots'!$B$4:$H$14,$H$3,FALSE)*1000000*$I$2*'MSET pivots'!I$65 -> 2676514.5 | AC26: =VLOOKUP($C26,'MSET pivots'!$B$4:$H$14,$H$3,FALSE)*1000000*$I$2*'MSET pivots'!J$65 -> 2919829.4 | AD26: =VLOOKUP($C26,'MSET pivots'!$B$4:$H$14,$H$3,FALSE)*1000000*$I$2*'MSET pivots'!K$65 -> 3163144.3 | AE26: =VLOOKUP($C26,'MSET pivots'!$B$4:$H$14,$H$3,FALSE)*1000000*$I$2*'MSET pivots'!L$65 -> 3406459.1 | ... AL26: =VLOOKUP($C26,'MSET pivots'!$B$4:$H$14,$H$3,FALSE)*1000000*$I$2*'MSET pivots'!S$65 -> 5109663.1
B27: Pakistan | C27: SAS | E27: SAS | F27: ALL | G27: ALL | H27: Government final consumption P.3g | I27: FD_3 | J27: abs-b | K27: =SUM(X27:AL27)/1000000 -> 51.096887 | W27: ='Preliminary results'!$C$31*1000000*I3 -> 902060.73 | X27: =VLOOKUP($C27,'MSET pivots'!$B$4:$H$14,$H$3,FALSE)*1000000*$I$3*'MSET pivots'!E$65 -> 1703255.1 | Y27: =VLOOKUP($C27,'MSET pivots'!$B$4:$H$14,$H$3,FALSE)*1000000*$I$3*'MSET pivots'!F$65 -> 1946570 | Z27: =VLOOKUP($C27,'MSET pivots'!$B$4:$H$14,$H$3,FALSE)*1000000*$I$3*'MSET pivots'!G$65 -> 2189884.8 | AA27: =VLOOKUP($C27,'MSET pivots'!$B$4:$H$14,$H$3,FALSE)*1000000*$I$3*'MSET pivots'!H$65 -> 2433199.7 | AB27: =VLOOKUP($C27,'MSET pivots'!$B$4:$H$14,$H$3,FALSE)*1000000*$I$3*'MSET pivots'!I$65 -> 2676514.5 | AC27: =VLOOKUP($C27,'MSET pivots'!$B$4:$H$14,$H$3,FALSE)*1000000*$I$3*'MSET pivots'!J$65 -> 2919829.4 | AD27: =VLOOKUP($C27,'MSET pivots'!$B$4:$H$14,$H$3,FALSE)*1000000*$I$3*'MSET pivots'!K$65 -> 3163144.3 | AE27: =VLOOKUP($C27,'MSET pivots'!$B$4:$H$14,$H$3,FALSE)*1000000*$I$3*'MSET pivots'!L$65 -> 3406459.1 | ... AL27: =VLOOKUP($C27,'MSET pivots'!$B$4:$H$14,$H$3,FALSE)*1000000*$I$3*'MSET pivots'!S$65 -> 5109663.1
C28: AJN | E28: AJN | F28: ALL | G28: ALL | H28: Government final consumption P.3g | I28: FD_3 | J28: rel-b | K28: =SUM(X28:AL28) -> -0.080057088 | X28: =VLOOKUP($C28,'MSET pivots'!$J$4:$P$14,'Final demand(6)'!$H$3,FALSE)*'MSET pivots'!E$65 -> -0.0026686096 | Y28: =VLOOKUP($C28,'MSET pivots'!$J$4:$P$14,'Final demand(6)'!$H$3,FALSE)*'MSET pivots'!F$65 -> -0.0030498281 | Z28: =VLOOKUP($C28,'MSET pivots'!$J$4:$P$14,'Final demand(6)'!$H$3,FALSE)*'MSET pivots'!G$65 -> -0.0034310466 | AA28: =VLOOKUP($C28,'MSET pivots'!$J$4:$P$14,'Final demand(6)'!$H$3,FALSE)*'MSET pivots'!H$65 -> -0.0038122652 | AB28: =VLOOKUP($C28,'MSET pivots'!$J$4:$P$14,'Final demand(6)'!$H$3,FALSE)*'MSET pivots'!I$65 -> -0.0041934837 | AC28: =VLOOKUP($C28,'MSET pivots'!$J$4:$P$14,'Final demand(6)'!$H$3,FALSE)*'MSET pivots'!J$65 -> -0.0045747022 | AD28: =VLOOKUP($C28,'MSET pivots'!$J$4:$P$14,'Final demand(6)'!$H$3,FALSE)*'MSET pivots'!K$65 -> -0.0049559207 | AE28: =VLOOKUP($C28,'MSET pivots'!$J$4:$P$14,'Final demand(6)'!$H$3,FALSE)*'MSET pivots'!L$65 -> -0.0053371392 | ... AL28: =VLOOKUP($C28,'MSET pivots'!$J$4:$P$14,'Final demand(6)'!$H$3,FALSE)*'MSET pivots'!S$65 -> -0.0080056688
C29: EEA | E29: EEA | F29: ALL | G29: ALL | H29: Government final consumption P.3g | I29: FD_3 | J29: rel-b | K29: =SUM(X29:AL29) -> -0.09054676 | X29: =VLOOKUP($C29,'MSET pivots'!$J$4:$P$14,'Final demand(6)'!$H$3,FALSE)*'MSET pivots'!E$65 -> -0.0030182706 | Y29: =VLOOKUP($C29,'MSET pivots'!$J$4:$P$14,'Final demand(6)'!$H$3,FALSE)*'MSET pivots'!F$65 -> -0.0034494392 | Z29: =VLOOKUP($C29,'MSET pivots'!$J$4:$P$14,'Final demand(6)'!$H$3,FALSE)*'MSET pivots'!G$65 -> -0.0038806078 | AA29: =VLOOKUP($C29,'MSET pivots'!$J$4:$P$14,'Final demand(6)'!$H$3,FALSE)*'MSET pivots'!H$65 -> -0.0043117763 | AB29: =VLOOKUP($C29,'MSET pivots'!$J$4:$P$14,'Final demand(6)'!$H$3,FALSE)*'MSET pivots'!I$65 -> -0.0047429449 | AC29: =VLOOKUP($C29,'MSET pivots'!$J$4:$P$14,'Final demand(6)'!$H$3,FALSE)*'MSET pivots'!J$65 -> -0.0051741135 | AD29: =VLOOKUP($C29,'MSET pivots'!$J$4:$P$14,'Final demand(6)'!$H$3,FALSE)*'MSET pivots'!K$65 -> -0.0056052821 | AE29: =VLOOKUP($C29,'MSET pivots'!$J$4:$P$14,'Final demand(6)'!$H$3,FALSE)*'MSET pivots'!L$65 -> -0.0060364507 | ... AL29: =VLOOKUP($C29,'MSET pivots'!$J$4:$P$14,'Final demand(6)'!$H$3,FALSE)*'MSET pivots'!S$65 -> -0.0090546307
B30: United Kingdom | C30: EUR | E30: EUR | F30: ALL | G30: ALL | H30: Government final consumption P.3g | I30: FD_3 | J30: rel-b | K30: =SUM(X30:AL30) -> -0.064028108 | W30: =('Preliminary results'!$C$31)/'Baseline govt spend'!$E$51 -> 0.00066729533 | X30: =VLOOKUP($C30,'MSET pivots'!$J$4:$P$14,'Final demand(6)'!$H$3,FALSE)*'MSET pivots'!E$65 -> -0.0021343023 | Y30: =VLOOKUP($C30,'MSET pivots'!$J$4:$P$14,'Final demand(6)'!$H$3,FALSE)*'MSET pivots'!F$65 -> -0.0024391935 | Z30: =VLOOKUP($C30,'MSET pivots'!$J$4:$P$14,'Final demand(6)'!$H$3,FALSE)*'MSET pivots'!G$65 -> -0.0027440846 | AA30: =VLOOKUP($C30,'MSET pivots'!$J$4:$P$14,'Final demand(6)'!$H$3,FALSE)*'MSET pivots'!H$65 -> -0.0030489758 | AB30: =VLOOKUP($C30,'MSET pivots'!$J$4:$P$14,'Final demand(6)'!$H$3,FALSE)*'MSET pivots'!I$65 -> -0.003353867 | AC30: =VLOOKUP($C30,'MSET pivots'!$J$4:$P$14,'Final demand(6)'!$H$3,FALSE)*'MSET pivots'!J$65 -> -0.0036587582 | AD30: =VLOOKUP($C30,'MSET pivots'!$J$4:$P$14,'Final demand(6)'!$H$3,FALSE)*'MSET pivots'!K$65 -> -0.0039636493 | AE30: =VLOOKUP($C30,'MSET pivots'!$J$4:$P$14,'Final demand(6)'!$H$3,FALSE)*'MSET pivots'!L$65 -> -0.0042685405 | ... AL30: =VLOOKUP($C30,'MSET pivots'!$J$4:$P$14,'Final demand(6)'!$H$3,FALSE)*'MSET pivots'!S$65 -> -0.0064027788
C31: NAM | E31: NAM | F31: ALL | G31: ALL | H31: Government final consumption P.3g | I31: FD_3 | J31: rel-b | K31: =SUM(X31:AL31) -> -0.1731371 | X31: =VLOOKUP($C31,'MSET pivots'!$J$4:$P$14,'Final demand(6)'!$H$3,FALSE)*'MSET pivots'!E$65 -> -0.0057713232 | Y31: =VLOOKUP($C31,'MSET pivots'!$J$4:$P$14,'Final demand(6)'!$H$3,FALSE)*'MSET pivots'!F$65 -> -0.0065957732 | Z31: =VLOOKUP($C31,'MSET pivots'!$J$4:$P$14,'Final demand(6)'!$H$3,FALSE)*'MSET pivots'!G$65 -> -0.0074202232 | AA31: =VLOOKUP($C31,'MSET pivots'!$J$4:$P$14,'Final demand(6)'!$H$3,FALSE)*'MSET pivots'!H$65 -> -0.0082446732 | AB31: =VLOOKUP($C31,'MSET pivots'!$J$4:$P$14,'Final demand(6)'!$H$3,FALSE)*'MSET pivots'!I$65 -> -0.0090691232 | AC31: =VLOOKUP($C31,'MSET pivots'!$J$4:$P$14,'Final demand(6)'!$H$3,FALSE)*'MSET pivots'!J$65 -> -0.0098935732 | AD31: =VLOOKUP($C31,'MSET pivots'!$J$4:$P$14,'Final demand(6)'!$H$3,FALSE)*'MSET pivots'!K$65 -> -0.010718023 | AE31: =VLOOKUP($C31,'MSET pivots'!$J$4:$P$14,'Final demand(6)'!$H$3,FALSE)*'MSET pivots'!L$65 -> -0.011542473 | ... AL31: =VLOOKUP($C31,'MSET pivots'!$J$4:$P$14,'Final demand(6)'!$H$3,FALSE)*'MSET pivots'!S$65 -> -0.017313623
G44: =_xlfn.IFNA(INDEX('[1]Sector list'!$A$2:$A$122,MATCH(F44,'[1]Sector list'!$B$2:$B$122,0)),"") | I44: =_xlfn.IFNA(INDEX('[1]FD list'!$A$2:$A$122,MATCH(H44,'[1]FD list'!$B$2:$B$122,0)),"")
G45: =_xlfn.IFNA(INDEX('[1]Sector list'!$A$2:$A$122,MATCH(F45,'[1]Sector list'!$B$2:$B$122,0)),"") | I45: =_xlfn.IFNA(INDEX('[1]FD list'!$A$2:$A$122,MATCH(H45,'[1]FD list'!$B$2:$B$122,0)),"")
G46: =_xlfn.IFNA(INDEX('[1]Sector list'!$A$2:$A$122,MATCH(F46,'[1]Sector list'!$B$2:$B$122,0)),"") | I46: =_xlfn.IFNA(INDEX('[1]FD list'!$A$2:$A$122,MATCH(H46,'[1]FD list'!$B$2:$B$122,0)),"")
G47: =_xlfn.IFNA(INDEX('[1]Sector list'!$A$2:$A$122,MATCH(F47,'[1]Sector list'!$B$2:$B$122,0)),"") | I47: =_xlfn.IFNA(INDEX('[1]FD list'!$A$2:$A$122,MATCH(H47,'[1]FD list'!$B$2:$B$122,0)),"")
G48: =_xlfn.IFNA(INDEX('[1]Sector list'!$A$2:$A$122,MATCH(F48,'[1]Sector list'!$B$2:$B$122,0)),"") | I48: =_xlfn.IFNA(INDEX('[1]FD list'!$A$2:$A$122,MATCH(H48,'[1]FD list'!$B$2:$B$122,0)),"")
G49: =_xlfn.IFNA(INDEX('[1]Sector list'!$A$2:$A$122,MATCH(F49,'[1]Sector list'!$B$2:$B$122,0)),"") | I49: =_xlfn.IFNA(INDEX('[1]FD list'!$A$2:$A$122,MATCH(H49,'[1]FD list'!$B$2:$B$122,0)),"")
G50: =_xlfn.IFNA(INDEX('[1]Sector list'!$A$2:$A$122,MATCH(F50,'[1]Sector list'!$B$2:$B$122,0)),"") | I50: =_xlfn.IFNA(INDEX('[1]FD list'!$A$2:$A$122,MATCH(H50,'[1]FD list'!$B$2:$B$122,0)),"")
G51: =_xlfn.IFNA(INDEX('[1]Sector list'!$A$2:$A$122,MATCH(F51,'[1]Sector list'!$B$2:$B$122,0)),"") | I51: =_xlfn.IFNA(INDEX('[1]FD list'!$A$2:$A$122,MATCH(H51,'[1]FD list'!$B$2:$B$122,0)),"")
G52: =_xlfn.IFNA(INDEX('[1]Sector list'!$A$2:$A$122,MATCH(F52,'[1]Sector list'!$B$2:$B$122,0)),"") | I52: =_xlfn.IFNA(INDEX('[1]FD list'!$A$2:$A$122,MATCH(H52,'[1]FD list'!$B$2:$B$122,0)),"")
G53: =_xlfn.IFNA(INDEX('[1]Sector list'!$A$2:$A$122,MATCH(F53,'[1]Sector list'!$B$2:$B$122,0)),"") | I53: =_xlfn.IFNA(INDEX('[1]FD list'!$A$2:$A$122,MATCH(H53,'[1]FD list'!$B$2:$B$122,0)),"")
G54: =_xlfn.IFNA(INDEX('[1]Sector list'!$A$2:$A$122,MATCH(F54,'[1]Sector list'!$B$2:$B$122,0)),"") | I54: =_xlfn.IFNA(INDEX('[1]FD list'!$A$2:$A$122,MATCH(H54,'[1]FD list'!$B$2:$B$122,0)),"")
G55: =_xlfn.IFNA(INDEX('[1]Sector list'!$A$2:$A$122,MATCH(F55,'[1]Sector list'!$B$2:$B$122,0)),"") | I55: =_xlfn.IFNA(INDEX('[1]FD list'!$A$2:$A$122,MATCH(H55,'[1]FD list'!$B$2:$B$122,0)),"")
... G69: =_xlfn.IFNA(INDEX('[1]Sector list'!$A$2:$A$122,MATCH(F69,'[1]Sector list'!$B$2:$B$122,0)),"") | I69: =_xlfn.IFNA(INDEX('[1]FD list'!$A$2:$A$122,MATCH(H69,'[1]FD list'!$B$2:$B$122,0)),"")
I70: =_xlfn.IFNA(INDEX('[1]FD list'!$A$2:$A$122,MATCH(H70,'[1]FD list'!$B$2:$B$122,0)),"")
I71: =_xlfn.IFNA(INDEX('[1]FD list'!$A$2:$A$122,MATCH(H71,'[1]FD list'!$B$2:$B$122,0)),"")
I72: =_xlfn.IFNA(INDEX('[1]FD list'!$A$2:$A$122,MATCH(H72,'[1]FD list'!$B$2:$B$122,0)),"")
I73: =_xlfn.IFNA(INDEX('[1]FD list'!$A$2:$A$122,MATCH(H73,'[1]FD list'!$B$2:$B$122,0)),"")
I74: =_xlfn.IFNA(INDEX('[1]FD list'!$A$2:$A$122,MATCH(H74,'[1]FD list'!$B$2:$B$122,0)),"")
I75: =_xlfn.IFNA(INDEX('[1]FD list'!$A$2:$A$122,MATCH(H75,'[1]FD list'!$B$2:$B$122,0)),"")
I76: =_xlfn.IFNA(INDEX('[1]FD list'!$A$2:$A$122,MATCH(H76,'[1]FD list'!$B$2:$B$122,0)),"")
I77: =_xlfn.IFNA(INDEX('[1]FD list'!$A$2:$A$122,MATCH(H77,'[1]FD list'!$B$2:$B$122,0)),"")
I78: =_xlfn.IFNA(INDEX('[1]FD list'!$A$2:$A$122,MATCH(H78,'[1]FD list'!$B$2:$B$122,0)),"")
I79: =_xlfn.IFNA(INDEX('[1]FD list'!$A$2:$A$122,MATCH(H79,'[1]FD list'!$B$2:$B$122,0)),"")
I80: =_xlfn.IFNA(INDEX('[1]FD list'!$A$2:$A$122,MATCH(H80,'[1]FD list'!$B$2:$B$122,0)),"")
I81: =_xlfn.IFNA(INDEX('[1]FD list'!$A$2:$A$122,MATCH(H81,'[1]FD list'!$B$2:$B$122,0)),"")
... I97: =_xlfn.IFNA(INDEX('[1]FD list'!$A$2:$A$122,MATCH(H97,'[1]FD list'!$B$2:$B$122,0)),"")
I98: =_xlfn.IFNA(INDEX('[1]Sector list'!$A$2:$A$122,MATCH(H98,'[1]Sector list'!$B$2:$B$122,0)),"")
I99: =_xlfn.IFNA(INDEX('[1]Sector list'!$A$2:$A$122,MATCH(H99,'[1]Sector list'!$B$2:$B$122,0)),"")
I100: =_xlfn.IFNA(INDEX('[1]Sector list'!$A$2:$A$122,MATCH(H100,'[1]Sector list'!$B$2:$B$122,0)),"")
I101: =_xlfn.IFNA(INDEX('[1]Sector list'!$A$2:$A$122,MATCH(H101,'[1]Sector list'!$B$2:$B$122,0)),"")
I102: =_xlfn.IFNA(INDEX('[1]Sector list'!$A$2:$A$122,MATCH(H102,'[1]Sector list'!$B$2:$B$122,0)),"")
I103: =_xlfn.IFNA(INDEX('[1]Sector list'!$A$2:$A$122,MATCH(H103,'[1]Sector list'!$B$2:$B$122,0)),"")
I104: =_xlfn.IFNA(INDEX('[1]Sector list'!$A$2:$A$122,MATCH(H104,'[1]Sector list'!$B$2:$B$122,0)),"")
I105: =_xlfn.IFNA(INDEX('[1]Sector list'!$A$2:$A$122,MATCH(H105,'[1]Sector list'!$B$2:$B$122,0)),"")
I106: =_xlfn.IFNA(INDEX('[1]Sector list'!$A$2:$A$122,MATCH(H106,'[1]Sector list'!$B$2:$B$122,0)),"")
I107: =_xlfn.IFNA(INDEX('[1]Sector list'!$A$2:$A$122,MATCH(H107,'[1]Sector list'!$B$2:$B$122,0)),"")
I108: =_xlfn.IFNA(INDEX('[1]Sector list'!$A$2:$A$122,MATCH(H108,'[1]Sector list'!$B$2:$B$122,0)),"")
I109: =_xlfn.IFNA(INDEX('[1]Sector list'!$A$2:$A$122,MATCH(H109,'[1]Sector list'!$B$2:$B$122,0)),"")
... I905: =_xlfn.IFNA(INDEX('[1]Sector list'!$A$2:$A$122,MATCH(H905,'[1]Sector list'!$B$2:$B$122,0)),"")

Sheet Investment by(6)
B2: Investment BY sector changes | G2: ='Final demand(6)'!H2 -> G77+C_central | H2: ='Final demand(6)'!H3 -> 6
B3: Fields with * must be specified manually or filled in automatically by selecting values in other columns
B5: Country | C5: Country ISO* | D5: Sector investing | E5: Sector investing code* | F5: Type* | G5: Comments
G6: =1/3 -> 0.33333333 | H6: FCF
B8: Germany | C8: =_xlfn.IFNA(INDEX('[2]Country list'!$A$2:$A$166,MATCH(B8,'[2]Country list'!$B$2:$B$166,0)),"") -> DEU | E8: 1-23 | F8: abs | G8: << Increase investment in agricultural sectors in Germany, 1000 kUSD in EVERY sector
G12: relative investment is not possible, because we don’t have an investment baseline right now
C13: REG_imp | E13: PROD_COMM | G13: Current options: abs-b
B14: Start in the next line >>
B15: Country | C15: Country ISO* | D15: Sector investing | E15: Sector investing code* | F15: Type* | G15: Comments | H15: 2019 | I15: 2020 | J15: 2021 | K15: 2022 | L15: 2023 | M15: 2024 | N15: 2025 | O15: 2026 | P15: 2027 | Q15: 2028 | R15: 2029 | S15: 2030 | T15: 2031 | U15: 2032 | V15: 2033 | W15: 2034 | X15: 2035 | Y15: 2036 | Z15: 2037 | AA15: 2038 | AB15: 2039 | AC15: 2040 | AD15: 2041 | AE15: 2042 | AF15: 2043 | AG15: 2044 | AH15: 2045 | AI15: 2046 | AJ15: 2047 | AK15: 2048 | AL15: 2049 | AM15: 2050
C16: SEP | E16: ALL | F16: abs-b | G16: =SUM(T16:AH16)/1000000 -> 41.63794 | T16: =VLOOKUP($C16,'MSET pivots'!$B$4:$H$14,$H$2,FALSE)*1000000*$G$6*'MSET pivots'!E$65 -> 1387952.2 | U16: =VLOOKUP($C16,'MSET pivots'!$B$4:$H$14,$H$2,FALSE)*1000000*$G$6*'MSET pivots'!F$65 -> 1586225.1 | V16: =VLOOKUP($C16,'MSET pivots'!$B$4:$H$14,$H$2,FALSE)*1000000*$G$6*'MSET pivots'!G$65 -> 1784498 | W16: =VLOOKUP($C16,'MSET pivots'!$B$4:$H$14,$H$2,FALSE)*1000000*$G$6*'MSET pivots'!H$65 -> 1982771 | X16: =VLOOKUP($C16,'MSET pivots'!$B$4:$H$14,$H$2,FALSE)*1000000*$G$6*'MSET pivots'!I$65 -> 2181043.9 | Y16: =VLOOKUP($C16,'MSET pivots'!$B$4:$H$14,$H$2,FALSE)*1000000*$G$6*'MSET pivots'!J$65 -> 2379316.8 | Z16: =VLOOKUP($C16,'MSET pivots'!$B$4:$H$14,$H$2,FALSE)*1000000*$G$6*'MSET pivots'!K$65 -> 2577589.8 | AA16: =VLOOKUP($C16,'MSET pivots'!$B$4:$H$14,$H$2,FALSE)*1000000*$G$6*'MSET pivots'!L$65 -> 2775862.7 | ... AH16: =VLOOKUP($C16,'MSET pivots'!$B$4:$H$14,$H$2,FALSE)*1000000*$G$6*'MSET pivots'!S$65 -> 4163773.2
C17: AFR | E17: ALL | F17: abs-b | G17: =SUM(T17:AH17)/1000000 -> 30.360582 | T17: =VLOOKUP($C17,'MSET pivots'!$B$4:$H$14,$H$2,FALSE)*1000000*$G$6*'MSET pivots'!E$65 -> 1012034.6 | U17: =VLOOKUP($C17,'MSET pivots'!$B$4:$H$14,$H$2,FALSE)*1000000*$G$6*'MSET pivots'!F$65 -> 1156606.6 | V17: =VLOOKUP($C17,'MSET pivots'!$B$4:$H$14,$H$2,FALSE)*1000000*$G$6*'MSET pivots'!G$65 -> 1301178.7 | W17: =VLOOKUP($C17,'MSET pivots'!$B$4:$H$14,$H$2,FALSE)*1000000*$G$6*'MSET pivots'!H$65 -> 1445750.7 | X17: =VLOOKUP($C17,'MSET pivots'!$B$4:$H$14,$H$2,FALSE)*1000000*$G$6*'MSET pivots'!I$65 -> 1590322.7 | Y17: =VLOOKUP($C17,'MSET pivots'!$B$4:$H$14,$H$2,FALSE)*1000000*$G$6*'MSET pivots'!J$65 -> 1734894.8 | Z17: =VLOOKUP($C17,'MSET pivots'!$B$4:$H$14,$H$2,FALSE)*1000000*$G$6*'MSET pivots'!K$65 -> 1879466.8 | AA17: =VLOOKUP($C17,'MSET pivots'!$B$4:$H$14,$H$2,FALSE)*1000000*$G$6*'MSET pivots'!L$65 -> 2024038.8 | ... AH17: =VLOOKUP($C17,'MSET pivots'!$B$4:$H$14,$H$2,FALSE)*1000000*$G$6*'MSET pivots'!S$65 -> 3036043
C18: EAS | E18: ALL | F18: abs-b | G18: =SUM(T18:AH18)/1000000 -> 157.47481 | T18: =VLOOKUP($C18,'MSET pivots'!$B$4:$H$14,$H$2,FALSE)*1000000*$G$6*'MSET pivots'!E$65 -> 5249239 | U18: =VLOOKUP($C18,'MSET pivots'!$B$4:$H$14,$H$2,FALSE)*1000000*$G$6*'MSET pivots'!F$65 -> 5999107.7 | V18: =VLOOKUP($C18,'MSET pivots'!$B$4:$H$14,$H$2,FALSE)*1000000*$G$6*'MSET pivots'!G$65 -> 6748976.5 | W18: =VLOOKUP($C18,'MSET pivots'!$B$4:$H$14,$H$2,FALSE)*1000000*$G$6*'MSET pivots'!H$65 -> 7498845.3 | X18: =VLOOKUP($C18,'MSET pivots'!$B$4:$H$14,$H$2,FALSE)*1000000*$G$6*'MSET pivots'!I$65 -> 8248714.1 | Y18: =VLOOKUP($C18,'MSET pivots'!$B$4:$H$14,$H$2,FALSE)*1000000*$G$6*'MSET pivots'!J$65 -> 8998582.9 | Z18: =VLOOKUP($C18,'MSET pivots'!$B$4:$H$14,$H$2,FALSE)*1000000*$G$6*'MSET pivots'!K$65 -> 9748451.7 | AA18: =VLOOKUP($C18,'MSET pivots'!$B$4:$H$14,$H$2,FALSE)*1000000*$G$6*'MSET pivots'!L$65 -> 10498320 | ... AH18: =VLOOKUP($C18,'MSET pivots'!$B$4:$H$14,$H$2,FALSE)*1000000*$G$6*'MSET pivots'!S$65 -> 15747402
C19: LAC | E19: ALL | F19: abs-b | G19: =SUM(T19:AH19)/1000000 -> 38.229821 | T19: =VLOOKUP($C19,'MSET pivots'!$B$4:$H$14,$H$2,FALSE)*1000000*$G$6*'MSET pivots'!E$65 -> 1274346.5 | U19: =VLOOKUP($C19,'MSET pivots'!$B$4:$H$14,$H$2,FALSE)*1000000*$G$6*'MSET pivots'!F$65 -> 1456390.5 | V19: =VLOOKUP($C19,'MSET pivots'!$B$4:$H$14,$H$2,FALSE)*1000000*$G$6*'MSET pivots'!G$65 -> 1638434.6 | W19: =VLOOKUP($C19,'MSET pivots'!$B$4:$H$14,$H$2,FALSE)*1000000*$G$6*'MSET pivots'!H$65 -> 1820478.6 | X19: =VLOOKUP($C19,'MSET pivots'!$B$4:$H$14,$H$2,FALSE)*1000000*$G$6*'MSET pivots'!I$65 -> 2002522.6 | Y19: =VLOOKUP($C19,'MSET pivots'!$B$4:$H$14,$H$2,FALSE)*1000000*$G$6*'MSET pivots'!J$65 -> 2184566.7 | Z19: =VLOOKUP($C19,'MSET pivots'!$B$4:$H$14,$H$2,FALSE)*1000000*$G$6*'MSET pivots'!K$65 -> 2366610.7 | AA19: =VLOOKUP($C19,'MSET pivots'!$B$4:$H$14,$H$2,FALSE)*1000000*$G$6*'MSET pivots'!L$65 -> 2548654.7 | ... AH19: =VLOOKUP($C19,'MSET pivots'!$B$4:$H$14,$H$2,FALSE)*1000000*$G$6*'MSET pivots'!S$65 -> 3822963
C20: SAS | E20: ALL | F20: abs-b | G20: =SUM(T20:AH20)/1000000 -> 51.096887 | S20: ='Preliminary results'!$C$31*1000000*G6 -> 902060.73 | T20: =VLOOKUP($C20,'MSET pivots'!$B$4:$H$14,$H$2,FALSE)*1000000*$G$6*'MSET pivots'!E$65 -> 1703255.1 | U20: =VLOOKUP($C20,'MSET pivots'!$B$4:$H$14,$H$2,FALSE)*1000000*$G$6*'MSET pivots'!F$65 -> 1946570 | V20: =VLOOKUP($C20,'MSET pivots'!$B$4:$H$14,$H$2,FALSE)*1000000*$G$6*'MSET pivots'!G$65 -> 2189884.8 | W20: =VLOOKUP($C20,'MSET pivots'!$B$4:$H$14,$H$2,FALSE)*1000000*$G$6*'MSET pivots'!H$65 -> 2433199.7 | X20: =VLOOKUP($C20,'MSET pivots'!$B$4:$H$14,$H$2,FALSE)*1000000*$G$6*'MSET pivots'!I$65 -> 2676514.5 | Y20: =VLOOKUP($C20,'MSET pivots'!$B$4:$H$14,$H$2,FALSE)*1000000*$G$6*'MSET pivots'!J$65 -> 2919829.4 | Z20: =VLOOKUP($C20,'MSET pivots'!$B$4:$H$14,$H$2,FALSE)*1000000*$G$6*'MSET pivots'!K$65 -> 3163144.3 | AA20: =VLOOKUP($C20,'MSET pivots'!$B$4:$H$14,$H$2,FALSE)*1000000*$G$6*'MSET pivots'!L$65 -> 3406459.1 | ... AH20: =VLOOKUP($C20,'MSET pivots'!$B$4:$H$14,$H$2,FALSE)*1000000*$G$6*'MSET pivots'!S$65 -> 5109663.1
C21: MEN | E21: ALL | F21: abs-b | G21: =SUM(T21:AH21)/1000000 -> 18.970318 | T21: =VLOOKUP($C21,'MSET pivots'!$B$4:$H$14,$H$2,FALSE)*1000000*$G$6*'MSET pivots'!E$65 -> 632353.43 | U21: =VLOOKUP($C21,'MSET pivots'!$B$4:$H$14,$H$2,FALSE)*1000000*$G$6*'MSET pivots'!F$65 -> 722686.93 | V21: =VLOOKUP($C21,'MSET pivots'!$B$4:$H$14,$H$2,FALSE)*1000000*$G$6*'MSET pivots'!G$65 -> 813020.42 | W21: =VLOOKUP($C21,'MSET pivots'!$B$4:$H$14,$H$2,FALSE)*1000000*$G$6*'MSET pivots'!H$65 -> 903353.92 | X21: =VLOOKUP($C21,'MSET pivots'!$B$4:$H$14,$H$2,FALSE)*1000000*$G$6*'MSET pivots'!I$65 -> 993687.41 | Y21: =VLOOKUP($C21,'MSET pivots'!$B$4:$H$14,$H$2,FALSE)*1000000*$G$6*'MSET pivots'!J$65 -> 1084020.9 | Z21: =VLOOKUP($C21,'MSET pivots'!$B$4:$H$14,$H$2,FALSE)*1000000*$G$6*'MSET pivots'!K$65 -> 1174354.4 | AA21: =VLOOKUP($C21,'MSET pivots'!$B$4:$H$14,$H$2,FALSE)*1000000*$G$6*'MSET pivots'!L$65 -> 1264687.9 | ... AH21: =VLOOKUP($C21,'MSET pivots'!$B$4:$H$14,$H$2,FALSE)*1000000*$G$6*'MSET pivots'!S$65 -> 1897022.4

Sheet Final demand(7)
B2: Final demand changes (consumption, govt, etc) | H2: G77+C_upper | I2: =1/3 -> 0.33333333 | J2: hh
B3: Fields with * must be specified manually or filled in automatically by selecting values in other columns | H3: 7 | I3: =1/3 -> 0.33333333 | J3: gov
B5: Country | C5: Country ISO* | F5: Product | G5: Product code* | H5: Final demand category | I5: FD code* | J5: Type* | K5: Comments
B6: Italy | C6: =_xlfn.IFNA(INDEX('[1]Country list'!$A$2:$A$166,MATCH(B6,'[1]Country list'!$B$2:$B$166,0)),"") -> ITA | F6: ALL | G6: =_xlfn.IFNA(INDEX('[1]Sector list'!$A$2:$A$122,MATCH(F6,'[1]Sector list'!$B$2:$B$122,0)),"") -> ALL | H6: Household final consumption P.3h | I6: =_xlfn.IFNA(INDEX('[1]FD list'!$A$2:$A$122,MATCH(H6,'[1]FD list'!$B$2:$B$122,0)),"") -> FD_1 | J6: rel-b | K6: << Decrease final demand (HH consumption) 3% for all products in Italy
C7: ITA | F7: Pork | G7: =_xlfn.IFNA(INDEX('[1]Sector list'!$A$2:$A$122,MATCH(F7,'[1]Sector list'!$B$2:$B$122,0)),"") -> 43 | H7: ALL | I7: =_xlfn.IFNA(INDEX('[1]FD list'!$A$2:$A$122,MATCH(H7,'[1]FD list'!$B$2:$B$122,0)),"") -> ALL | J7: rel-b | K7: << Increase final demand (across all demand categories) for pork in Italy by 12% (if zero stays zero)
B8: Germany | C8: =_xlfn.IFNA(INDEX('[1]Country list'!$A$2:$A$166,MATCH(B8,'[1]Country list'!$B$2:$B$166,0)),"") -> DEU | G8: 1-23 | I8: FD_1 | J8: abs-b | K8: << Increase demand in Germany for all agricultural sectors (1-23), only for consumer demand; try NOT to use negative values as it might create issues
B9: Malawi | C9: =_xlfn.IFNA(INDEX('[1]Country list'!$A$2:$A$166,MATCH(B9,'[1]Country list'!$B$2:$B$166,0)),"") -> MWI | F9: Building construction | G9: =_xlfn.IFNA(INDEX('[1]Sector list'!$A$2:$A$122,MATCH(F9,'[1]Sector list'!$B$2:$B$122,0)),"") -> 98 | H9: Gross fixed capital formation P.51 | I9: =_xlfn.IFNA(INDEX('[1]FD list'!$A$2:$A$122,MATCH(H9,'[1]FD list'!$B$2:$B$122,0)),"") -> FD_4 | J9: rel-b | K9: << Directly decrease investment (GFCF) demand for construction sector in Malawi with 1%; NOTE: if you want to do INVESTMENT BY the sector IT SHOULD NOT BE DONE HERE
C13: REG_exp | E13: REG_imp | G13: TRAD_COMM | I13: PROD_COMM (only FD) | J13: Current options: rel-b and abs-b
B14: Start in the next line >>
B15: Producing country | C15: Producing country ISO* | D15: Consuming country | E15: Consuming country ISO* | F15: Product | G15: Product code* | H15: Final demand category | I15: FD code* | J15: Type* | K15: Comments | L15: 2019 | M15: 2020 | N15: 2021 | O15: 2022 | P15: 2023 | Q15: 2024 | R15: 2025 | S15: 2026 | T15: 2027 | U15: 2028 | V15: 2029 | W15: 2030 | X15: 2031 | Y15: 2032 | Z15: 2033 | AA15: 2034 | AB15: 2035 | AC15: 2036 | AD15: 2037 | AE15: 2038 | AF15: 2039 | AG15: 2040 | AH15: 2041 | AI15: 2042 | AJ15: 2043 | AK15: 2044 | AL15: 2045 | AM15: 2046 | AN15: 2047 | AO15: 2048 | AP15: 2049 | AQ15: 2050
C16: SEP | E16: SEP | F16: ALL | G16: ALL | H16: Household final consumption P.3h | I16: FD_1 | J16: abs-b | K16: =SUM(X16:AL16)/1000000 -> 175.68497 | X16: =VLOOKUP($C16,'MSET pivots'!$B$4:$H$14,$H$3,FALSE)*1000000*$I$2*'MSET pivots'!E$65 -> 5856253.3 | Y16: =VLOOKUP($C16,'MSET pivots'!$B$4:$H$14,$H$3,FALSE)*1000000*$I$2*'MSET pivots'!F$65 -> 6692835.9 | Z16: =VLOOKUP($C16,'MSET pivots'!$B$4:$H$14,$H$3,FALSE)*1000000*$I$2*'MSET pivots'!G$65 -> 7529418.4 | AA16: =VLOOKUP($C16,'MSET pivots'!$B$4:$H$14,$H$3,FALSE)*1000000*$I$2*'MSET pivots'!H$65 -> 8366000.9 | AB16: =VLOOKUP($C16,'MSET pivots'!$B$4:$H$14,$H$3,FALSE)*1000000*$I$2*'MSET pivots'!I$65 -> 9202583.4 | AC16: =VLOOKUP($C16,'MSET pivots'!$B$4:$H$14,$H$3,FALSE)*1000000*$I$2*'MSET pivots'!J$65 -> 10039166 | AD16: =VLOOKUP($C16,'MSET pivots'!$B$4:$H$14,$H$3,FALSE)*1000000*$I$2*'MSET pivots'!K$65 -> 10875748 | AE16: =VLOOKUP($C16,'MSET pivots'!$B$4:$H$14,$H$3,FALSE)*1000000*$I$2*'MSET pivots'!L$65 -> 11712331 | ... AL16: =VLOOKUP($C16,'MSET pivots'!$B$4:$H$14,$H$3,FALSE)*1000000*$I$2*'MSET pivots'!S$65 -> 17568409
C17: SEP | E17: SEP | F17: ALL | G17: ALL | H17: Government final consumption P.3g | I17: FD_3 | J17: abs-b | K17: =SUM(X17:AL17)/1000000 -> 175.68497 | X17: =VLOOKUP($C17,'MSET pivots'!$B$4:$H$14,$H$3,FALSE)*1000000*$I$3*'MSET pivots'!E$65 -> 5856253.3 | Y17: =VLOOKUP($C17,'MSET pivots'!$B$4:$H$14,$H$3,FALSE)*1000000*$I$3*'MSET pivots'!F$65 -> 6692835.9 | Z17: =VLOOKUP($C17,'MSET pivots'!$B$4:$H$14,$H$3,FALSE)*1000000*$I$3*'MSET pivots'!G$65 -> 7529418.4 | AA17: =VLOOKUP($C17,'MSET pivots'!$B$4:$H$14,$H$3,FALSE)*1000000*$I$3*'MSET pivots'!H$65 -> 8366000.9 | AB17: =VLOOKUP($C17,'MSET pivots'!$B$4:$H$14,$H$3,FALSE)*1000000*$I$3*'MSET pivots'!I$65 -> 9202583.4 | AC17: =VLOOKUP($C17,'MSET pivots'!$B$4:$H$14,$H$3,FALSE)*1000000*$I$3*'MSET pivots'!J$65 -> 10039166 | AD17: =VLOOKUP($C17,'MSET pivots'!$B$4:$H$14,$H$3,FALSE)*1000000*$I$3*'MSET pivots'!K$65 -> 10875748 | AE17: =VLOOKUP($C17,'MSET pivots'!$B$4:$H$14,$H$3,FALSE)*1000000*$I$3*'MSET pivots'!L$65 -> 11712331 | ... AL17: =VLOOKUP($C17,'MSET pivots'!$B$4:$H$14,$H$3,FALSE)*1000000*$I$3*'MSET pivots'!S$65 -> 17568409
C18: AFR | E18: AFR | F18: ALL | G18: ALL | H18: Household final consumption P.3h | I18: FD_1 | J18: abs-b | K18: =SUM(X18:AL18)/1000000 -> 128.10187 | X18: =VLOOKUP($C18,'MSET pivots'!$B$4:$H$14,$H$3,FALSE)*1000000*$I$2*'MSET pivots'!E$65 -> 4270126.2 | Y18: =VLOOKUP($C18,'MSET pivots'!$B$4:$H$14,$H$3,FALSE)*1000000*$I$2*'MSET pivots'!F$65 -> 4880126 | Z18: =VLOOKUP($C18,'MSET pivots'!$B$4:$H$14,$H$3,FALSE)*1000000*$I$2*'MSET pivots'!G$65 -> 5490125.7 | AA18: =VLOOKUP($C18,'MSET pivots'!$B$4:$H$14,$H$3,FALSE)*1000000*$I$2*'MSET pivots'!H$65 -> 6100125.4 | AB18: =VLOOKUP($C18,'MSET pivots'!$B$4:$H$14,$H$3,FALSE)*1000000*$I$2*'MSET pivots'!I$65 -> 6710125.2 | AC18: =VLOOKUP($C18,'MSET pivots'!$B$4:$H$14,$H$3,FALSE)*1000000*$I$2*'MSET pivots'!J$65 -> 7320124.9 | AD18: =VLOOKUP($C18,'MSET pivots'!$B$4:$H$14,$H$3,FALSE)*1000000*$I$2*'MSET pivots'!K$65 -> 7930124.6 | AE18: =VLOOKUP($C18,'MSET pivots'!$B$4:$H$14,$H$3,FALSE)*1000000*$I$2*'MSET pivots'!L$65 -> 8540124.4 | ... AL18: =VLOOKUP($C18,'MSET pivots'!$B$4:$H$14,$H$3,FALSE)*1000000*$I$2*'MSET pivots'!S$65 -> 12810122
C19: AFR | E19: AFR | F19: ALL | G19: ALL | H19: Government final consumption P.3g | I19: FD_3 | J19: abs-b | K19: =SUM(X19:AL19)/1000000 -> 128.10187 | X19: =VLOOKUP($C19,'MSET pivots'!$B$4:$H$14,$H$3,FALSE)*1000000*$I$3*'MSET pivots'!E$65 -> 4270126.2 | Y19: =VLOOKUP($C19,'MSET pivots'!$B$4:$H$14,$H$3,FALSE)*1000000*$I$3*'MSET pivots'!F$65 -> 4880126 | Z19: =VLOOKUP($C19,'MSET pivots'!$B$4:$H$14,$H$3,FALSE)*1000000*$I$3*'MSET pivots'!G$65 -> 5490125.7 | AA19: =VLOOKUP($C19,'MSET pivots'!$B$4:$H$14,$H$3,FALSE)*1000000*$I$3*'MSET pivots'!H$65 -> 6100125.4 | AB19: =VLOOKUP($C19,'MSET pivots'!$B$4:$H$14,$H$3,FALSE)*1000000*$I$3*'MSET pivots'!I$65 -> 6710125.2 | AC19: =VLOOKUP($C19,'MSET pivots'!$B$4:$H$14,$H$3,FALSE)*1000000*$I$3*'MSET pivots'!J$65 -> 7320124.9 | AD19: =VLOOKUP($C19,'MSET pivots'!$B$4:$H$14,$H$3,FALSE)*1000000*$I$3*'MSET pivots'!K$65 -> 7930124.6 | AE19: =VLOOKUP($C19,'MSET pivots'!$B$4:$H$14,$H$3,FALSE)*1000000*$I$3*'MSET pivots'!L$65 -> 8540124.4 | ... AL19: =VLOOKUP($C19,'MSET pivots'!$B$4:$H$14,$H$3,FALSE)*1000000*$I$3*'MSET pivots'!S$65 -> 12810122
C20: EAS | E20: EAS | F20: ALL | G20: ALL | H20: Household final consumption P.3h | I20: FD_1 | J20: abs-b | K20: =SUM(X20:AL20)/1000000 -> 664.44103 | X20: =VLOOKUP($C20,'MSET pivots'!$B$4:$H$14,$H$3,FALSE)*1000000*$I$2*'MSET pivots'!E$65 -> 22148366 | Y20: =VLOOKUP($C20,'MSET pivots'!$B$4:$H$14,$H$3,FALSE)*1000000*$I$2*'MSET pivots'!F$65 -> 25312324 | Z20: =VLOOKUP($C20,'MSET pivots'!$B$4:$H$14,$H$3,FALSE)*1000000*$I$2*'MSET pivots'!G$65 -> 28476281 | AA20: =VLOOKUP($C20,'MSET pivots'!$B$4:$H$14,$H$3,FALSE)*1000000*$I$2*'MSET pivots'!H$65 -> 31640239 | AB20: =VLOOKUP($C20,'MSET pivots'!$B$4:$H$14,$H$3,FALSE)*1000000*$I$2*'MSET pivots'!I$65 -> 34804196 | AC20: =VLOOKUP($C20,'MSET pivots'!$B$4:$H$14,$H$3,FALSE)*1000000*$I$2*'MSET pivots'!J$65 -> 37968154 | AD20: =VLOOKUP($C20,'MSET pivots'!$B$4:$H$14,$H$3,FALSE)*1000000*$I$2*'MSET pivots'!K$65 -> 41132111 | AE20: =VLOOKUP($C20,'MSET pivots'!$B$4:$H$14,$H$3,FALSE)*1000000*$I$2*'MSET pivots'!L$65 -> 44296069 | ... AL20: =VLOOKUP($C20,'MSET pivots'!$B$4:$H$14,$H$3,FALSE)*1000000*$I$2*'MSET pivots'!S$65 -> 66443771
C21: EAS | E21: EAS | F21: ALL | G21: ALL | H21: Government final consumption P.3g | I21: FD_3 | J21: abs-b | K21: =SUM(X21:AL21)/1000000 -> 664.44103 | X21: =VLOOKUP($C21,'MSET pivots'!$B$4:$H$14,$H$3,FALSE)*1000000*$I$3*'MSET pivots'!E$65 -> 22148366 | Y21: =VLOOKUP($C21,'MSET pivots'!$B$4:$H$14,$H$3,FALSE)*1000000*$I$3*'MSET pivots'!F$65 -> 25312324 | Z21: =VLOOKUP($C21,'MSET pivots'!$B$4:$H$14,$H$3,FALSE)*1000000*$I$3*'MSET pivots'!G$65 -> 28476281 | AA21: =VLOOKUP($C21,'MSET pivots'!$B$4:$H$14,$H$3,FALSE)*1000000*$I$3*'MSET pivots'!H$65 -> 31640239 | AB21: =VLOOKUP($C21,'MSET pivots'!$B$4:$H$14,$H$3,FALSE)*1000000*$I$3*'MSET pivots'!I$65 -> 34804196 | AC21: =VLOOKUP($C21,'MSET pivots'!$B$4:$H$14,$H$3,FALSE)*1000000*$I$3*'MSET pivots'!J$65 -> 37968154 | AD21: =VLOOKUP($C21,'MSET pivots'!$B$4:$H$14,$H$3,FALSE)*1000000*$I$3*'MSET pivots'!K$65 -> 41132111 | AE21: =VLOOKUP($C21,'MSET pivots'!$B$4:$H$14,$H$3,FALSE)*1000000*$I$3*'MSET pivots'!L$65 -> 44296069 | ... AL21: =VLOOKUP($C21,'MSET pivots'!$B$4:$H$14,$H$3,FALSE)*1000000*$I$3*'MSET pivots'!S$65 -> 66443771
C22: LAC | E22: LAC | F22: ALL | G22: ALL | H22: Household final consumption P.3h | I22: FD_1 | J22: abs-b | K22: =SUM(X22:AL22)/1000000 -> 161.30492 | X22: =VLOOKUP($C22,'MSET pivots'!$B$4:$H$14,$H$3,FALSE)*1000000*$I$2*'MSET pivots'!E$65 -> 5376911.4 | Y22: =VLOOKUP($C22,'MSET pivots'!$B$4:$H$14,$H$3,FALSE)*1000000*$I$2*'MSET pivots'!F$65 -> 6145018.6 | Z22: =VLOOKUP($C22,'MSET pivots'!$B$4:$H$14,$H$3,FALSE)*1000000*$I$2*'MSET pivots'!G$65 -> 6913125.8 | AA22: =VLOOKUP($C22,'MSET pivots'!$B$4:$H$14,$H$3,FALSE)*1000000*$I$2*'MSET pivots'!H$65 -> 7681232.9 | AB22: =VLOOKUP($C22,'MSET pivots'!$B$4:$H$14,$H$3,FALSE)*1000000*$I$2*'MSET pivots'!I$65 -> 8449340.1 | AC22: =VLOOKUP($C22,'MSET pivots'!$B$4:$H$14,$H$3,FALSE)*1000000*$I$2*'MSET pivots'!J$65 -> 9217447.3 | AD22: =VLOOKUP($C22,'MSET pivots'!$B$4:$H$14,$H$3,FALSE)*1000000*$I$2*'MSET pivots'!K$65 -> 9985554.4 | AE22: =VLOOKUP($C22,'MSET pivots'!$B$4:$H$14,$H$3,FALSE)*1000000*$I$2*'MSET pivots'!L$65 -> 10753662 | ... AL22: =VLOOKUP($C22,'MSET pivots'!$B$4:$H$14,$H$3,FALSE)*1000000*$I$2*'MSET pivots'!S$65 -> 16130412
C23: LAC | E23: LAC | F23: ALL | G23: ALL | H23: Government final consumption P.3g | I23: FD_3 | J23: abs-b | K23: =SUM(X23:AL23)/1000000 -> 161.30492 | X23: =VLOOKUP($C23,'MSET pivots'!$B$4:$H$14,$H$3,FALSE)*1000000*$I$3*'MSET pivots'!E$65 -> 5376911.4 | Y23: =VLOOKUP($C23,'MSET pivots'!$B$4:$H$14,$H$3,FALSE)*1000000*$I$3*'MSET pivots'!F$65 -> 6145018.6 | Z23: =VLOOKUP($C23,'MSET pivots'!$B$4:$H$14,$H$3,FALSE)*1000000*$I$3*'MSET pivots'!G$65 -> 6913125.8 | AA23: =VLOOKUP($C23,'MSET pivots'!$B$4:$H$14,$H$3,FALSE)*1000000*$I$3*'MSET pivots'!H$65 -> 7681232.9 | AB23: =VLOOKUP($C23,'MSET pivots'!$B$4:$H$14,$H$3,FALSE)*1000000*$I$3*'MSET pivots'!I$65 -> 8449340.1 | AC23: =VLOOKUP($C23,'MSET pivots'!$B$4:$H$14,$H$3,FALSE)*1000000*$I$3*'MSET pivots'!J$65 -> 9217447.3 | AD23: =VLOOKUP($C23,'MSET pivots'!$B$4:$H$14,$H$3,FALSE)*1000000*$I$3*'MSET pivots'!K$65 -> 9985554.4 | AE23: =VLOOKUP($C23,'MSET pivots'!$B$4:$H$14,$H$3,FALSE)*1000000*$I$3*'MSET pivots'!L$65 -> 10753662 | ... AL23: =VLOOKUP($C23,'MSET pivots'!$B$4:$H$14,$H$3,FALSE)*1000000*$I$3*'MSET pivots'!S$65 -> 16130412
C24: MEN | E24: MEN | F24: ALL | G24: ALL | H24: Household final consumption P.3h | I24: FD_1 | J24: abs-b | K24: =SUM(X24:AL24)/1000000 -> 80.042377 | X24: =VLOOKUP($C24,'MSET pivots'!$B$4:$H$14,$H$3,FALSE)*1000000*$I$2*'MSET pivots'!E$65 -> 2668119.3 | Y24: =VLOOKUP($C24,'MSET pivots'!$B$4:$H$14,$H$3,FALSE)*1000000*$I$2*'MSET pivots'!F$65 -> 3049267.7 | Z24: =VLOOKUP($C24,'MSET pivots'!$B$4:$H$14,$H$3,FALSE)*1000000*$I$2*'MSET pivots'!G$65 -> 3430416.2 | AA24: =VLOOKUP($C24,'MSET pivots'!$B$4:$H$14,$H$3,FALSE)*1000000*$I$2*'MSET pivots'!H$65 -> 3811564.6 | AB24: =VLOOKUP($C24,'MSET pivots'!$B$4:$H$14,$H$3,FALSE)*1000000*$I$2*'MSET pivots'!I$65 -> 4192713.1 | AC24: =VLOOKUP($C24,'MSET pivots'!$B$4:$H$14,$H$3,FALSE)*1000000*$I$2*'MSET pivots'!J$65 -> 4573861.6 | AD24: =VLOOKUP($C24,'MSET pivots'!$B$4:$H$14,$H$3,FALSE)*1000000*$I$2*'MSET pivots'!K$65 -> 4955010 | AE24: =VLOOKUP($C24,'MSET pivots'!$B$4:$H$14,$H$3,FALSE)*1000000*$I$2*'MSET pivots'!L$65 -> 5336158.5 | ... AL24: =VLOOKUP($C24,'MSET pivots'!$B$4:$H$14,$H$3,FALSE)*1000000*$I$2*'MSET pivots'!S$65 -> 8004197.7
C25: MEN | E25: MEN | F25: ALL | G25: ALL | H25: Government final consumption P.3g | I25: FD_3 | J25: abs-b | K25: =SUM(X25:AL25)/1000000 -> 80.042377 | X25: =VLOOKUP($C25,'MSET pivots'!$B$4:$H$14,$H$3,FALSE)*1000000*$I$3*'MSET pivots'!E$65 -> 2668119.3 | Y25: =VLOOKUP($C25,'MSET pivots'!$B$4:$H$14,$H$3,FALSE)*1000000*$I$3*'MSET pivots'!F$65 -> 3049267.7 | Z25: =VLOOKUP($C25,'MSET pivots'!$B$4:$H$14,$H$3,FALSE)*1000000*$I$3*'MSET pivots'!G$65 -> 3430416.2 | AA25: =VLOOKUP($C25,'MSET pivots'!$B$4:$H$14,$H$3,FALSE)*1000000*$I$3*'MSET pivots'!H$65 -> 3811564.6 | AB25: =VLOOKUP($C25,'MSET pivots'!$B$4:$H$14,$H$3,FALSE)*1000000*$I$3*'MSET pivots'!I$65 -> 4192713.1 | AC25: =VLOOKUP($C25,'MSET pivots'!$B$4:$H$14,$H$3,FALSE)*1000000*$I$3*'MSET pivots'!J$65 -> 4573861.6 | AD25: =VLOOKUP($C25,'MSET pivots'!$B$4:$H$14,$H$3,FALSE)*1000000*$I$3*'MSET pivots'!K$65 -> 4955010 | AE25: =VLOOKUP($C25,'MSET pivots'!$B$4:$H$14,$H$3,FALSE)*1000000*$I$3*'MSET pivots'!L$65 -> 5336158.5 | ... AL25: =VLOOKUP($C25,'MSET pivots'!$B$4:$H$14,$H$3,FALSE)*1000000*$I$3*'MSET pivots'!S$65 -> 8004197.7
B26: Pakistan | C26: SAS | E26: SAS | F26: ALL | G26: ALL | H26: Household final consumption P.3h | I26: FD_1 | J26: abs-b | K26: =SUM(X26:AL26)/1000000 -> 215.59555 | W26: ='Preliminary results'!$C$31*1000000*I2 -> 902060.73 | X26: =VLOOKUP($C26,'MSET pivots'!$B$4:$H$14,$H$3,FALSE)*1000000*$I$2*'MSET pivots'!E$65 -> 7186626.2 | Y26: =VLOOKUP($C26,'MSET pivots'!$B$4:$H$14,$H$3,FALSE)*1000000*$I$2*'MSET pivots'!F$65 -> 8213256.3 | Z26: =VLOOKUP($C26,'MSET pivots'!$B$4:$H$14,$H$3,FALSE)*1000000*$I$2*'MSET pivots'!G$65 -> 9239886.4 | AA26: =VLOOKUP($C26,'MSET pivots'!$B$4:$H$14,$H$3,FALSE)*1000000*$I$2*'MSET pivots'!H$65 -> 10266517 | AB26: =VLOOKUP($C26,'MSET pivots'!$B$4:$H$14,$H$3,FALSE)*1000000*$I$2*'MSET pivots'!I$65 -> 11293147 | AC26: =VLOOKUP($C26,'MSET pivots'!$B$4:$H$14,$H$3,FALSE)*1000000*$I$2*'MSET pivots'!J$65 -> 12319777 | AD26: =VLOOKUP($C26,'MSET pivots'!$B$4:$H$14,$H$3,FALSE)*1000000*$I$2*'MSET pivots'!K$65 -> 13346407 | AE26: =VLOOKUP($C26,'MSET pivots'!$B$4:$H$14,$H$3,FALSE)*1000000*$I$2*'MSET pivots'!L$65 -> 14373037 | ... AL26: =VLOOKUP($C26,'MSET pivots'!$B$4:$H$14,$H$3,FALSE)*1000000*$I$2*'MSET pivots'!S$65 -> 21559448
B27: Pakistan | C27: SAS | E27: SAS | F27: ALL | G27: ALL | H27: Government final consumption P.3g | I27: FD_3 | J27: abs-b | K27: =SUM(X27:AL27)/1000000 -> 215.59555 | W27: ='Preliminary results'!$C$31*1000000*I3 -> 902060.73 | X27: =VLOOKUP($C27,'MSET pivots'!$B$4:$H$14,$H$3,FALSE)*1000000*$I$3*'MSET pivots'!E$65 -> 7186626.2 | Y27: =VLOOKUP($C27,'MSET pivots'!$B$4:$H$14,$H$3,FALSE)*1000000*$I$3*'MSET pivots'!F$65 -> 8213256.3 | Z27: =VLOOKUP($C27,'MSET pivots'!$B$4:$H$14,$H$3,FALSE)*1000000*$I$3*'MSET pivots'!G$65 -> 9239886.4 | AA27: =VLOOKUP($C27,'MSET pivots'!$B$4:$H$14,$H$3,FALSE)*1000000*$I$3*'MSET pivots'!H$65 -> 10266517 | AB27: =VLOOKUP($C27,'MSET pivots'!$B$4:$H$14,$H$3,FALSE)*1000000*$I$3*'MSET pivots'!I$65 -> 11293147 | AC27: =VLOOKUP($C27,'MSET pivots'!$B$4:$H$14,$H$3,FALSE)*1000000*$I$3*'MSET pivots'!J$65 -> 12319777 | AD27: =VLOOKUP($C27,'MSET pivots'!$B$4:$H$14,$H$3,FALSE)*1000000*$I$3*'MSET pivots'!K$65 -> 13346407 | AE27: =VLOOKUP($C27,'MSET pivots'!$B$4:$H$14,$H$3,FALSE)*1000000*$I$3*'MSET pivots'!L$65 -> 14373037 | ... AL27: =VLOOKUP($C27,'MSET pivots'!$B$4:$H$14,$H$3,FALSE)*1000000*$I$3*'MSET pivots'!S$65 -> 21559448
C28: AJN | E28: AJN | F28: ALL | G28: ALL | H28: Government final consumption P.3g | I28: FD_3 | J28: rel-b | K28: =SUM(X28:AL28) -> -0.33778872 | X28: =VLOOKUP($C28,'MSET pivots'!$J$4:$P$14,'Final demand(7)'!$H$3,FALSE)*'MSET pivots'!E$65 -> -0.011259793 | Y28: =VLOOKUP($C28,'MSET pivots'!$J$4:$P$14,'Final demand(7)'!$H$3,FALSE)*'MSET pivots'!F$65 -> -0.012868287 | Z28: =VLOOKUP($C28,'MSET pivots'!$J$4:$P$14,'Final demand(7)'!$H$3,FALSE)*'MSET pivots'!G$65 -> -0.01447678 | AA28: =VLOOKUP($C28,'MSET pivots'!$J$4:$P$14,'Final demand(7)'!$H$3,FALSE)*'MSET pivots'!H$65 -> -0.016085274 | AB28: =VLOOKUP($C28,'MSET pivots'!$J$4:$P$14,'Final demand(7)'!$H$3,FALSE)*'MSET pivots'!I$65 -> -0.017693767 | AC28: =VLOOKUP($C28,'MSET pivots'!$J$4:$P$14,'Final demand(7)'!$H$3,FALSE)*'MSET pivots'!J$65 -> -0.019302261 | AD28: =VLOOKUP($C28,'MSET pivots'!$J$4:$P$14,'Final demand(7)'!$H$3,FALSE)*'MSET pivots'!K$65 -> -0.020910755 | AE28: =VLOOKUP($C28,'MSET pivots'!$J$4:$P$14,'Final demand(7)'!$H$3,FALSE)*'MSET pivots'!L$65 -> -0.022519248 | ... AL28: =VLOOKUP($C28,'MSET pivots'!$J$4:$P$14,'Final demand(7)'!$H$3,FALSE)*'MSET pivots'!S$65 -> -0.033778703
C29: EEA | E29: EEA | F29: ALL | G29: ALL | H29: Government final consumption P.3g | I29: FD_3 | J29: rel-b | K29: =SUM(X29:AL29) -> -0.3820483 | X29: =VLOOKUP($C29,'MSET pivots'!$J$4:$P$14,'Final demand(7)'!$H$3,FALSE)*'MSET pivots'!E$65 -> -0.012735134 | Y29: =VLOOKUP($C29,'MSET pivots'!$J$4:$P$14,'Final demand(7)'!$H$3,FALSE)*'MSET pivots'!F$65 -> -0.014554385 | Z29: =VLOOKUP($C29,'MSET pivots'!$J$4:$P$14,'Final demand(7)'!$H$3,FALSE)*'MSET pivots'!G$65 -> -0.016373635 | AA29: =VLOOKUP($C29,'MSET pivots'!$J$4:$P$14,'Final demand(7)'!$H$3,FALSE)*'MSET pivots'!H$65 -> -0.018192885 | AB29: =VLOOKUP($C29,'MSET pivots'!$J$4:$P$14,'Final demand(7)'!$H$3,FALSE)*'MSET pivots'!I$65 -> -0.020012136 | AC29: =VLOOKUP($C29,'MSET pivots'!$J$4:$P$14,'Final demand(7)'!$H$3,FALSE)*'MSET pivots'!J$65 -> -0.021831386 | AD29: =VLOOKUP($C29,'MSET pivots'!$J$4:$P$14,'Final demand(7)'!$H$3,FALSE)*'MSET pivots'!K$65 -> -0.023650636 | AE29: =VLOOKUP($C29,'MSET pivots'!$J$4:$P$14,'Final demand(7)'!$H$3,FALSE)*'MSET pivots'!L$65 -> -0.025469887 | ... AL29: =VLOOKUP($C29,'MSET pivots'!$J$4:$P$14,'Final demand(7)'!$H$3,FALSE)*'MSET pivots'!S$65 -> -0.038204639
B30: United Kingdom | C30: EUR | E30: EUR | F30: ALL | G30: ALL | H30: Government final consumption P.3g | I30: FD_3 | J30: rel-b | K30: =SUM(X30:AL30) -> -0.27015688 | W30: =('Preliminary results'!$C$31)/'Baseline govt spend'!$E$51 -> 0.00066729533 | X30: =VLOOKUP($C30,'MSET pivots'!$J$4:$P$14,'Final demand(7)'!$H$3,FALSE)*'MSET pivots'!E$65 -> -0.0090053643 | Y30: =VLOOKUP($C30,'MSET pivots'!$J$4:$P$14,'Final demand(7)'!$H$3,FALSE)*'MSET pivots'!F$65 -> -0.010291806 | Z30: =VLOOKUP($C30,'MSET pivots'!$J$4:$P$14,'Final demand(7)'!$H$3,FALSE)*'MSET pivots'!G$65 -> -0.011578248 | AA30: =VLOOKUP($C30,'MSET pivots'!$J$4:$P$14,'Final demand(7)'!$H$3,FALSE)*'MSET pivots'!H$65 -> -0.01286469 | AB30: =VLOOKUP($C30,'MSET pivots'!$J$4:$P$14,'Final demand(7)'!$H$3,FALSE)*'MSET pivots'!I$65 -> -0.014151132 | AC30: =VLOOKUP($C30,'MSET pivots'!$J$4:$P$14,'Final demand(7)'!$H$3,FALSE)*'MSET pivots'!J$65 -> -0.015437574 | AD30: =VLOOKUP($C30,'MSET pivots'!$J$4:$P$14,'Final demand(7)'!$H$3,FALSE)*'MSET pivots'!K$65 -> -0.016724016 | AE30: =VLOOKUP($C30,'MSET pivots'!$J$4:$P$14,'Final demand(7)'!$H$3,FALSE)*'MSET pivots'!L$65 -> -0.018010458 | ... AL30: =VLOOKUP($C30,'MSET pivots'!$J$4:$P$14,'Final demand(7)'!$H$3,FALSE)*'MSET pivots'!S$65 -> -0.027015552
C31: NAM | E31: NAM | F31: ALL | G31: ALL | H31: Government final consumption P.3g | I31: FD_3 | J31: rel-b | K31: =SUM(X31:AL31) -> -0.73052569 | X31: =VLOOKUP($C31,'MSET pivots'!$J$4:$P$14,'Final demand(7)'!$H$3,FALSE)*'MSET pivots'!E$65 -> -0.024351222 | Y31: =VLOOKUP($C31,'MSET pivots'!$J$4:$P$14,'Final demand(7)'!$H$3,FALSE)*'MSET pivots'!F$65 -> -0.027829863 | Z31: =VLOOKUP($C31,'MSET pivots'!$J$4:$P$14,'Final demand(7)'!$H$3,FALSE)*'MSET pivots'!G$65 -> -0.031308505 | AA31: =VLOOKUP($C31,'MSET pivots'!$J$4:$P$14,'Final demand(7)'!$H$3,FALSE)*'MSET pivots'!H$65 -> -0.034787146 | AB31: =VLOOKUP($C31,'MSET pivots'!$J$4:$P$14,'Final demand(7)'!$H$3,FALSE)*'MSET pivots'!I$65 -> -0.038265788 | AC31: =VLOOKUP($C31,'MSET pivots'!$J$4:$P$14,'Final demand(7)'!$H$3,FALSE)*'MSET pivots'!J$65 -> -0.04174443 | AD31: =VLOOKUP($C31,'MSET pivots'!$J$4:$P$14,'Final demand(7)'!$H$3,FALSE)*'MSET pivots'!K$65 -> -0.045223071 | AE31: =VLOOKUP($C31,'MSET pivots'!$J$4:$P$14,'Final demand(7)'!$H$3,FALSE)*'MSET pivots'!L$65 -> -0.048701713 | ... AL31: =VLOOKUP($C31,'MSET pivots'!$J$4:$P$14,'Final demand(7)'!$H$3,FALSE)*'MSET pivots'!S$65 -> -0.073052204
G44: =_xlfn.IFNA(INDEX('[1]Sector list'!$A$2:$A$122,MATCH(F44,'[1]Sector list'!$B$2:$B$122,0)),"") | I44: =_xlfn.IFNA(INDEX('[1]FD list'!$A$2:$A$122,MATCH(H44,'[1]FD list'!$B$2:$B$122,0)),"")
G45: =_xlfn.IFNA(INDEX('[1]Sector list'!$A$2:$A$122,MATCH(F45,'[1]Sector list'!$B$2:$B$122,0)),"") | I45: =_xlfn.IFNA(INDEX('[1]FD list'!$A$2:$A$122,MATCH(H45,'[1]FD list'!$B$2:$B$122,0)),"")
G46: =_xlfn.IFNA(INDEX('[1]Sector list'!$A$2:$A$122,MATCH(F46,'[1]Sector list'!$B$2:$B$122,0)),"") | I46: =_xlfn.IFNA(INDEX('[1]FD list'!$A$2:$A$122,MATCH(H46,'[1]FD list'!$B$2:$B$122,0)),"")
G47: =_xlfn.IFNA(INDEX('[1]Sector list'!$A$2:$A$122,MATCH(F47,'[1]Sector list'!$B$2:$B$122,0)),"") | I47: =_xlfn.IFNA(INDEX('[1]FD list'!$A$2:$A$122,MATCH(H47,'[1]FD list'!$B$2:$B$122,0)),"")
G48: =_xlfn.IFNA(INDEX('[1]Sector list'!$A$2:$A$122,MATCH(F48,'[1]Sector list'!$B$2:$B$122,0)),"") | I48: =_xlfn.IFNA(INDEX('[1]FD list'!$A$2:$A$122,MATCH(H48,'[1]FD list'!$B$2:$B$122,0)),"")
G49: =_xlfn.IFNA(INDEX('[1]Sector list'!$A$2:$A$122,MATCH(F49,'[1]Sector list'!$B$2:$B$122,0)),"") | I49: =_xlfn.IFNA(INDEX('[1]FD list'!$A$2:$A$122,MATCH(H49,'[1]FD list'!$B$2:$B$122,0)),"")
G50: =_xlfn.IFNA(INDEX('[1]Sector list'!$A$2:$A$122,MATCH(F50,'[1]Sector list'!$B$2:$B$122,0)),"") | I50: =_xlfn.IFNA(INDEX('[1]FD list'!$A$2:$A$122,MATCH(H50,'[1]FD list'!$B$2:$B$122,0)),"")
G51: =_xlfn.IFNA(INDEX('[1]Sector list'!$A$2:$A$122,MATCH(F51,'[1]Sector list'!$B$2:$B$122,0)),"") | I51: =_xlfn.IFNA(INDEX('[1]FD list'!$A$2:$A$122,MATCH(H51,'[1]FD list'!$B$2:$B$122,0)),"")
G52: =_xlfn.IFNA(INDEX('[1]Sector list'!$A$2:$A$122,MATCH(F52,'[1]Sector list'!$B$2:$B$122,0)),"") | I52: =_xlfn.IFNA(INDEX('[1]FD list'!$A$2:$A$122,MATCH(H52,'[1]FD list'!$B$2:$B$122,0)),"")
G53: =_xlfn.IFNA(INDEX('[1]Sector list'!$A$2:$A$122,MATCH(F53,'[1]Sector list'!$B$2:$B$122,0)),"") | I53: =_xlfn.IFNA(INDEX('[1]FD list'!$A$2:$A$122,MATCH(H53,'[1]FD list'!$B$2:$B$122,0)),"")
G54: =_xlfn.IFNA(INDEX('[1]Sector list'!$A$2:$A$122,MATCH(F54,'[1]Sector list'!$B$2:$B$122,0)),"") | I54: =_xlfn.IFNA(INDEX('[1]FD list'!$A$2:$A$122,MATCH(H54,'[1]FD list'!$B$2:$B$122,0)),"")
G55: =_xlfn.IFNA(INDEX('[1]Sector list'!$A$2:$A$122,MATCH(F55,'[1]Sector list'!$B$2:$B$122,0)),"") | I55: =_xlfn.IFNA(INDEX('[1]FD list'!$A$2:$A$122,MATCH(H55,'[1]FD list'!$B$2:$B$122,0)),"")
... G69: =_xlfn.IFNA(INDEX('[1]Sector list'!$A$2:$A$122,MATCH(F69,'[1]Sector list'!$B$2:$B$122,0)),"") | I69: =_xlfn.IFNA(INDEX('[1]FD list'!$A$2:$A$122,MATCH(H69,'[1]FD list'!$B$2:$B$122,0)),"")
I70: =_xlfn.IFNA(INDEX('[1]FD list'!$A$2:$A$122,MATCH(H70,'[1]FD list'!$B$2:$B$122,0)),"")
I71: =_xlfn.IFNA(INDEX('[1]FD list'!$A$2:$A$122,MATCH(H71,'[1]FD list'!$B$2:$B$122,0)),"")
I72: =_xlfn.IFNA(INDEX('[1]FD list'!$A$2:$A$122,MATCH(H72,'[1]FD list'!$B$2:$B$122,0)),"")
I73: =_xlfn.IFNA(INDEX('[1]FD list'!$A$2:$A$122,MATCH(H73,'[1]FD list'!$B$2:$B$122,0)),"")
I74: =_xlfn.IFNA(INDEX('[1]FD list'!$A$2:$A$122,MATCH(H74,'[1]FD list'!$B$2:$B$122,0)),"")
I75: =_xlfn.IFNA(INDEX('[1]FD list'!$A$2:$A$122,MATCH(H75,'[1]FD list'!$B$2:$B$122,0)),"")
I76: =_xlfn.IFNA(INDEX('[1]FD list'!$A$2:$A$122,MATCH(H76,'[1]FD list'!$B$2:$B$122,0)),"")
I77: =_xlfn.IFNA(INDEX('[1]FD list'!$A$2:$A$122,MATCH(H77,'[1]FD list'!$B$2:$B$122,0)),"")
I78: =_xlfn.IFNA(INDEX('[1]FD list'!$A$2:$A$122,MATCH(H78,'[1]FD list'!$B$2:$B$122,0)),"")
I79: =_xlfn.IFNA(INDEX('[1]FD list'!$A$2:$A$122,MATCH(H79,'[1]FD list'!$B$2:$B$122,0)),"")
I80: =_xlfn.IFNA(INDEX('[1]FD list'!$A$2:$A$122,MATCH(H80,'[1]FD list'!$B$2:$B$122,0)),"")
I81: =_xlfn.IFNA(INDEX('[1]FD list'!$A$2:$A$122,MATCH(H81,'[1]FD list'!$B$2:$B$122,0)),"")
... I97: =_xlfn.IFNA(INDEX('[1]FD list'!$A$2:$A$122,MATCH(H97,'[1]FD list'!$B$2:$B$122,0)),"")
I98: =_xlfn.IFNA(INDEX('[1]Sector list'!$A$2:$A$122,MATCH(H98,'[1]Sector list'!$B$2:$B$122,0)),"")
I99: =_xlfn.IFNA(INDEX('[1]Sector list'!$A$2:$A$122,MATCH(H99,'[1]Sector list'!$B$2:$B$122,0)),"")
I100: =_xlfn.IFNA(INDEX('[1]Sector list'!$A$2:$A$122,MATCH(H100,'[1]Sector list'!$B$2:$B$122,0)),"")
I101: =_xlfn.IFNA(INDEX('[1]Sector list'!$A$2:$A$122,MATCH(H101,'[1]Sector list'!$B$2:$B$122,0)),"")
I102: =_xlfn.IFNA(INDEX('[1]Sector list'!$A$2:$A$122,MATCH(H102,'[1]Sector list'!$B$2:$B$122,0)),"")
I103: =_xlfn.IFNA(INDEX('[1]Sector list'!$A$2:$A$122,MATCH(H103,'[1]Sector list'!$B$2:$B$122,0)),"")
I104: =_xlfn.IFNA(INDEX('[1]Sector list'!$A$2:$A$122,MATCH(H104,'[1]Sector list'!$B$2:$B$122,0)),"")
I105: =_xlfn.IFNA(INDEX('[1]Sector list'!$A$2:$A$122,MATCH(H105,'[1]Sector list'!$B$2:$B$122,0)),"")
I106: =_xlfn.IFNA(INDEX('[1]Sector list'!$A$2:$A$122,MATCH(H106,'[1]Sector list'!$B$2:$B$122,0)),"")
I107: =_xlfn.IFNA(INDEX('[1]Sector list'!$A$2:$A$122,MATCH(H107,'[1]Sector list'!$B$2:$B$122,0)),"")
I108: =_xlfn.IFNA(INDEX('[1]Sector list'!$A$2:$A$122,MATCH(H108,'[1]Sector list'!$B$2:$B$122,0)),"")
I109: =_xlfn.IFNA(INDEX('[1]Sector list'!$A$2:$A$122,MATCH(H109,'[1]Sector list'!$B$2:$B$122,0)),"")
... I905: =_xlfn.IFNA(INDEX('[1]Sector list'!$A$2:$A$122,MATCH(H905,'[1]Sector list'!$B$2:$B$122,0)),"")

Sheet Investment by(7)
B2: Investment BY sector changes | G2: ='Final demand(7)'!H2 -> G77+C_upper | H2: ='Final demand(7)'!H3 -> 7
B3: Fields with * must be specified manually or filled in automatically by selecting values in other columns
B5: Country | C5: Country ISO* | D5: Sector investing | E5: Sector investing code* | F5: Type* | G5: Comments
G6: =1/3 -> 0.33333333 | H6: FCF
B8: Germany | C8: =_xlfn.IFNA(INDEX('[2]Country list'!$A$2:$A$166,MATCH(B8,'[2]Country list'!$B$2:$B$166,0)),"") -> DEU | E8: 1-23 | F8: abs | G8: << Increase investment in agricultural sectors in Germany, 1000 kUSD in EVERY sector
G12: relative investment is not possible, because we don’t have an investment baseline right now
C13: REG_imp | E13: PROD_COMM | G13: Current options: abs-b
B14: Start in the next line >>
B15: Country | C15: Country ISO* | D15: Sector investing | E15: Sector investing code* | F15: Type* | G15: Comments | H15: 2019 | I15: 2020 | J15: 2021 | K15: 2022 | L15: 2023 | M15: 2024 | N15: 2025 | O15: 2026 | P15: 2027 | Q15: 2028 | R15: 2029 | S15: 2030 | T15: 2031 | U15: 2032 | V15: 2033 | W15: 2034 | X15: 2035 | Y15: 2036 | Z15: 2037 | AA15: 2038 | AB15: 2039 | AC15: 2040 | AD15: 2041 | AE15: 2042 | AF15: 2043 | AG15: 2044 | AH15: 2045 | AI15: 2046 | AJ15: 2047 | AK15: 2048 | AL15: 2049 | AM15: 2050
C16: SEP | E16: ALL | F16: abs-b | G16: =SUM(T16:AH16)/1000000 -> 175.68497 | T16: =VLOOKUP($C16,'MSET pivots'!$B$4:$H$14,$H$2,FALSE)*1000000*$G$6*'MSET pivots'!E$65 -> 5856253.3 | U16: =VLOOKUP($C16,'MSET pivots'!$B$4:$H$14,$H$2,FALSE)*1000000*$G$6*'MSET pivots'!F$65 -> 6692835.9 | V16: =VLOOKUP($C16,'MSET pivots'!$B$4:$H$14,$H$2,FALSE)*1000000*$G$6*'MSET pivots'!G$65 -> 7529418.4 | W16: =VLOOKUP($C16,'MSET pivots'!$B$4:$H$14,$H$2,FALSE)*1000000*$G$6*'MSET pivots'!H$65 -> 8366000.9 | X16: =VLOOKUP($C16,'MSET pivots'!$B$4:$H$14,$H$2,FALSE)*1000000*$G$6*'MSET pivots'!I$65 -> 9202583.4 | Y16: =VLOOKUP($C16,'MSET pivots'!$B$4:$H$14,$H$2,FALSE)*1000000*$G$6*'MSET pivots'!J$65 -> 10039166 | Z16: =VLOOKUP($C16,'MSET pivots'!$B$4:$H$14,$H$2,FALSE)*1000000*$G$6*'MSET pivots'!K$65 -> 10875748 | AA16: =VLOOKUP($C16,'MSET pivots'!$B$4:$H$14,$H$2,FALSE)*1000000*$G$6*'MSET pivots'!L$65 -> 11712331 | ... AH16: =VLOOKUP($C16,'MSET pivots'!$B$4:$H$14,$H$2,FALSE)*1000000*$G$6*'MSET pivots'!S$65 -> 17568409
C17: AFR | E17: ALL | F17: abs-b | G17: =SUM(T17:AH17)/1000000 -> 128.10187 | T17: =VLOOKUP($C17,'MSET pivots'!$B$4:$H$14,$H$2,FALSE)*1000000*$G$6*'MSET pivots'!E$65 -> 4270126.2 | U17: =VLOOKUP($C17,'MSET pivots'!$B$4:$H$14,$H$2,FALSE)*1000000*$G$6*'MSET pivots'!F$65 -> 4880126 | V17: =VLOOKUP($C17,'MSET pivots'!$B$4:$H$14,$H$2,FALSE)*1000000*$G$6*'MSET pivots'!G$65 -> 5490125.7 | W17: =VLOOKUP($C17,'MSET pivots'!$B$4:$H$14,$H$2,FALSE)*1000000*$G$6*'MSET pivots'!H$65 -> 6100125.4 | X17: =VLOOKUP($C17,'MSET pivots'!$B$4:$H$14,$H$2,FALSE)*1000000*$G$6*'MSET pivots'!I$65 -> 6710125.2 | Y17: =VLOOKUP($C17,'MSET pivots'!$B$4:$H$14,$H$2,FALSE)*1000000*$G$6*'MSET pivots'!J$65 -> 7320124.9 | Z17: =VLOOKUP($C17,'MSET pivots'!$B$4:$H$14,$H$2,FALSE)*1000000*$G$6*'MSET pivots'!K$65 -> 7930124.6 | AA17: =VLOOKUP($C17,'MSET pivots'!$B$4:$H$14,$H$2,FALSE)*1000000*$G$6*'MSET pivots'!L$65 -> 8540124.4 | ... AH17: =VLOOKUP($C17,'MSET pivots'!$B$4:$H$14,$H$2,FALSE)*1000000*$G$6*'MSET pivots'!S$65 -> 12810122
C18: EAS | E18: ALL | F18: abs-b | G18: =SUM(T18:AH18)/1000000 -> 664.44103 | T18: =VLOOKUP($C18,'MSET pivots'!$B$4:$H$14,$H$2,FALSE)*1000000*$G$6*'MSET pivots'!E$65 -> 22148366 | U18: =VLOOKUP($C18,'MSET pivots'!$B$4:$H$14,$H$2,FALSE)*1000000*$G$6*'MSET pivots'!F$65 -> 25312324 | V18: =VLOOKUP($C18,'MSET pivots'!$B$4:$H$14,$H$2,FALSE)*1000000*$G$6*'MSET pivots'!G$65 -> 28476281 | W18: =VLOOKUP($C18,'MSET pivots'!$B$4:$H$14,$H$2,FALSE)*1000000*$G$6*'MSET pivots'!H$65 -> 31640239 | X18: =VLOOKUP($C18,'MSET pivots'!$B$4:$H$14,$H$2,FALSE)*1000000*$G$6*'MSET pivots'!I$65 -> 34804196 | Y18: =VLOOKUP($C18,'MSET pivots'!$B$4:$H$14,$H$2,FALSE)*1000000*$G$6*'MSET pivots'!J$65 -> 37968154 | Z18: =VLOOKUP($C18,'MSET pivots'!$B$4:$H$14,$H$2,FALSE)*1000000*$G$6*'MSET pivots'!K$65 -> 41132111 | AA18: =VLOOKUP($C18,'MSET pivots'!$B$4:$H$14,$H$2,FALSE)*1000000*$G$6*'MSET pivots'!L$65 -> 44296069 | ... AH18: =VLOOKUP($C18,'MSET pivots'!$B$4:$H$14,$H$2,FALSE)*1000000*$G$6*'MSET pivots'!S$65 -> 66443771
C19: LAC | E19: ALL | F19: abs-b | G19: =SUM(T19:AH19)/1000000 -> 161.30492 | T19: =VLOOKUP($C19,'MSET pivots'!$B$4:$H$14,$H$2,FALSE)*1000000*$G$6*'MSET pivots'!E$65 -> 5376911.4 | U19: =VLOOKUP($C19,'MSET pivots'!$B$4:$H$14,$H$2,FALSE)*1000000*$G$6*'MSET pivots'!F$65 -> 6145018.6 | V19: =VLOOKUP($C19,'MSET pivots'!$B$4:$H$14,$H$2,FALSE)*1000000*$G$6*'MSET pivots'!G$65 -> 6913125.8 | W19: =VLOOKUP($C19,'MSET pivots'!$B$4:$H$14,$H$2,FALSE)*1000000*$G$6*'MSET pivots'!H$65 -> 7681232.9 | X19: =VLOOKUP($C19,'MSET pivots'!$B$4:$H$14,$H$2,FALSE)*1000000*$G$6*'MSET pivots'!I$65 -> 8449340.1 | Y19: =VLOOKUP($C19,'MSET pivots'!$B$4:$H$14,$H$2,FALSE)*1000000*$G$6*'MSET pivots'!J$65 -> 9217447.3 | Z19: =VLOOKUP($C19,'MSET pivots'!$B$4:$H$14,$H$2,FALSE)*1000000*$G$6*'MSET pivots'!K$65 -> 9985554.4 | AA19: =VLOOKUP($C19,'MSET pivots'!$B$4:$H$14,$H$2,FALSE)*1000000*$G$6*'MSET pivots'!L$65 -> 10753662 | ... AH19: =VLOOKUP($C19,'MSET pivots'!$B$4:$H$14,$H$2,FALSE)*1000000*$G$6*'MSET pivots'!S$65 -> 16130412
C20: SAS | E20: ALL | F20: abs-b | G20: =SUM(T20:AH20)/1000000 -> 215.59555 | S20: ='Preliminary results'!$C$31*1000000*G6 -> 902060.73 | T20: =VLOOKUP($C20,'MSET pivots'!$B$4:$H$14,$H$2,FALSE)*1000000*$G$6*'MSET pivots'!E$65 -> 7186626.2 | U20: =VLOOKUP($C20,'MSET pivots'!$B$4:$H$14,$H$2,FALSE)*1000000*$G$6*'MSET pivots'!F$65 -> 8213256.3 | V20: =VLOOKUP($C20,'MSET pivots'!$B$4:$H$14,$H$2,FALSE)*1000000*$G$6*'MSET pivots'!G$65 -> 9239886.4 | W20: =VLOOKUP($C20,'MSET pivots'!$B$4:$H$14,$H$2,FALSE)*1000000*$G$6*'MSET pivots'!H$65 -> 10266517 | X20: =VLOOKUP($C20,'MSET pivots'!$B$4:$H$14,$H$2,FALSE)*1000000*$G$6*'MSET pivots'!I$65 -> 11293147 | Y20: =VLOOKUP($C20,'MSET pivots'!$B$4:$H$14,$H$2,FALSE)*1000000*$G$6*'MSET pivots'!J$65 -> 12319777 | Z20: =VLOOKUP($C20,'MSET pivots'!$B$4:$H$14,$H$2,FALSE)*1000000*$G$6*'MSET pivots'!K$65 -> 13346407 | AA20: =VLOOKUP($C20,'MSET pivots'!$B$4:$H$14,$H$2,FALSE)*1000000*$G$6*'MSET pivots'!L$65 -> 14373037 | ... AH20: =VLOOKUP($C20,'MSET pivots'!$B$4:$H$14,$H$2,FALSE)*1000000*$G$6*'MSET pivots'!S$65 -> 21559448
C21: MEN | E21: ALL | F21: abs-b | G21: =SUM(T21:AH21)/1000000 -> 80.042377 | T21: =VLOOKUP($C21,'MSET pivots'!$B$4:$H$14,$H$2,FALSE)*1000000*$G$6*'MSET pivots'!E$65 -> 2668119.3 | U21: =VLOOKUP($C21,'MSET pivots'!$B$4:$H$14,$H$2,FALSE)*1000000*$G$6*'MSET pivots'!F$65 -> 3049267.7 | V21: =VLOOKUP($C21,'MSET pivots'!$B$4:$H$14,$H$2,FALSE)*1000000*$G$6*'MSET pivots'!G$65 -> 3430416.2 | W21: =VLOOKUP($C21,'MSET pivots'!$B$4:$H$14,$H$2,FALSE)*1000000*$G$6*'MSET pivots'!H$65 -> 3811564.6 | X21: =VLOOKUP($C21,'MSET pivots'!$B$4:$H$14,$H$2,FALSE)*1000000*$G$6*'MSET pivots'!I$65 -> 4192713.1 | Y21: =VLOOKUP($C21,'MSET pivots'!$B$4:$H$14,$H$2,FALSE)*1000000*$G$6*'MSET pivots'!J$65 -> 4573861.6 | Z21: =VLOOKUP($C21,'MSET pivots'!$B$4:$H$14,$H$2,FALSE)*1000000*$G$6*'MSET pivots'!K$65 -> 4955010 | AA21: =VLOOKUP($C21,'MSET pivots'!$B$4:$H$14,$H$2,FALSE)*1000000*$G$6*'MSET pivots'!L$65 -> 5336158.5 | ... AH21: =VLOOKUP($C21,'MSET pivots'!$B$4:$H$14,$H$2,FALSE)*1000000*$G$6*'MSET pivots'!S$65 -> 8004197.7

Sheet PERT_data
A1: Question | B1: Participant | C1: Lowest_Plausible_Pr | D1: Best_Guess_Pr | E1: Highest_Plausible_Pr | F1: No_value_label
A2: 2a | B2: ='Quant interpretation'!B110 -> A | C2: ='Quant interpretation'!F110 -> 0.225 | D2: ='Quant interpretation'!G110 -> 0.4 | E2: ='Quant interpretation'!H110 -> 0.65
A3: 2a | B3: ='Quant interpretation'!B111 -> B | C3: ='Quant interpretation'!F111 -> 0.01 | D3: ='Quant interpretation'!G111 -> 0.03 | E3: ='Quant interpretation'!H111 -> 0.1
A4: 2a | B4: ='Quant interpretation'!B112 -> C | C4: ='Quant interpretation'!F112 -> 0.03 | D4: ='Quant interpretation'!G112 -> 0.4 | E4: ='Quant interpretation'!H112 -> 1
A5: 2a | B5: ='Quant interpretation'!B113 -> D | C5: ='Quant interpretation'!F113 -> 0.03 | D5: ='Quant interpretation'!G113 -> 0.1 | E5: ='Quant interpretation'!H113 -> 0.4
A6: 2a | B6: ='Quant interpretation'!B114 -> E | C6: ='Quant interpretation'!F114 -> 0.1 | D6: ='Quant interpretation'!G114 -> 0.4 | E6: ='Quant interpretation'!H114 -> 1
A7: 2a | B7: ='Quant interpretation'!B115 -> F | C7: ='Quant interpretation'!F115 -> 0.03 | D7: ='Quant interpretation'!G115 -> 0.225 | E7: ='Quant interpretation'!H115 -> 0.4
A8: 2a | B8: ='Quant interpretation'!B116 -> G | C8: ='Quant interpretation'!F116 -> 0.03 | D8: ='Quant interpretation'!G116 -> 0.1 | E8: ='Quant interpretation'!H116 -> 0.4
A9: 2a | B9: ='Quant interpretation'!B117 -> H | F9: ='Quant interpretation'!I117 -> Error in triples
A10: 2a | B10: ='Quant interpretation'!B118 -> I | F10: ='Quant interpretation'!I118 -> Prefer not to quantify
A11: 2a | B11: ='Quant interpretation'!B119 -> J | F11: ='Quant interpretation'!I119 -> Error in triples
A12: 2a | B12: ='Quant interpretation'!B120 -> K | C12: ='Quant interpretation'!F120 -> 0 | D12: ='Quant interpretation'!G120 -> 0 | E12: ='Quant interpretation'!H120 -> 0.03
A13: 2a | B13: ='Quant interpretation'!B121 -> L | F13: ='Quant interpretation'!I121 -> Error in triples
A14: 2a | B14: ='Quant interpretation'!B122 -> M | C14: ='Quant interpretation'!F122 -> 0.03 | D14: ='Quant interpretation'!G122 -> 0.1 | E14: ='Quant interpretation'!H122 -> 0.225
A15: 2a | B15: ='Quant interpretation'!B123 -> N | C15: ='Quant interpretation'!F123 -> 0 | D15: ='Quant interpretation'!G123 -> 0.03 | E15: ='Quant interpretation'!H123 -> 0.05
A16: 1a | B16: ='Quant interpretation'!C26 -> A | C16: ='Quant interpretation'!D26 -> 37 | D16: ='Quant interpretation'!E26 -> 75 | E16: ='Quant interpretation'!F26 -> 200
A17: 1a | B17: ='Quant interpretation'!C27 -> B | C17: ='Quant interpretation'!D27 -> 5 | D17: ='Quant interpretation'!E27 -> 75 | E17: ='Quant interpretation'!F27 -> 200
A18: 1a | B18: ='Quant interpretation'!C28 -> C | C18: ='Quant interpretation'!D28 -> 5 | D18: ='Quant interpretation'!E28 -> 57 | E18: ='Quant interpretation'!F28 -> 125
A19: 1a | B19: ='Quant interpretation'!C29 -> D | C19: ='Quant interpretation'!D29 -> 0 | D19: ='Quant interpretation'!E29 -> 18 | E19: ='Quant interpretation'!F29 -> 37
A20: 1a | B20: ='Quant interpretation'!C30 -> E | C20: ='Quant interpretation'!D30 -> 150 | D20: ='Quant interpretation'!E30 -> 200 | E20: ='Quant interpretation'!F30 -> 375
A21: 1a | B21: ='Quant interpretation'!C31 -> F | F21: ='Quant interpretation'!G31 -> Prefer not to quantify
A22: 1a | B22: ='Quant interpretation'!C32 -> G | C22: ='Quant interpretation'!D32 -> 18 | D22: ='Quant interpretation'!E32 -> 75 | E22: ='Quant interpretation'!F32 -> 375
A23: 1a | B23: ='Quant interpretation'!C33 -> H | C23: ='Quant interpretation'!D33 -> 5 | D23: ='Quant interpretation'!E33 -> 125 | E23: ='Quant interpretation'!F33 -> 500
A24: 1a | B24: ='Quant interpretation'!C34 -> I | C24: ='Quant interpretation'!D34 -> 125 | D24: ='Quant interpretation'!E34 -> 200 | E24: ='Quant interpretation'!F34 -> 500
A25: 1a | B25: ='Quant interpretation'!C35 -> J | F25: ='Quant interpretation'!G35 -> Error in triples
A26: 1a | B26: ='Quant interpretation'!C36 -> K | C26: ='Quant interpretation'!D36 -> 5 | D26: ='Quant interpretation'!E36 -> 80 | E26: ='Quant interpretation'!F36 -> 375
A27: 1a | B27: ='Quant interpretation'!C37 -> L | F27: ='Quant interpretation'!G37 -> Error in triples
A28: 1a | B28: ='Quant interpretation'!C38 -> M | F28: ='Quant interpretation'!G38 -> Prefer not to quantify
A29: 1a | B29: ='Quant interpretation'!C39 -> N | C29: ='Quant interpretation'!D39 -> 150 | D29: ='Quant interpretation'!E39 -> 200 | E29: ='Quant interpretation'!F39 -> 375

Sheet Analysis >

Sheet Preliminary results
B1: Combines the results of the expert elicitation and the PERT analysis, adjusting for inflation, to prepare for entry into the scenario analysis.
B4: Inputs | C4: Value | D4: Source
B5: UK GDP 2025 (bn) | C5: ='Scenario sets'!C210/1000 -> 4002.5875 | D5: World Bank (2026)
B6: Pakistan GDP 2025 (bn) | C6: ='Scenario sets'!C154/1000 -> 407.30721 | D6: World Bank (2026)
B7: CVF GDP 2025 (bn) | C7: =SUMIF('Scenario sets'!$H$5:$H$221,"Yes",'Scenario sets'!$C$5:$C$221)/1000 -> 4447.704 | D7: World Bank (2026) | F7: 74
B8: G77 + China GDP 2025 (bn) | C8: =SUMIF('Scenario sets'!$G$5:$G$221,"Yes",'Scenario sets'!$C$5:$C$221)/1000 -> 40439.305 | D8: World Bank (2026) | F8: 134 | G8: =(F8-F7) -> 60 | H8: =G8/F7 -> 0.81081081
B9: Global GDP 2025 (bn) | C9: ='Scenario sets'!C2 -> 117147.98 | D9: World Bank (2026)
B10: CVF GDP as % of global 2025 (%) | C10: =C7/C9 -> 0.037966545
B11: G77 + China GDP as % of global 2025 (%) | C11: =C8/C9 -> 0.34519849 | E11: =C11/C10 -> 9.0921755
B13: Section 1 results
B14: From PERT_dist>results | C14: PERT1a_2026-08-24
A15: Question | B15: Distribution | C15: Pooled_Mean | D15: Pooled_Median | E15: Hard_Union_LPP | F15: Hard_Union_HPP | G15: Mixture_5th | H15: Mixture_95th | I15: N_Participants | J15: Lambda | K15: Nsim
A16: 1a | B16: Moment-matched Beta | C16: ='PERT1a_2026-08-24'!C2 -> 129.0634 | D16: ='PERT1a_2026-08-24'!D2 -> 113.59651 | E16: ='PERT1a_2026-08-24'!E2 -> 0 | F16: ='PERT1a_2026-08-24'!F2 -> 500 | G16: ='PERT1a_2026-08-24'!G2 -> 20.510354 | H16: ='PERT1a_2026-08-24'!H2 -> 290.85765 | I16: ='PERT1a_2026-08-24'!I2 -> 10 | J16: ='PERT1a_2026-08-24'!J2 -> 5 | K16: ='PERT1a_2026-08-24'!K2 -> 10000
A17: 1a | B17: Mixture | C17: ='PERT1a_2026-08-24'!C3 -> 129.0634 | D17: ='PERT1a_2026-08-24'!D3 -> 109.11762 | E17: ='PERT1a_2026-08-24'!E3 -> 0 | F17: ='PERT1a_2026-08-24'!F3 -> 500 | G17: ='PERT1a_2026-08-24'!G3 -> 17.422921 | H17: ='PERT1a_2026-08-24'!H3 -> 273.42063 | I17: ='PERT1a_2026-08-24'!I3 -> 10 | J17: ='PERT1a_2026-08-24'!J3 -> 5 | K17: ='PERT1a_2026-08-24'!K3 -> 10000
C18: =C16*Inflation!$D$7 -> 102.48821
C20: Total damages (bn) | D20: Total damages as a % of Pak GDP | E20: Award (inflation adjusted) | F20: Award as a % of Pakistan GDP | G20: Award as a % of UK GDP
B21: Pooled median damages from CC (bn) | C21: =D16 -> 113.59651 | D21: =C21/$C$6 -> 0.27889638
B22: 5th Percentile - (bn) - inflation adjusted to 2019 USD | C22: =G16*Inflation!$D$7 -> 16.287108 | D22: =G16/C6 -> 0.050355981 | E22: =C22*$C$26 -> 0.48861323 | F22: =G16*$C$26/$C$6 -> 0.0015106794 | G22: =G16*$C$26/$C$5 -> 0.00015372821
B23: Pooled median damages from CC (bn) - inflation adjusted to 2019 USD | C23: =C21*Inflation!$D$7 -> 90.206073 | D23: =D21 -> 0.27889638 | E23: =C23*$C$26 -> 2.7061822 | F23: =D16*$C$26/$C$6 -> 0.0083668914 | G23: =D16*$C$26/$C$5 -> 0.00085142304
B24: 95th Percentile - (bn) - inflation adjusted to 2019 USD | C24: =H16*Inflation!$D$7 -> 230.96772 | D24: =H16/C6 -> 0.71409895 | E24: =C24*$C$26 -> 6.9290317 | F24: =H16*$C$26/$C$6 -> 0.021422968 | G24: =H16*$C$26/$C$5 -> 0.0021800222
A26: 1c | B26: UK share of climate harm (median) | C26: ='Quant interpretation'!C57 -> 0.03 | D26: Expert elicitation analysis
C29: Award (bn) | D29: PAK GDP | E29: UK GDP
A30: Section 1 result | B30: Pooled median | C30: =C21*C26 -> 3.4078952 | D30: =C30/$C$6 -> 0.0083668914 | E30: =C30/$C$5 -> 0.00085142304
A31: Section 1 result | B31: Pooled median - inflation adjuted to 2019 USD | C31: =C30*Inflation!$D$7 -> 2.7061822
B33: Section 2 results
B34: From PERT_dist>results
A35: Question | B35: Distribution | C35: Pooled_Mean | D35: Pooled_Median | E35: Hard_Union_LPP | F35: Hard_Union_HPP | G35: Mixture_5th | H35: Mixture_95th | I35: N_Participants | J35: Lambda | K35: Nsim
A36: 2a | B36: Moment-matched Beta | C36: ='PERT2a_2026-08-24'!C2 -> 0.1966749 | D36: ='PERT2a_2026-08-24'!D2 -> 0.13855828 | E36: ='PERT2a_2026-08-24'!E2 -> 0 | F36: ='PERT2a_2026-08-24'!F2 -> 1 | G36: ='PERT2a_2026-08-24'!G2 -> 0.0042975583 | H36: ='PERT2a_2026-08-24'!H2 -> 0.58462564 | I36: ='PERT2a_2026-08-24'!I2 -> 10 | J36: ='PERT2a_2026-08-24'!J2 -> 5 | K36: ='PERT2a_2026-08-24'!K2 -> 10000
A37: 2a | B37: Mixture | C37: ='PERT2a_2026-08-24'!C3 -> 0.1966749 | D37: ='PERT2a_2026-08-24'!D3 -> 0.13379964 | E37: ='PERT2a_2026-08-24'!E3 -> 0 | F37: ='PERT2a_2026-08-24'!F3 -> 1 | G37: ='PERT2a_2026-08-24'!G3 -> 0.0032766649 | H37: ='PERT2a_2026-08-24'!H3 -> 0.56192087 | I37: ='PERT2a_2026-08-24'!I3 -> 10 | J37: ='PERT2a_2026-08-24'!J3 -> 5 | K37: ='PERT2a_2026-08-24'!K3 -> 10000
B41: Scaling | C41: Min | D41: Lower scenario | E41: Central scenario | F41: Upper scenario | G41: Max
B42: Transfers to CVF (bn) - Pooled median | C42: =E$36*$C$7*$D21 -> 0 | D42: =G$36*$C$7*$D21 -> 5.3309 | E42: =D$36*$C$7*$D21 -> 171.87442 | F42: =H$36*$C$7*$D21 -> 725.19802 | G42: =F$36*$C$7*$D21 -> 1240.4485
B43: Transfers to CVF (bn) - Pooled median (inflation adjusted) | C43: =C42*Inflation!$D$7 -> 0 | D43: =D42*Inflation!$D$7 -> 4.2332248 | E43: =E42*Inflation!$D$7 -> 136.4841 | F43: =F42*Inflation!$D$7 -> 575.87391 | G43: =G42*Inflation!$D$7 -> 985.03021
D44: =D43/15 -> 0.28221499 | E44: =E43/15 -> 9.0989397 | F44: =F43/15 -> 38.391594
B45: Transfers to CVF per year (bn) - Pooled median | C45: =C42/15 -> 0 | D45: =D42/15 -> 0.35539333 | E45: =E42/15 -> 11.458295 | F45: =F42/15 -> 48.346535 | G45: =G42/15 -> 82.696569
B46: Transfers to CVF as % of CVF GDP 2025 | C46: =C42/$C$7 -> 0 | D46: =D42/$C$7 -> 0.0011985735 | E46: =E42/$C$7 -> 0.038643404 | F46: =F42/$C$7 -> 0.16304997 | G46: =G42/$C$7 -> 0.27889638
B47: Transfers per yr as % of CVF GDP 2025 | C47: =C46/15 -> 0 | D47: =D46/15 -> 7.9904898e-05 | E47: =E46/15 -> 0.0025762269 | F47: =F46/15 -> 0.010869998 | G47: =G46/15 -> 0.018593092
B50: UK Portion of transfers to CVF (bn) | C50: =C42*$C$26 -> 0 | D50: =D42*$C$26 -> 0.159927 | E50: =E42*$C$26 -> 5.1562327 | F50: =F42*$C$26 -> 21.755941 | G50: =G42*$C$26 -> 37.213456
B51: UK Portion of transfers to CVF as % of GDP 2025 | C51: =C50/$C$5 -> 0 | D51: =D50/$C$5 -> 3.9955903e-05 | E51: =E50/$C$5 -> 0.0012882248 | F51: =F50/$C$5 -> 0.005435469 | G51: =G50/$C$5 -> 0.0092973497
D53: =D45*1000 -> 355.39333
B55: Transfers to G77+C (bn) - Pooled median | C55: =C46*$C$8 -> 0 | D55: =D46*$C$8 -> 48.469478 | E55: =E46*$C$8 -> 1562.7124 | F55: =F46*$C$8 -> 6593.6277 | G55: =G46*$C$8 -> 11278.376
B56: Transfers to G77+C (bn) - Pooled median (inflation adjusted) | C56: =C55*Inflation!$D$7 -> 0 | D56: =D55*Inflation!$D$7 -> 38.489223 | E56: =E55*Inflation!$D$7 -> 1240.9374 | F56: =F55*Inflation!$D$7 -> 5235.9467 | G56: =G55*Inflation!$D$7 -> 8956.0676
B57: Transfers to G77+C (bn/yr) - Pooled median (inflation adjusted) | C57: =C56/15 -> 0 | D57: =D56/15 -> 2.5659482 | E57: =E56/15 -> 82.729157 | F57: =F56/15 -> 349.06311 | G57: =G56/15 -> 597.07117
